Workbook

Sheet Dashboard
B1: DATA INTELLIGENCE DASHBOARD | Customer Transactions
B2: ="Dataset: "&TEXT(MIN('Raw Data'!$B$2:$B$251),"dd-mmm-yyyy")&" to "&TEXT(MAX('Raw Data'!$B$2:$B$251),"dd-mmm-yyyy")&" | Refreshed: "&TEXT(NOW(),"dd-mmm-yyyy hh:mm") -> Dataset: 11-Apr-2024 to 11-Apr-2025 | Refreshed: 15-Oct-2026 11:10 | O2: Criteria helpers
B3: Region | C3: All | D3: Category | E3: All | F3: From | G3: 45393 | H3: To | I3: 45758 | O3: =IF(C3="All","*",C3) -> * | P3: =IF(E3="All","*",E3) -> *
B5: TOTAL REVENUE | D5: ORDERS | F5: UNITS SOLD | H5: AVG ORDER VALUE | J5: ACTIVE CUSTOMERS | L5: ORDERS / CUSTOMER
B6: =SUMIFS('Raw Data'!$N$2:$N$251,'Raw Data'!$K$2:$K$251,$O$3,'Raw Data'!$G$2:$G$251,$P$3,'Raw Data'!$B$2:$B$251,">="&$G$3,'Raw Data'!$B$2:$B$251,"<="&$I$3) -> 229192.47 | D6: =COUNTIFS('Raw Data'!$K$2:$K$251,$O$3,'Raw Data'!$G$2:$G$251,$P$3,'Raw Data'!$B$2:$B$251,">="&$G$3,'Raw Data'!$B$2:$B$251,"<="&$I$3) -> 250 | F6: =SUMIFS('Raw Data'!$H$2:$H$251,'Raw Data'!$K$2:$K$251,$O$3,'Raw Data'!$G$2:$G$251,$P$3,'Raw Data'!$B$2:$B$251,">="&$G$3,'Raw Data'!$B$2:$B$251,"<="&$I$3) -> 753 | H6: =IFERROR(B6/D6,0) -> 916.76988 | J6: =SUMPRODUCT(--(COUNTIFS('Raw Data'!$C$2:$C$251,'Customer Analysis'!$A$23:$A$72,'Raw Data'!$K$2:$K$251,$O$3,'Raw Data'!$G$2:$G$251,$P$3,'Raw Data'!$B$2:$B$251,">="&$G$3,'Raw Data'!$B$2:$B$251,"<="&$I$3)>0)) -> 50 | L6: =IFERROR(D6/J6,0) -> 5
B8: ="Share of all sales: "&TEXT(IFERROR(B6/SUM('Raw Data'!$N$2:$N$251),0),"0.0%") -> Share of all sales: 100.0% | D8: ="Revenue per order "&TEXT(IFERROR(B6/D6,0),"$#,##0") -> Revenue per order $917 | F8: ="Avg "&TEXT(IFERROR(F6/D6,0),"0.0")&" units per order" -> Avg 3.0 units per order | H8: Revenue / Orders | J8: ="of "&COUNTA('Customer Analysis'!$A$23:$A$72)&" total customers" -> of 50 total customers | L8: Purchase frequency
B10: AOV vs OVERALL AVERAGE | D10: LATEST FULL-MONTH GROWTH | F10: REPEAT CUSTOMER RATE | H10: TOP REGION | J10: TOP PRODUCT | L10: TOP CUSTOMER (ALL-TIME)
B11: =IFERROR(H6/(SUM('Raw Data'!$N$2:$N$251)/COUNTA('Raw Data'!$A$2:$A$251))-1,0) -> 0 | D11: ='Sales Analysis'!F71 -> 0.23834149 | F11: ='Customer Analysis'!H4 -> 0.94 | H11: =INDEX(B65:B69,MATCH(MAX(C65:C69),C65:C69,0)) -> East | J11: =INDEX(L65:L74,MATCH(MAX(M65:M74),M65:M74,0)) -> Laptop | L11: ='Customer Analysis'!C9 -> Mark Carter
B13: Selection vs all data | D13: =TEXT('Sales Analysis'!A71,"mmm yyyy")&" vs "&TEXT('Sales Analysis'!A70,"mmm yyyy") -> Mar 2025 vs Feb 2025 | F13: Target: 90%+ (green) | H13: =TEXT(MAX(C65:C69),"$#,##0")&" revenue" -> $59,288 revenue | J13: =TEXT(MAX(M65:M74),"$#,##0")&" revenue" -> $67,499 revenue | L13: =TEXT('Customer Analysis'!D9,"$#,##0")&" revenue" -> $15,660 revenue
B49: Top 5 Customers (all-time) | I49: Payment Mix & Segment
B50: Rank | C50: Customer | E50: Revenue | F50: Orders | G50: % of Total | I50: Payment Method | J50: Revenue | K50: % Share
B51: 1 | C51: ='Customer Analysis'!C9 -> Mark Carter | E51: ='Customer Analysis'!D9 -> 15659.65 | F51: ='Customer Analysis'!E9 -> 12 | G51: ='Customer Analysis'!F9 -> 0.068325325 | I51: ='Sales Analysis'!A22 -> Cash | J51: ='Sales Analysis'!B22 -> 57427.79 | K51: ='Sales Analysis'!F22 -> 0.25056578
B52: 2 | C52: ='Customer Analysis'!C10 -> Edward Mitchell | E52: ='Customer Analysis'!D10 -> 11919.77 | F52: ='Customer Analysis'!E10 -> 6 | G52: ='Customer Analysis'!F10 -> 0.052007686 | I52: ='Sales Analysis'!A23 -> Credit Card | J52: ='Sales Analysis'!B23 -> 61447.96 | K52: ='Sales Analysis'!F23 -> 0.26810636
B53: 3 | C53: ='Customer Analysis'!C11 -> Barbara Young | E53: ='Customer Analysis'!D11 -> 10649.8 | F53: ='Customer Analysis'!E11 -> 5 | G53: ='Customer Analysis'!F11 -> 0.046466623 | I53: ='Sales Analysis'!A24 -> Debit Card | J53: ='Sales Analysis'!B24 -> 52118.31 | K53: ='Sales Analysis'!F24 -> 0.22739975
B54: 4 | C54: ='Customer Analysis'!C12 -> Patricia Moore | E54: ='Customer Analysis'!D12 -> 9799.73 | F54: ='Customer Analysis'!E12 -> 8 | G54: ='Customer Analysis'!F12 -> 0.042757644 | I54: ='Sales Analysis'!A25 -> PayPal | J54: ='Sales Analysis'!B25 -> 58198.41 | K54: ='Sales Analysis'!F25 -> 0.25392811
B55: 5 | C55: ='Customer Analysis'!C13 -> Paul Baker | E55: ='Customer Analysis'!D13 -> 8309.74 | F55: ='Customer Analysis'!E13 -> 8 | G55: ='Customer Analysis'!F13 -> 0.036256601
I56: Segment | J56: Revenue | K56: % Share
I57: ='Sales Analysis'!A30 -> Basic | J57: ='Sales Analysis'!B30 -> 62177.81 | K57: ='Sales Analysis'!F30 -> 0.27129081
I58: ='Sales Analysis'!A31 -> Standard | J58: ='Sales Analysis'!B31 -> 82357.54 | K58: ='Sales Analysis'!F31 -> 0.3593379
I59: ='Sales Analysis'!A32 -> Premium | J59: ='Sales Analysis'!B32 -> 84657.12 | K59: ='Sales Analysis'!F32 -> 0.3693713
B63: Chart data (recalculates with the filters above)
B64: Region | C64: Revenue | E64: Month Start | F64: Month | G64: Revenue | I64: Category | J64: Revenue | L64: Product | M64: Revenue
B65: Central | C65: =SUMIFS('Raw Data'!$N$2:$N$251,'Raw Data'!$K$2:$K$251,B65,'Raw Data'!$G$2:$G$251,$P$3,'Raw Data'!$B$2:$B$251,">="&$G$3,'Raw Data'!$B$2:$B$251,"<="&$I$3) -> 41288.34 | E65: ='Sales Analysis'!$A$60 -> 45383 | F65: =TEXT(E65,"mmm-yy") -> Apr-24 | G65: =SUMIFS('Raw Data'!$N$2:$N$251,'Raw Data'!$K$2:$K$251,$O$3,'Raw Data'!$G$2:$G$251,$P$3,'Raw Data'!$B$2:$B$251,">="&MAX(E65,$G$3),'Raw Data'!$B$2:$B$251,"<="&MIN(EOMONTH(E65,0),$I$3)) -> 20919.33 | I65: Appliances | J65: =SUMIFS('Raw Data'!$N$2:$N$251,'Raw Data'!$G$2:$G$251,I65,'Raw Data'!$K$2:$K$251,$O$3,'Raw Data'!$B$2:$B$251,">="&$G$3,'Raw Data'!$B$2:$B$251,"<="&$I$3) -> 8338.74 | L65: ='Sales Analysis'!$A$37 -> Laptop | M65: =SUMIFS('Raw Data'!$N$2:$N$251,'Raw Data'!$F$2:$F$251,L65,'Raw Data'!$K$2:$K$251,$O$3,'Raw Data'!$G$2:$G$251,$P$3,'Raw Data'!$B$2:$B$251,">="&$G$3,'Raw Data'!$B$2:$B$251,"<="&$I$3) -> 67499.25
B66: East | C66: =SUMIFS('Raw Data'!$N$2:$N$251,'Raw Data'!$K$2:$K$251,B66,'Raw Data'!$G$2:$G$251,$P$3,'Raw Data'!$B$2:$B$251,">="&$G$3,'Raw Data'!$B$2:$B$251,"<="&$I$3) -> 59288.39 | E66: ='Sales Analysis'!$A$61 -> 45413 | F66: =TEXT(E66,"mmm-yy") -> May-24 | G66: =SUMIFS('Raw Data'!$N$2:$N$251,'Raw Data'!$K$2:$K$251,$O$3,'Raw Data'!$G$2:$G$251,$P$3,'Raw Data'!$B$2:$B$251,">="&MAX(E66,$G$3),'Raw Data'!$B$2:$B$251,"<="&MIN(EOMONTH(E66,0),$I$3)) -> 17039.35 | I66: Electronics | J66: =SUMIFS('Raw Data'!$N$2:$N$251,'Raw Data'!$G$2:$G$251,I66,'Raw Data'!$K$2:$K$251,$O$3,'Raw Data'!$B$2:$B$251,">="&$G$3,'Raw Data'!$B$2:$B$251,"<="&$I$3) -> 171756.05 | L66: ='Sales Analysis'!$A$38 -> Smartphone | M66: =SUMIFS('Raw Data'!$N$2:$N$251,'Raw Data'!$F$2:$F$251,L66,'Raw Data'!$K$2:$K$251,$O$3,'Raw Data'!$G$2:$G$251,$P$3,'Raw Data'!$B$2:$B$251,">="&$G$3,'Raw Data'!$B$2:$B$251,"<="&$I$3) -> 67199.04
B67: North | C67: =SUMIFS('Raw Data'!$N$2:$N$251,'Raw Data'!$K$2:$K$251,B67,'Raw Data'!$G$2:$G$251,$P$3,'Raw Data'!$B$2:$B$251,">="&$G$3,'Raw Data'!$B$2:$B$251,"<="&$I$3) -> 50808.31 | E67: ='Sales Analysis'!$A$62 -> 45444 | F67: =TEXT(E67,"mmm-yy") -> Jun-24 | G67: =SUMIFS('Raw Data'!$N$2:$N$251,'Raw Data'!$K$2:$K$251,$O$3,'Raw Data'!$G$2:$G$251,$P$3,'Raw Data'!$B$2:$B$251,">="&MAX(E67,$G$3),'Raw Data'!$B$2:$B$251,"<="&MIN(EOMONTH(E67,0),$I$3)) -> 19299.45 | I67: Furniture | J67: =SUMIFS('Raw Data'!$N$2:$N$251,'Raw Data'!$G$2:$G$251,I67,'Raw Data'!$K$2:$K$251,$O$3,'Raw Data'!$B$2:$B$251,">="&$G$3,'Raw Data'!$B$2:$B$251,"<="&$I$3) -> 49097.68 | L67: ='Sales Analysis'!$A$39 -> Headphones | M67: =SUMIFS('Raw Data'!$N$2:$N$251,'Raw Data'!$F$2:$F$251,L67,'Raw Data'!$K$2:$K$251,$O$3,'Raw Data'!$G$2:$G$251,$P$3,'Raw Data'!$B$2:$B$251,">="&$G$3,'Raw Data'!$B$2:$B$251,"<="&$I$3) -> 7049.53
B68: South | C68: =SUMIFS('Raw Data'!$N$2:$N$251,'Raw Data'!$K$2:$K$251,B68,'Raw Data'!$G$2:$G$251,$P$3,'Raw Data'!$B$2:$B$251,">="&$G$3,'Raw Data'!$B$2:$B$251,"<="&$I$3) -> 36398.75 | E68: ='Sales Analysis'!$A$63 -> 45474 | F68: =TEXT(E68,"mmm-yy") -> Jul-24 | G68: =SUMIFS('Raw Data'!$N$2:$N$251,'Raw Data'!$K$2:$K$251,$O$3,'Raw Data'!$G$2:$G$251,$P$3,'Raw Data'!$B$2:$B$251,">="&MAX(E68,$G$3),'Raw Data'!$B$2:$B$251,"<="&MIN(EOMONTH(E68,0),$I$3)) -> 18479.4 | L68: ='Sales Analysis'!$A$40 -> Coffee Maker | M68: =SUMIFS('Raw Data'!$N$2:$N$251,'Raw Data'!$F$2:$F$251,L68,'Raw Data'!$K$2:$K$251,$O$3,'Raw Data'!$G$2:$G$251,$P$3,'Raw Data'!$B$2:$B$251,">="&$G$3,'Raw Data'!$B$2:$B$251,"<="&$I$3) -> 3119.61
B69: West | C69: =SUMIFS('Raw Data'!$N$2:$N$251,'Raw Data'!$K$2:$K$251,B69,'Raw Data'!$G$2:$G$251,$P$3,'Raw Data'!$B$2:$B$251,">="&$G$3,'Raw Data'!$B$2:$B$251,"<="&$I$3) -> 41408.68 | E69: ='Sales Analysis'!$A$64 -> 45505 | F69: =TEXT(E69,"mmm-yy") -> Aug-24 | G69: =SUMIFS('Raw Data'!$N$2:$N$251,'Raw Data'!$K$2:$K$251,$O$3,'Raw Data'!$G$2:$G$251,$P$3,'Raw Data'!$B$2:$B$251,">="&MAX(E69,$G$3),'Raw Data'!$B$2:$B$251,"<="&MIN(EOMONTH(E69,0),$I$3)) -> 15759.43 | L69: ='Sales Analysis'!$A$41 -> Blender | M69: =SUMIFS('Raw Data'!$N$2:$N$251,'Raw Data'!$F$2:$F$251,L69,'Raw Data'!$K$2:$K$251,$O$3,'Raw Data'!$G$2:$G$251,$P$3,'Raw Data'!$B$2:$B$251,">="&$G$3,'Raw Data'!$B$2:$B$251,"<="&$I$3) -> 5219.13
E70: ='Sales Analysis'!$A$65 -> 45536 | F70: =TEXT(E70,"mmm-yy") -> Sep-24 | G70: =SUMIFS('Raw Data'!$N$2:$N$251,'Raw Data'!$K$2:$K$251,$O$3,'Raw Data'!$G$2:$G$251,$P$3,'Raw Data'!$B$2:$B$251,">="&MAX(E70,$G$3),'Raw Data'!$B$2:$B$251,"<="&MIN(EOMONTH(E70,0),$I$3)) -> 12989.51 | L70: ='Sales Analysis'!$A$42 -> Office Chair | M70: =SUMIFS('Raw Data'!$N$2:$N$251,'Raw Data'!$F$2:$F$251,L70,'Raw Data'!$K$2:$K$251,$O$3,'Raw Data'!$G$2:$G$251,$P$3,'Raw Data'!$B$2:$B$251,">="&$G$3,'Raw Data'!$B$2:$B$251,"<="&$I$3) -> 10399.48
E71: ='Sales Analysis'!$A$66 -> 45566 | F71: =TEXT(E71,"mmm-yy") -> Oct-24 | G71: =SUMIFS('Raw Data'!$N$2:$N$251,'Raw Data'!$K$2:$K$251,$O$3,'Raw Data'!$G$2:$G$251,$P$3,'Raw Data'!$B$2:$B$251,">="&MAX(E71,$G$3),'Raw Data'!$B$2:$B$251,"<="&MIN(EOMONTH(E71,0),$I$3)) -> 20609.52 | L71: ='Sales Analysis'!$A$43 -> Desk | M71: =SUMIFS('Raw Data'!$N$2:$N$251,'Raw Data'!$F$2:$F$251,L71,'Raw Data'!$K$2:$K$251,$O$3,'Raw Data'!$G$2:$G$251,$P$3,'Raw Data'!$B$2:$B$251,">="&$G$3,'Raw Data'!$B$2:$B$251,"<="&$I$3) -> 23399.22
E72: ='Sales Analysis'!$A$67 -> 45597 | F72: =TEXT(E72,"mmm-yy") -> Nov-24 | G72: =SUMIFS('Raw Data'!$N$2:$N$251,'Raw Data'!$K$2:$K$251,$O$3,'Raw Data'!$G$2:$G$251,$P$3,'Raw Data'!$B$2:$B$251,">="&MAX(E72,$G$3),'Raw Data'!$B$2:$B$251,"<="&MIN(EOMONTH(E72,0),$I$3)) -> 12309.44 | L72: ='Sales Analysis'!$A$44 -> Bookshelf | M72: =SUMIFS('Raw Data'!$N$2:$N$251,'Raw Data'!$F$2:$F$251,L72,'Raw Data'!$K$2:$K$251,$O$3,'Raw Data'!$G$2:$G$251,$P$3,'Raw Data'!$B$2:$B$251,">="&$G$3,'Raw Data'!$B$2:$B$251,"<="&$I$3) -> 15298.98
E73: ='Sales Analysis'!$A$68 -> 45627 | F73: =TEXT(E73,"mmm-yy") -> Dec-24 | G73: =SUMIFS('Raw Data'!$N$2:$N$251,'Raw Data'!$K$2:$K$251,$O$3,'Raw Data'!$G$2:$G$251,$P$3,'Raw Data'!$B$2:$B$251,">="&MAX(E73,$G$3),'Raw Data'!$B$2:$B$251,"<="&MIN(EOMONTH(E73,0),$I$3)) -> 23039.3 | L73: ='Sales Analysis'!$A$45 -> Monitor | M73: =SUMIFS('Raw Data'!$N$2:$N$251,'Raw Data'!$F$2:$F$251,L73,'Raw Data'!$K$2:$K$251,$O$3,'Raw Data'!$G$2:$G$251,$P$3,'Raw Data'!$B$2:$B$251,">="&$G$3,'Raw Data'!$B$2:$B$251,"<="&$I$3) -> 21999.12
E74: ='Sales Analysis'!$A$69 -> 45658 | F74: =TEXT(E74,"mmm-yy") -> Jan-25 | G74: =SUMIFS('Raw Data'!$N$2:$N$251,'Raw Data'!$K$2:$K$251,$O$3,'Raw Data'!$G$2:$G$251,$P$3,'Raw Data'!$B$2:$B$251,">="&MAX(E74,$G$3),'Raw Data'!$B$2:$B$251,"<="&MIN(EOMONTH(E74,0),$I$3)) -> 25799.15 | L74: ='Sales Analysis'!$A$46 -> Keyboard | M74: =SUMIFS('Raw Data'!$N$2:$N$251,'Raw Data'!$F$2:$F$251,L74,'Raw Data'!$K$2:$K$251,$O$3,'Raw Data'!$G$2:$G$251,$P$3,'Raw Data'!$B$2:$B$251,">="&$G$3,'Raw Data'!$B$2:$B$251,"<="&$I$3) -> 8009.11
E75: ='Sales Analysis'!$A$70 -> 45689 | F75: =TEXT(E75,"mmm-yy") -> Feb-25 | G75: =SUMIFS('Raw Data'!$N$2:$N$251,'Raw Data'!$K$2:$K$251,$O$3,'Raw Data'!$G$2:$G$251,$P$3,'Raw Data'!$B$2:$B$251,">="&MAX(E75,$G$3),'Raw Data'!$B$2:$B$251,"<="&MIN(EOMONTH(E75,0),$I$3)) -> 16069.38
E76: ='Sales Analysis'!$A$71 -> 45717 | F76: =TEXT(E76,"mmm-yy") -> Mar-25 | G76: =SUMIFS('Raw Data'!$N$2:$N$251,'Raw Data'!$K$2:$K$251,$O$3,'Raw Data'!$G$2:$G$251,$P$3,'Raw Data'!$B$2:$B$251,">="&MAX(E76,$G$3),'Raw Data'!$B$2:$B$251,"<="&MIN(EOMONTH(E76,0),$I$3)) -> 19899.38
E77: ='Sales Analysis'!$A$72 -> 45748 | F77: =TEXT(E77,"mmm-yy") -> Apr-25 | G77: =SUMIFS('Raw Data'!$N$2:$N$251,'Raw Data'!$K$2:$K$251,$O$3,'Raw Data'!$G$2:$G$251,$P$3,'Raw Data'!$B$2:$B$251,">="&MAX(E77,$G$3),'Raw Data'!$B$2:$B$251,"<="&MIN(EOMONTH(E77,0),$I$3)) -> 6979.83

Sheet Executive Charts
B1: EXECUTIVE CHARTS | Customer Transactions Analytics
B2: ="Dataset: "&TEXT(MIN('Raw Data'!$B$2:$B$251),"dd-mmm-yyyy")&" to "&TEXT(MAX('Raw Data'!$B$2:$B$251),"dd-mmm-yyyy") -> Dataset: 11-Apr-2024 to 11-Apr-2025 | T2: << Dashboard
B4: TOTAL REVENUE | F4: AVG ORDER VALUE | J4: UNITS SOLD | N4: ACTIVE CUSTOMERS | R4: REPEAT CUSTOMER RATE
B5: ='Sales Analysis'!B11 -> 229192.47 | F5: ='Sales Analysis'!E11 -> 916.76988 | J5: ='Sales Analysis'!D11 -> 753 | N5: =COUNTA('Customer Analysis'!$A$23:$A$72) -> 50 | R5: ='Customer Analysis'!H4 -> 0.94
B7: ="Across "&TEXT('Sales Analysis'!C11,"#,##0")&" orders" -> Across 250 orders | F7: ="Revenue / orders" -> Revenue / orders | J7: ="Avg "&TEXT('Sales Analysis'!D11/'Sales Analysis'!C11,"0.0")&" units per order" -> Avg 3.0 units per order | N7: ="Top 10 = "&TEXT('Customer Analysis'!F19,"0.0%")&" of revenue" -> Top 10 = 41.0% of revenue | R7: ="Customers with 2+ orders" -> Customers with 2+ orders
B9: 1 REVENUE TREND & MOMENTUM
B46: 2 PRODUCT & CATEGORY MIX
B83: 3 REGIONAL & PAYMENT PERFORMANCE
B120: 4 CUSTOMER INSIGHTS

Sheet Visualizations
A1: Visualizations

Sheet Insights Report
A1: Insights Report - Data Storytelling
B4: Executive Summary
B5: ="Between "&TEXT(MIN('Raw Data'!$B$2:$B$251),"mmm yyyy")&" and "&TEXT(MAX('Raw Data'!$B$2:$B$251),"mmm yyyy")&", "&TEXT('Sales Analysis'!C11,"#,##0")&" orders from "&COUNTA('Customer Analysis'!$A$23:$A$72)&" customers generated "&TEXT('Sales Analysis'!B11,"$#,##0")&" in revenue (average order "&TEXT('Sales Analysis'!E11,"$#,##0")&"). Sales are concentrated in a few products, one category and a small group of high-value customers - which is both the opportunity and the risk." -> Between Apr 2024 and Apr 2025, 250 orders from 50 customers generated $2,29,192 in revenue (average order $917). Sales are concentrated in a few products, one category and a small group of high-value customers - which is both the opportunity and the risk.
B7: Key metric | C7: Value
B8: Total Revenue | C8: ='Sales Analysis'!B11 -> 229192.47
B9: Orders | C9: ='Sales Analysis'!C11 -> 250
B10: Customers | C10: =COUNTA('Customer Analysis'!$A$23:$A$72) -> 50
B11: Avg Order Value | C11: ='Sales Analysis'!E11 -> 916.76988
A13: # | B13: Theme | C13: What the data says | D13: So what - recommendation
A14: 1 | B14: Category mix | C14: =INDEX('Sales Analysis'!$A$15:$A$17,MATCH(MAX('Sales Analysis'!$B$15:$B$17),'Sales Analysis'!$B$15:$B$17,0))&" generates "&TEXT(MAX('Sales Analysis'!$F$15:$F$17),"0.0%")&" of revenue ("&TEXT(MAX('Sales Analysis'!$B$15:$B$17),"$#,##0")&"), while "&INDEX('Sales Analysis'!$A$15:$A$17,MATCH(MIN('Sales Analysis'!$B$15:$B$17),'Sales Analysis'!$B$15:$B$17,0))&" adds only "&TEXT(MIN('Sales Analysis'!$F$15:$F$17),"0.0%")&"." -> Electronics generates 74.9% of revenue ($1,71,756), while Appliances adds only 3.6%. | D14: Protect the electronics franchise (stock, pricing, supplier terms). Lift low-value appliance baskets with bundles and add-on offers.
A15: 2 | B15: Product concentration | C15: ="Top two products by revenue - "&INDEX('Sales Analysis'!$A$37:$A$46,MATCH(LARGE('Sales Analysis'!$B$37:$B$46,1),'Sales Analysis'!$B$37:$B$46,0))&" and "&INDEX('Sales Analysis'!$A$37:$A$46,MATCH(LARGE('Sales Analysis'!$B$37:$B$46,2),'Sales Analysis'!$B$37:$B$46,0))&" - deliver "&TEXT((LARGE('Sales Analysis'!$B$37:$B$46,1)+LARGE('Sales Analysis'!$B$37:$B$46,2))/'Sales Analysis'!B47,"0.0%")&" of revenue from only "&TEXT((INDEX('Sales Analysis'!$C$37:$C$46,MATCH(LARGE('Sales Analysis'!$B$37:$B$46,1),'Sales Analysis'!$B$37:$B$46,0))+INDEX('Sales Analysis'!$C$37:$C$46,MATCH(LARGE('Sales Analysis'!$B$37:$B$46,2),'Sales Analysis'!$B$37:$B$46,0)))/'Sales Analysis'!C47,"0.0%")&" of orders." -> Top two products by revenue - Laptop and Smartphone - deliver 58.8% of revenue from only 22.0% of orders. | D15: Cross-sell accessories (keyboards, monitors, headphones) at checkout for premium devices; monitor stock-outs on the top two SKUs.
A16: 3 | B16: Volume vs value | C16: ="Most frequently ordered product is "&'Names & Lists'!B17&" ("&'Names & Lists'!C17&") but it ranks #"&INDEX('Sales Analysis'!$G$37:$G$46,MATCH('Names & Lists'!B17,'Sales Analysis'!$A$37:$A$46,0))&" by revenue; the highest-revenue product is "&'Names & Lists'!B19&"." -> Most frequently ordered product is Bookshelf (35 orders) but it ranks #5 by revenue; the highest-revenue product is Laptop. | D16: Use high-frequency, lower-ticket items as traffic builders and pair them with high-ticket items to grow basket value.
A17: 4 | B17: Regional performance | C17: ="Best region: "&INDEX('Sales Analysis'!$A$6:$A$10,MATCH(MAX('Sales Analysis'!$B$6:$B$10),'Sales Analysis'!$B$6:$B$10,0))&" ("&TEXT(MAX('Sales Analysis'!$B$6:$B$10),"$#,##0")&", "&TEXT(INDEX('Sales Analysis'!$F$6:$F$10,MATCH(MAX('Sales Analysis'!$B$6:$B$10),'Sales Analysis'!$B$6:$B$10,0)),"0.0%")&" of sales). Weakest: "&INDEX('Sales Analysis'!$A$6:$A$10,MATCH(MIN('Sales Analysis'!$B$6:$B$10),'Sales Analysis'!$B$6:$B$10,0))&" ("&TEXT(MIN('Sales Analysis'!$B$6:$B$10),"$#,##0")&") - a gap of "&TEXT(MAX('Sales Analysis'!$B$6:$B$10)/MIN('Sales Analysis'!$B$6:$B$10)-1,"0%")&"." -> Best region: East ($59,288, 25.9% of sales). Weakest: South ($36,399) - a gap of 63%. | D17: Replicate the best region's playbook; run a diagnostic and targeted campaign in the weakest region before adding spend.
A18: 5 | B18: Customer concentration | C18: ="Top customer "&'Customer Analysis'!C9&" contributes "&TEXT('Customer Analysis'!F9,"0.0%")&" of revenue; the top 10 customers contribute "&TEXT('Customer Analysis'!G18,"0.0%")&". "&'Customer Analysis'!E3&" High-Value customers (top "&TEXT(1-'Customer Analysis'!B3,"0%")&") generate "&TEXT('Customer Analysis'!E5,"0.0%")&" of sales." -> Top customer Mark Carter contributes 6.8% of revenue; the top 10 customers contribute 41.0%. 10 High-Value customers (top 20%) generate 41.0% of sales. | D18: Assign account managers and loyalty perks to High-Value customers; track their order frequency as an early-warning KPI.
A19: 6 | B19: Repeat behaviour | C19: =TEXT('Customer Analysis'!H4,"0%")&" of customers bought more than once ("&'Customer Analysis'!H3&" of "&COUNTA('Customer Analysis'!$A$23:$A$72)&"). Most frequent buyer: "&'Names & Lists'!B25&" with "&'Names & Lists'!C25&"." -> 94% of customers bought more than once (47 of 50). Most frequent buyer: Mark Carter with 12 transactions. | D19: Retention is strong - shift focus from re-activation to increasing spend per visit (upsell, bundles, subscriptions).
A20: 7 | B20: Seasonality | C20: ="Among full months, revenue peaked in "&TEXT(INDEX('Sales Analysis'!$A$61:$A$71,MATCH(MAX('Sales Analysis'!$C$61:$C$71),'Sales Analysis'!$C$61:$C$71,0)),"mmm yyyy")&" ("&TEXT(MAX('Sales Analysis'!$C$61:$C$71),"$#,##0")&") and bottomed in "&TEXT(INDEX('Sales Analysis'!$A$61:$A$71,MATCH(MIN('Sales Analysis'!$C$61:$C$71),'Sales Analysis'!$C$61:$C$71,0)),"mmm yyyy")&" ("&TEXT(MIN('Sales Analysis'!$C$61:$C$71),"$#,##0")&")." -> Among full months, revenue peaked in Jan 2025 ($25,799) and bottomed in Nov 2024 ($12,309). | D20: Plan inventory and promotions around peak months; use targeted offers to lift the slow months. Note first/last month are partial.
A21: 8 | B21: Payment mix | C21: ="Most-used method by revenue: "&INDEX('Sales Analysis'!$A$22:$A$25,MATCH(MAX('Sales Analysis'!$B$22:$B$25),'Sales Analysis'!$B$22:$B$25,0))&" ("&TEXT(MAX('Sales Analysis'!$F$22:$F$25),"0.0%")&"); the spread between top and bottom method is only "&TEXT((MAX('Sales Analysis'!$F$22:$F$25)-MIN('Sales Analysis'!$F$22:$F$25))*100,"0.0")&" percentage points." -> Most-used method by revenue: Credit Card (26.8%); the spread between top and bottom method is only 4.1 percentage points. | D21: No payment dependency risk - keep all four methods; test small incentives on lower-cost rails.
A22: 9 | B22: Regression drivers | C22: ="Order value = "&TEXT(Regression!B18,"$#,##0")&" + "&TEXT(Regression!B19,"$#,##0")&" per extra unit + "&TEXT(Regression!B20,"$#,##0.00")&" per $1 of unit price (R-squared "&TEXT(Regression!B7,"0.00")&"). Monthly trend is "&IF(Regression!E41<0.05,"significant","NOT statistically significant")&" (p = "&TEXT(Regression!E41,"0.00")&")." -> Order value = -$932 + $314 per extra unit + $3.04 per $1 of unit price (R-squared 0.86). Monthly trend is NOT statistically significant (p = 0.41). | D22: Both quantity and price move order value, so volume incentives and premium mix both pay off. Do not extrapolate a trend - demand is seasonal/volatile.
A23: 10 | B23: Data quality | C23: ="Customer_Since holds conflicting dates for "&'Customer Analysis'!H5&" of "&COUNTA('Customer Analysis'!$A$23:$A$72)&" customers; Region and Segment also change between transactions of the same Customer_ID." -> Customer_Since holds conflicting dates for 47 of 50 customers; Region and Segment also change between transactions of the same Customer_ID. | D23: Fix the customer master (one record per customer) before using segment/tenure for decisions; treat current segment cuts as transaction-level.

Sheet Sales Analysis
A1: Sales Analysis
A4: 1. Revenue by Region
A5: Region | B5: Revenue | C5: Orders | D5: Units Sold | E5: Avg Order Value | F5: % of Revenue | G5: Rank
A6: Central | B6: =SUMIFS('Raw Data'!$N$2:$N$251,'Raw Data'!$K$2:$K$251,$A6) -> 41288.34 | C6: =COUNTIFS('Raw Data'!$K$2:$K$251,$A6) -> 54 | D6: =SUMIFS('Raw Data'!$H$2:$H$251,'Raw Data'!$K$2:$K$251,$A6) -> 166 | E6: =IFERROR(B6/C6,0) -> 764.59889 | F6: =B6/$B$11 -> 0.18014702 | G6: =RANK(B6,$B$6:$B$10,0) -> 4
A7: East | B7: =SUMIFS('Raw Data'!$N$2:$N$251,'Raw Data'!$K$2:$K$251,$A7) -> 59288.39 | C7: =COUNTIFS('Raw Data'!$K$2:$K$251,$A7) -> 48 | D7: =SUMIFS('Raw Data'!$H$2:$H$251,'Raw Data'!$K$2:$K$251,$A7) -> 161 | E7: =IFERROR(B7/C7,0) -> 1235.1748 | F7: =B7/$B$11 -> 0.25868385 | G7: =RANK(B7,$B$6:$B$10,0) -> 1
A8: North | B8: =SUMIFS('Raw Data'!$N$2:$N$251,'Raw Data'!$K$2:$K$251,$A8) -> 50808.31 | C8: =COUNTIFS('Raw Data'!$K$2:$K$251,$A8) -> 59 | D8: =SUMIFS('Raw Data'!$H$2:$H$251,'Raw Data'!$K$2:$K$251,$A8) -> 169 | E8: =IFERROR(B8/C8,0) -> 861.1578 | F8: =B8/$B$11 -> 0.22168403 | G8: =RANK(B8,$B$6:$B$10,0) -> 2
A9: South | B9: =SUMIFS('Raw Data'!$N$2:$N$251,'Raw Data'!$K$2:$K$251,$A9) -> 36398.75 | C9: =COUNTIFS('Raw Data'!$K$2:$K$251,$A9) -> 42 | D9: =SUMIFS('Raw Data'!$H$2:$H$251,'Raw Data'!$K$2:$K$251,$A9) -> 125 | E9: =IFERROR(B9/C9,0) -> 866.6369 | F9: =B9/$B$11 -> 0.15881303 | G9: =RANK(B9,$B$6:$B$10,0) -> 5
A10: West | B10: =SUMIFS('Raw Data'!$N$2:$N$251,'Raw Data'!$K$2:$K$251,$A10) -> 41408.68 | C10: =COUNTIFS('Raw Data'!$K$2:$K$251,$A10) -> 47 | D10: =SUMIFS('Raw Data'!$H$2:$H$251,'Raw Data'!$K$2:$K$251,$A10) -> 132 | E10: =IFERROR(B10/C10,0) -> 881.03574 | F10: =B10/$B$11 -> 0.18067208 | G10: =RANK(B10,$B$6:$B$10,0) -> 3
A11: Total | B11: =SUM(B6:B10) -> 229192.47 | C11: =SUM(C6:C10) -> 250 | D11: =SUM(D6:D10) -> 753 | E11: =B11/C11 -> 916.76988 | F11: =SUM(F6:F10) -> 1
A13: 2. Revenue by Category
A14: Category | B14: Revenue | C14: Orders | D14: Units Sold | E14: Avg Order Value | F14: % of Revenue | G14: Rank
A15: Appliances | B15: =SUMIFS('Raw Data'!$N$2:$N$251,'Raw Data'!$G$2:$G$251,$A15) -> 8338.74 | C15: =COUNTIFS('Raw Data'!$G$2:$G$251,$A15) -> 43 | D15: =SUMIFS('Raw Data'!$H$2:$H$251,'Raw Data'!$G$2:$G$251,$A15) -> 126 | E15: =IFERROR(B15/C15,0) -> 193.92419 | F15: =B15/$B$18 -> 0.036383132 | G15: =RANK(B15,$B$15:$B$17,0) -> 3
A16: Electronics | B16: =SUMIFS('Raw Data'!$N$2:$N$251,'Raw Data'!$G$2:$G$251,$A16) -> 171756.05 | C16: =COUNTIFS('Raw Data'!$G$2:$G$251,$A16) -> 131 | D16: =SUMIFS('Raw Data'!$H$2:$H$251,'Raw Data'!$G$2:$G$251,$A16) -> 395 | E16: =IFERROR(B16/C16,0) -> 1311.1149 | F16: =B16/$B$18 -> 0.74939657 | G16: =RANK(B16,$B$15:$B$17,0) -> 1
A17: Furniture | B17: =SUMIFS('Raw Data'!$N$2:$N$251,'Raw Data'!$G$2:$G$251,$A17) -> 49097.68 | C17: =COUNTIFS('Raw Data'!$G$2:$G$251,$A17) -> 76 | D17: =SUMIFS('Raw Data'!$H$2:$H$251,'Raw Data'!$G$2:$G$251,$A17) -> 232 | E17: =IFERROR(B17/C17,0) -> 646.02211 | F17: =B17/$B$18 -> 0.2142203 | G17: =RANK(B17,$B$15:$B$17,0) -> 2
A18: Total | B18: =SUM(B15:B17) -> 229192.47 | C18: =SUM(C15:C17) -> 250 | D18: =SUM(D15:D17) -> 753 | E18: =B18/C18 -> 916.76988 | F18: =SUM(F15:F17) -> 1
A20: 3. Revenue by Payment Method
A21: Payment Method | B21: Revenue | C21: Orders | D21: Units Sold | E21: Avg Order Value | F21: % of Revenue | G21: Rank
A22: Cash | B22: =SUMIFS('Raw Data'!$N$2:$N$251,'Raw Data'!$J$2:$J$251,$A22) -> 57427.79 | C22: =COUNTIFS('Raw Data'!$J$2:$J$251,$A22) -> 76 | D22: =SUMIFS('Raw Data'!$H$2:$H$251,'Raw Data'!$J$2:$J$251,$A22) -> 221 | E22: =IFERROR(B22/C22,0) -> 755.62882 | F22: =B22/$B$26 -> 0.25056578 | G22: =RANK(B22,$B$22:$B$25,0) -> 3
A23: Credit Card | B23: =SUMIFS('Raw Data'!$N$2:$N$251,'Raw Data'!$J$2:$J$251,$A23) -> 61447.96 | C23: =COUNTIFS('Raw Data'!$J$2:$J$251,$A23) -> 68 | D23: =SUMIFS('Raw Data'!$H$2:$H$251,'Raw Data'!$J$2:$J$251,$A23) -> 204 | E23: =IFERROR(B23/C23,0) -> 903.64647 | F23: =B23/$B$26 -> 0.26810636 | G23: =RANK(B23,$B$22:$B$25,0) -> 1
A24: Debit Card | B24: =SUMIFS('Raw Data'!$N$2:$N$251,'Raw Data'!$J$2:$J$251,$A24) -> 52118.31 | C24: =COUNTIFS('Raw Data'!$J$2:$J$251,$A24) -> 54 | D24: =SUMIFS('Raw Data'!$H$2:$H$251,'Raw Data'!$J$2:$J$251,$A24) -> 169 | E24: =IFERROR(B24/C24,0) -> 965.15389 | F24: =B24/$B$26 -> 0.22739975 | G24: =RANK(B24,$B$22:$B$25,0) -> 4
A25: PayPal | B25: =SUMIFS('Raw Data'!$N$2:$N$251,'Raw Data'!$J$2:$J$251,$A25) -> 58198.41 | C25: =COUNTIFS('Raw Data'!$J$2:$J$251,$A25) -> 52 | D25: =SUMIFS('Raw Data'!$H$2:$H$251,'Raw Data'!$J$2:$J$251,$A25) -> 159 | E25: =IFERROR(B25/C25,0) -> 1119.2002 | F25: =B25/$B$26 -> 0.25392811 | G25: =RANK(B25,$B$22:$B$25,0) -> 2
A26: Total | B26: =SUM(B22:B25) -> 229192.47 | C26: =SUM(C22:C25) -> 250 | D26: =SUM(D22:D25) -> 753 | E26: =B26/C26 -> 916.76988 | F26: =SUM(F22:F25) -> 1
A28: 4. Revenue by Customer Segment (as recorded per transaction)
A29: Segment | B29: Revenue | C29: Orders | D29: Units Sold | E29: Avg Order Value | F29: % of Revenue | G29: Rank
A30: Basic | B30: =SUMIFS('Raw Data'!$N$2:$N$251,'Raw Data'!$L$2:$L$251,$A30) -> 62177.81 | C30: =COUNTIFS('Raw Data'!$L$2:$L$251,$A30) -> 74 | D30: =SUMIFS('Raw Data'!$H$2:$H$251,'Raw Data'!$L$2:$L$251,$A30) -> 219 | E30: =IFERROR(B30/C30,0) -> 840.24068 | F30: =B30/$B$33 -> 0.27129081 | G30: =RANK(B30,$B$30:$B$32,0) -> 3
A31: Standard | B31: =SUMIFS('Raw Data'!$N$2:$N$251,'Raw Data'!$L$2:$L$251,$A31) -> 82357.54 | C31: =COUNTIFS('Raw Data'!$L$2:$L$251,$A31) -> 81 | D31: =SUMIFS('Raw Data'!$H$2:$H$251,'Raw Data'!$L$2:$L$251,$A31) -> 246 | E31: =IFERROR(B31/C31,0) -> 1016.7598 | F31: =B31/$B$33 -> 0.3593379 | G31: =RANK(B31,$B$30:$B$32,0) -> 2
A32: Premium | B32: =SUMIFS('Raw Data'!$N$2:$N$251,'Raw Data'!$L$2:$L$251,$A32) -> 84657.12 | C32: =COUNTIFS('Raw Data'!$L$2:$L$251,$A32) -> 95 | D32: =SUMIFS('Raw Data'!$H$2:$H$251,'Raw Data'!$L$2:$L$251,$A32) -> 288 | E32: =IFERROR(B32/C32,0) -> 891.12758 | F32: =B32/$B$33 -> 0.3693713 | G32: =RANK(B32,$B$30:$B$32,0) -> 1
A33: Total | B33: =SUM(B30:B32) -> 229192.47 | C33: =SUM(C30:C32) -> 250 | D33: =SUM(D30:D32) -> 753 | E33: =B33/C33 -> 916.76988 | F33: =SUM(F30:F32) -> 1
A35: 5. Revenue by Product
A36: Product | B36: Revenue | C36: Orders | D36: Units Sold | E36: Avg Order Value | F36: % of Revenue | G36: Rank | H36: Product ID | I36: Category | J36: Abbreviation | K36: Orders Rank
A37: Laptop | B37: =SUMIFS('Raw Data'!$N$2:$N$251,'Raw Data'!$F$2:$F$251,$A37) -> 67499.25 | C37: =COUNTIFS('Raw Data'!$F$2:$F$251,$A37) -> 24 | D37: =SUMIFS('Raw Data'!$H$2:$H$251,'Raw Data'!$F$2:$F$251,$A37) -> 75 | E37: =IFERROR(B37/C37,0) -> 2812.4688 | F37: =B37/$B$47 -> 0.29450902 | G37: =RANK(B37,$B$37:$B$46,0) -> 1 | H37: =INDEX('Raw Data'!$E$2:$E$251,MATCH($A37,'Raw Data'!$F$2:$F$251,0)) -> P001 | I37: =INDEX('Raw Data'!$G$2:$G$251,MATCH($A37,'Raw Data'!$F$2:$F$251,0)) -> Electronics | J37: =IF(ISNUMBER(FIND(" ",$A37)),UPPER(LEFT($A37,1)&MID($A37,FIND(" ",$A37)+1,1)),UPPER(LEFT($A37,3))) -> LAP | K37: =RANK(C37,$C$37:$C$46,0) -> 7
A38: Smartphone | B38: =SUMIFS('Raw Data'!$N$2:$N$251,'Raw Data'!$F$2:$F$251,$A38) -> 67199.04 | C38: =COUNTIFS('Raw Data'!$F$2:$F$251,$A38) -> 31 | D38: =SUMIFS('Raw Data'!$H$2:$H$251,'Raw Data'!$F$2:$F$251,$A38) -> 96 | E38: =IFERROR(B38/C38,0) -> 2167.711 | F38: =B38/$B$47 -> 0.29319916 | G38: =RANK(B38,$B$37:$B$46,0) -> 2 | H38: =INDEX('Raw Data'!$E$2:$E$251,MATCH($A38,'Raw Data'!$F$2:$F$251,0)) -> P002 | I38: =INDEX('Raw Data'!$G$2:$G$251,MATCH($A38,'Raw Data'!$F$2:$F$251,0)) -> Electronics | J38: =IF(ISNUMBER(FIND(" ",$A38)),UPPER(LEFT($A38,1)&MID($A38,FIND(" ",$A38)+1,1)),UPPER(LEFT($A38,3))) -> SMA | K38: =RANK(C38,$C$37:$C$46,0) -> 3
A39: Headphones | B39: =SUMIFS('Raw Data'!$N$2:$N$251,'Raw Data'!$F$2:$F$251,$A39) -> 7049.53 | C39: =COUNTIFS('Raw Data'!$F$2:$F$251,$A39) -> 16 | D39: =SUMIFS('Raw Data'!$H$2:$H$251,'Raw Data'!$F$2:$F$251,$A39) -> 47 | E39: =IFERROR(B39/C39,0) -> 440.59562 | F39: =B39/$B$47 -> 0.030758122 | G39: =RANK(B39,$B$37:$B$46,0) -> 8 | H39: =INDEX('Raw Data'!$E$2:$E$251,MATCH($A39,'Raw Data'!$F$2:$F$251,0)) -> P003 | I39: =INDEX('Raw Data'!$G$2:$G$251,MATCH($A39,'Raw Data'!$F$2:$F$251,0)) -> Electronics | J39: =IF(ISNUMBER(FIND(" ",$A39)),UPPER(LEFT($A39,1)&MID($A39,FIND(" ",$A39)+1,1)),UPPER(LEFT($A39,3))) -> HEA | K39: =RANK(C39,$C$37:$C$46,0) -> 8
A40: Coffee Maker | B40: =SUMIFS('Raw Data'!$N$2:$N$251,'Raw Data'!$F$2:$F$251,$A40) -> 3119.61 | C40: =COUNTIFS('Raw Data'!$F$2:$F$251,$A40) -> 14 | D40: =SUMIFS('Raw Data'!$H$2:$H$251,'Raw Data'!$F$2:$F$251,$A40) -> 39 | E40: =IFERROR(B40/C40,0) -> 222.82929 | F40: =B40/$B$47 -> 0.013611311 | G40: =RANK(B40,$B$37:$B$46,0) -> 10 | H40: =INDEX('Raw Data'!$E$2:$E$251,MATCH($A40,'Raw Data'!$F$2:$F$251,0)) -> P004 | I40: =INDEX('Raw Data'!$G$2:$G$251,MATCH($A40,'Raw Data'!$F$2:$F$251,0)) -> Appliances | J40: =IF(ISNUMBER(FIND(" ",$A40)),UPPER(LEFT($A40,1)&MID($A40,FIND(" ",$A40)+1,1)),UPPER(LEFT($A40,3))) -> CM | K40: =RANK(C40,$C$37:$C$46,0) -> 10
A41: Blender | B41: =SUMIFS('Raw Data'!$N$2:$N$251,'Raw Data'!$F$2:$F$251,$A41) -> 5219.13 | C41: =COUNTIFS('Raw Data'!$F$2:$F$251,$A41) -> 29 | D41: =SUMIFS('Raw Data'!$H$2:$H$251,'Raw Data'!$F$2:$F$251,$A41) -> 87 | E41: =IFERROR(B41/C41,0) -> 179.97 | F41: =B41/$B$47 -> 0.022771821 | G41: =RANK(B41,$B$37:$B$46,0) -> 9 | H41: =INDEX('Raw Data'!$E$2:$E$251,MATCH($A41,'Raw Data'!$F$2:$F$251,0)) -> P005 | I41: =INDEX('Raw Data'!$G$2:$G$251,MATCH($A41,'Raw Data'!$F$2:$F$251,0)) -> Appliances | J41: =IF(ISNUMBER(FIND(" ",$A41)),UPPER(LEFT($A41,1)&MID($A41,FIND(" ",$A41)+1,1)),UPPER(LEFT($A41,3))) -> BLE | K41: =RANK(C41,$C$37:$C$46,0) -> 4
A42: Office Chair | B42: =SUMIFS('Raw Data'!$N$2:$N$251,'Raw Data'!$F$2:$F$251,$A42) -> 10399.48 | C42: =COUNTIFS('Raw Data'!$F$2:$F$251,$A42) -> 15 | D42: =SUMIFS('Raw Data'!$H$2:$H$251,'Raw Data'!$F$2:$F$251,$A42) -> 52 | E42: =IFERROR(B42/C42,0) -> 693.29867 | F42: =B42/$B$47 -> 0.04537444 | G42: =RANK(B42,$B$37:$B$46,0) -> 6 | H42: =INDEX('Raw Data'!$E$2:$E$251,MATCH($A42,'Raw Data'!$F$2:$F$251,0)) -> P006 | I42: =INDEX('Raw Data'!$G$2:$G$251,MATCH($A42,'Raw Data'!$F$2:$F$251,0)) -> Furniture | J42: =IF(ISNUMBER(FIND(" ",$A42)),UPPER(LEFT($A42,1)&MID($A42,FIND(" ",$A42)+1,1)),UPPER(LEFT($A42,3))) -> OC | K42: =RANK(C42,$C$37:$C$46,0) -> 9
A43: Desk | B43: =SUMIFS('Raw Data'!$N$2:$N$251,'Raw Data'!$F$2:$F$251,$A43) -> 23399.22 | C43: =COUNTIFS('Raw Data'!$F$2:$F$251,$A43) -> 26 | D43: =SUMIFS('Raw Data'!$H$2:$H$251,'Raw Data'!$F$2:$F$251,$A43) -> 78 | E43: =IFERROR(B43/C43,0) -> 899.97 | F43: =B43/$B$47 -> 0.10209419 | G43: =RANK(B43,$B$37:$B$46,0) -> 3 | H43: =INDEX('Raw Data'!$E$2:$E$251,MATCH($A43,'Raw Data'!$F$2:$F$251,0)) -> P007 | I43: =INDEX('Raw Data'!$G$2:$G$251,MATCH($A43,'Raw Data'!$F$2:$F$251,0)) -> Furniture | J43: =IF(ISNUMBER(FIND(" ",$A43)),UPPER(LEFT($A43,1)&MID($A43,FIND(" ",$A43)+1,1)),UPPER(LEFT($A43,3))) -> DES | K43: =RANK(C43,$C$37:$C$46,0) -> 5
A44: Bookshelf | B44: =SUMIFS('Raw Data'!$N$2:$N$251,'Raw Data'!$F$2:$F$251,$A44) -> 15298.98 | C44: =COUNTIFS('Raw Data'!$F$2:$F$251,$A44) -> 35 | D44: =SUMIFS('Raw Data'!$H$2:$H$251,'Raw Data'!$F$2:$F$251,$A44) -> 102 | E44: =IFERROR(B44/C44,0) -> 437.11371 | F44: =B44/$B$47 -> 0.066751669 | G44: =RANK(B44,$B$37:$B$46,0) -> 5 | H44: =INDEX('Raw Data'!$E$2:$E$251,MATCH($A44,'Raw Data'!$F$2:$F$251,0)) -> P008 | I44: =INDEX('Raw Data'!$G$2:$G$251,MATCH($A44,'Raw Data'!$F$2:$F$251,0)) -> Furniture | J44: =IF(ISNUMBER(FIND(" ",$A44)),UPPER(LEFT($A44,1)&MID($A44,FIND(" ",$A44)+1,1)),UPPER(LEFT($A44,3))) -> BOO | K44: =RANK(C44,$C$37:$C$46,0) -> 1
A45: Monitor | B45: =SUMIFS('Raw Data'!$N$2:$N$251,'Raw Data'!$F$2:$F$251,$A45) -> 21999.12 | C45: =COUNTIFS('Raw Data'!$F$2:$F$251,$A45) -> 26 | D45: =SUMIFS('Raw Data'!$H$2:$H$251,'Raw Data'!$F$2:$F$251,$A45) -> 88 | E45: =IFERROR(B45/C45,0) -> 846.12 | F45: =B45/$B$47 -> 0.095985352 | G45: =RANK(B45,$B$37:$B$46,0) -> 4 | H45: =INDEX('Raw Data'!$E$2:$E$251,MATCH($A45,'Raw Data'!$F$2:$F$251,0)) -> P009 | I45: =INDEX('Raw Data'!$G$2:$G$251,MATCH($A45,'Raw Data'!$F$2:$F$251,0)) -> Electronics | J45: =IF(ISNUMBER(FIND(" ",$A45)),UPPER(LEFT($A45,1)&MID($A45,FIND(" ",$A45)+1,1)),UPPER(LEFT($A45,3))) -> MON | K45: =RANK(C45,$C$37:$C$46,0) -> 5
A46: Keyboard | B46: =SUMIFS('Raw Data'!$N$2:$N$251,'Raw Data'!$F$2:$F$251,$A46) -> 8009.11 | C46: =COUNTIFS('Raw Data'!$F$2:$F$251,$A46) -> 34 | D46: =SUMIFS('Raw Data'!$H$2:$H$251,'Raw Data'!$F$2:$F$251,$A46) -> 89 | E46: =IFERROR(B46/C46,0) -> 235.56206 | F46: =B46/$B$47 -> 0.034944909 | G46: =RANK(B46,$B$37:$B$46,0) -> 7 | H46: =INDEX('Raw Data'!$E$2:$E$251,MATCH($A46,'Raw Data'!$F$2:$F$251,0)) -> P010 | I46: =INDEX('Raw Data'!$G$2:$G$251,MATCH($A46,'Raw Data'!$F$2:$F$251,0)) -> Electronics | J46: =IF(ISNUMBER(FIND(" ",$A46)),UPPER(LEFT($A46,1)&MID($A46,FIND(" ",$A46)+1,1)),UPPER(LEFT($A46,3))) -> KEY | K46: =RANK(C46,$C$37:$C$46,0) -> 2
A47: Total | B47: =SUM(B37:B46) -> 229192.47 | C47: =SUM(C37:C46) -> 250 | D47: =SUM(D37:D46) -> 753 | E47: =B47/C47 -> 916.76988 | F47: =SUM(F37:F46) -> 1
A49: 6. Region x Category Revenue Matrix (GroupBy cross-tab)
A50: Region | B50: Appliances | C50: Electronics | D50: Furniture | E50: Total
A51: Central | B51: =SUMIFS('Raw Data'!$N$2:$N$251,'Raw Data'!$K$2:$K$251,$A51,'Raw Data'!$G$2:$G$251,B$50) -> 1999.71 | C51: =SUMIFS('Raw Data'!$N$2:$N$251,'Raw Data'!$K$2:$K$251,$A51,'Raw Data'!$G$2:$G$251,C$50) -> 24889.33 | D51: =SUMIFS('Raw Data'!$N$2:$N$251,'Raw Data'!$K$2:$K$251,$A51,'Raw Data'!$G$2:$G$251,D$50) -> 14399.3 | E51: =SUM(B51:D51) -> 41288.34
A52: East | B52: =SUMIFS('Raw Data'!$N$2:$N$251,'Raw Data'!$K$2:$K$251,$A52,'Raw Data'!$G$2:$G$251,B$50) -> 2239.67 | C52: =SUMIFS('Raw Data'!$N$2:$N$251,'Raw Data'!$K$2:$K$251,$A52,'Raw Data'!$G$2:$G$251,C$50) -> 50649.01 | D52: =SUMIFS('Raw Data'!$N$2:$N$251,'Raw Data'!$K$2:$K$251,$A52,'Raw Data'!$G$2:$G$251,D$50) -> 6399.71 | E52: =SUM(B52:D52) -> 59288.39
A53: North | B53: =SUMIFS('Raw Data'!$N$2:$N$251,'Raw Data'!$K$2:$K$251,$A53,'Raw Data'!$G$2:$G$251,B$50) -> 1119.84 | C53: =SUMIFS('Raw Data'!$N$2:$N$251,'Raw Data'!$K$2:$K$251,$A53,'Raw Data'!$G$2:$G$251,C$50) -> 39239.04 | D53: =SUMIFS('Raw Data'!$N$2:$N$251,'Raw Data'!$K$2:$K$251,$A53,'Raw Data'!$G$2:$G$251,D$50) -> 10449.43 | E53: =SUM(B53:D53) -> 50808.31
A54: South | B54: =SUMIFS('Raw Data'!$N$2:$N$251,'Raw Data'!$K$2:$K$251,$A54,'Raw Data'!$G$2:$G$251,B$50) -> 1099.83 | C54: =SUMIFS('Raw Data'!$N$2:$N$251,'Raw Data'!$K$2:$K$251,$A54,'Raw Data'!$G$2:$G$251,C$50) -> 25549.32 | D54: =SUMIFS('Raw Data'!$N$2:$N$251,'Raw Data'!$K$2:$K$251,$A54,'Raw Data'!$G$2:$G$251,D$50) -> 9749.6 | E54: =SUM(B54:D54) -> 36398.75
A55: West | B55: =SUMIFS('Raw Data'!$N$2:$N$251,'Raw Data'!$K$2:$K$251,$A55,'Raw Data'!$G$2:$G$251,B$50) -> 1879.69 | C55: =SUMIFS('Raw Data'!$N$2:$N$251,'Raw Data'!$K$2:$K$251,$A55,'Raw Data'!$G$2:$G$251,C$50) -> 31429.35 | D55: =SUMIFS('Raw Data'!$N$2:$N$251,'Raw Data'!$K$2:$K$251,$A55,'Raw Data'!$G$2:$G$251,D$50) -> 8099.64 | E55: =SUM(B55:D55) -> 41408.68
A56: Total | B56: =SUM(B51:B55) -> 8338.74 | C56: =SUM(C51:C55) -> 171756.05 | D56: =SUM(D51:D55) -> 49097.68 | E56: =SUM(E51:E55) -> 229192.47
A58: 7. Monthly Revenue Trend (EOMONTH-based month buckets)
A59: Month Start | B59: Month End | C59: Revenue | D59: Orders | E59: Units | F59: MoM Growth | G59: Cumulative Revenue | H59: Days of Data | I59: Daily Run-Rate | J59: Month # | K59: Coverage
A60: =DATE(YEAR(MIN('Raw Data'!$B$2:$B$251)),MONTH(MIN('Raw Data'!$B$2:$B$251)),1) -> 45383 | B60: =EOMONTH(A60,0) -> 45412 | C60: =SUMIFS('Raw Data'!$N$2:$N$251,'Raw Data'!$B$2:$B$251,">="&A60,'Raw Data'!$B$2:$B$251,"<="&B60) -> 20919.33 | D60: =COUNTIFS('Raw Data'!$B$2:$B$251,">="&A60,'Raw Data'!$B$2:$B$251,"<="&B60) -> 21 | E60: =SUMIFS('Raw Data'!$H$2:$H$251,'Raw Data'!$B$2:$B$251,">="&A60,'Raw Data'!$B$2:$B$251,"<="&B60) -> 67 | G60: =SUM($C$60:C60) -> 20919.33 | H60: =MIN(B60,MAX('Raw Data'!$B$2:$B$251))-MAX(A60,MIN('Raw Data'!$B$2:$B$251))+1 -> 20 | I60: =C60/H60 -> 1045.9665 | J60: 1 | K60: =IF(AND(A60>=MIN('Raw Data'!$B$2:$B$251),B60<=MAX('Raw Data'!$B$2:$B$251)),"Full","Partial") -> Partial
A61: =EDATE(A60,1) -> 45413 | B61: =EOMONTH(A61,0) -> 45443 | C61: =SUMIFS('Raw Data'!$N$2:$N$251,'Raw Data'!$B$2:$B$251,">="&A61,'Raw Data'!$B$2:$B$251,"<="&B61) -> 17039.35 | D61: =COUNTIFS('Raw Data'!$B$2:$B$251,">="&A61,'Raw Data'!$B$2:$B$251,"<="&B61) -> 19 | E61: =SUMIFS('Raw Data'!$H$2:$H$251,'Raw Data'!$B$2:$B$251,">="&A61,'Raw Data'!$B$2:$B$251,"<="&B61) -> 65 | F61: =IFERROR(C61/C60-1,"") -> -0.18547344 | G61: =SUM($C$60:C61) -> 37958.68 | H61: =MIN(B61,MAX('Raw Data'!$B$2:$B$251))-MAX(A61,MIN('Raw Data'!$B$2:$B$251))+1 -> 31 | I61: =C61/H61 -> 549.65645 | J61: =J60+1 -> 2 | K61: =IF(AND(A61>=MIN('Raw Data'!$B$2:$B$251),B61<=MAX('Raw Data'!$B$2:$B$251)),"Full","Partial") -> Full
A62: =EDATE(A61,1) -> 45444 | B62: =EOMONTH(A62,0) -> 45473 | C62: =SUMIFS('Raw Data'!$N$2:$N$251,'Raw Data'!$B$2:$B$251,">="&A62,'Raw Data'!$B$2:$B$251,"<="&B62) -> 19299.45 | D62: =COUNTIFS('Raw Data'!$B$2:$B$251,">="&A62,'Raw Data'!$B$2:$B$251,"<="&B62) -> 19 | E62: =SUMIFS('Raw Data'!$H$2:$H$251,'Raw Data'!$B$2:$B$251,">="&A62,'Raw Data'!$B$2:$B$251,"<="&B62) -> 55 | F62: =IFERROR(C62/C61-1,"") -> 0.13264004 | G62: =SUM($C$60:C62) -> 57258.13 | H62: =MIN(B62,MAX('Raw Data'!$B$2:$B$251))-MAX(A62,MIN('Raw Data'!$B$2:$B$251))+1 -> 30 | I62: =C62/H62 -> 643.315 | J62: =J61+1 -> 3 | K62: =IF(AND(A62>=MIN('Raw Data'!$B$2:$B$251),B62<=MAX('Raw Data'!$B$2:$B$251)),"Full","Partial") -> Full
A63: =EDATE(A62,1) -> 45474 | B63: =EOMONTH(A63,0) -> 45504 | C63: =SUMIFS('Raw Data'!$N$2:$N$251,'Raw Data'!$B$2:$B$251,">="&A63,'Raw Data'!$B$2:$B$251,"<="&B63) -> 18479.4 | D63: =COUNTIFS('Raw Data'!$B$2:$B$251,">="&A63,'Raw Data'!$B$2:$B$251,"<="&B63) -> 24 | E63: =SUMIFS('Raw Data'!$H$2:$H$251,'Raw Data'!$B$2:$B$251,">="&A63,'Raw Data'!$B$2:$B$251,"<="&B63) -> 60 | F63: =IFERROR(C63/C62-1,"") -> -0.042490848 | G63: =SUM($C$60:C63) -> 75737.53 | H63: =MIN(B63,MAX('Raw Data'!$B$2:$B$251))-MAX(A63,MIN('Raw Data'!$B$2:$B$251))+1 -> 31 | I63: =C63/H63 -> 596.10968 | J63: =J62+1 -> 4 | K63: =IF(AND(A63>=MIN('Raw Data'!$B$2:$B$251),B63<=MAX('Raw Data'!$B$2:$B$251)),"Full","Partial") -> Full
A64: =EDATE(A63,1) -> 45505 | B64: =EOMONTH(A64,0) -> 45535 | C64: =SUMIFS('Raw Data'!$N$2:$N$251,'Raw Data'!$B$2:$B$251,">="&A64,'Raw Data'!$B$2:$B$251,"<="&B64) -> 15759.43 | D64: =COUNTIFS('Raw Data'!$B$2:$B$251,">="&A64,'Raw Data'!$B$2:$B$251,"<="&B64) -> 18 | E64: =SUMIFS('Raw Data'!$H$2:$H$251,'Raw Data'!$B$2:$B$251,">="&A64,'Raw Data'!$B$2:$B$251,"<="&B64) -> 57 | F64: =IFERROR(C64/C63-1,"") -> -0.1471893 | G64: =SUM($C$60:C64) -> 91496.96 | H64: =MIN(B64,MAX('Raw Data'!$B$2:$B$251))-MAX(A64,MIN('Raw Data'!$B$2:$B$251))+1 -> 31 | I64: =C64/H64 -> 508.36871 | J64: =J63+1 -> 5 | K64: =IF(AND(A64>=MIN('Raw Data'!$B$2:$B$251),B64<=MAX('Raw Data'!$B$2:$B$251)),"Full","Partial") -> Full
A65: =EDATE(A64,1) -> 45536 | B65: =EOMONTH(A65,0) -> 45565 | C65: =SUMIFS('Raw Data'!$N$2:$N$251,'Raw Data'!$B$2:$B$251,">="&A65,'Raw Data'!$B$2:$B$251,"<="&B65) -> 12989.51 | D65: =COUNTIFS('Raw Data'!$B$2:$B$251,">="&A65,'Raw Data'!$B$2:$B$251,"<="&B65) -> 19 | E65: =SUMIFS('Raw Data'!$H$2:$H$251,'Raw Data'!$B$2:$B$251,">="&A65,'Raw Data'!$B$2:$B$251,"<="&B65) -> 49 | F65: =IFERROR(C65/C64-1,"") -> -0.1757627 | G65: =SUM($C$60:C65) -> 104486.47 | H65: =MIN(B65,MAX('Raw Data'!$B$2:$B$251))-MAX(A65,MIN('Raw Data'!$B$2:$B$251))+1 -> 30 | I65: =C65/H65 -> 432.98367 | J65: =J64+1 -> 6 | K65: =IF(AND(A65>=MIN('Raw Data'!$B$2:$B$251),B65<=MAX('Raw Data'!$B$2:$B$251)),"Full","Partial") -> Full
A66: =EDATE(A65,1) -> 45566 | B66: =EOMONTH(A66,0) -> 45596 | C66: =SUMIFS('Raw Data'!$N$2:$N$251,'Raw Data'!$B$2:$B$251,">="&A66,'Raw Data'!$B$2:$B$251,"<="&B66) -> 20609.52 | D66: =COUNTIFS('Raw Data'!$B$2:$B$251,">="&A66,'Raw Data'!$B$2:$B$251,"<="&B66) -> 16 | E66: =SUMIFS('Raw Data'!$H$2:$H$251,'Raw Data'!$B$2:$B$251,">="&A66,'Raw Data'!$B$2:$B$251,"<="&B66) -> 48 | F66: =IFERROR(C66/C65-1,"") -> 0.58662798 | G66: =SUM($C$60:C66) -> 125095.99 | H66: =MIN(B66,MAX('Raw Data'!$B$2:$B$251))-MAX(A66,MIN('Raw Data'!$B$2:$B$251))+1 -> 31 | I66: =C66/H66 -> 664.82323 | J66: =J65+1 -> 7 | K66: =IF(AND(A66>=MIN('Raw Data'!$B$2:$B$251),B66<=MAX('Raw Data'!$B$2:$B$251)),"Full","Partial") -> Full
A67: =EDATE(A66,1) -> 45597 | B67: =EOMONTH(A67,0) -> 45626 | C67: =SUMIFS('Raw Data'!$N$2:$N$251,'Raw Data'!$B$2:$B$251,">="&A67,'Raw Data'!$B$2:$B$251,"<="&B67) -> 12309.44 | D67: =COUNTIFS('Raw Data'!$B$2:$B$251,">="&A67,'Raw Data'!$B$2:$B$251,"<="&B67) -> 17 | E67: =SUMIFS('Raw Data'!$H$2:$H$251,'Raw Data'!$B$2:$B$251,">="&A67,'Raw Data'!$B$2:$B$251,"<="&B67) -> 56 | F67: =IFERROR(C67/C66-1,"") -> -0.40273039 | G67: =SUM($C$60:C67) -> 137405.43 | H67: =MIN(B67,MAX('Raw Data'!$B$2:$B$251))-MAX(A67,MIN('Raw Data'!$B$2:$B$251))+1 -> 30 | I67: =C67/H67 -> 410.31467 | J67: =J66+1 -> 8 | K67: =IF(AND(A67>=MIN('Raw Data'!$B$2:$B$251),B67<=MAX('Raw Data'!$B$2:$B$251)),"Full","Partial") -> Full
A68: =EDATE(A67,1) -> 45627 | B68: =EOMONTH(A68,0) -> 45657 | C68: =SUMIFS('Raw Data'!$N$2:$N$251,'Raw Data'!$B$2:$B$251,">="&A68,'Raw Data'!$B$2:$B$251,"<="&B68) -> 23039.3 | D68: =COUNTIFS('Raw Data'!$B$2:$B$251,">="&A68,'Raw Data'!$B$2:$B$251,"<="&B68) -> 25 | E68: =SUMIFS('Raw Data'!$H$2:$H$251,'Raw Data'!$B$2:$B$251,">="&A68,'Raw Data'!$B$2:$B$251,"<="&B68) -> 70 | F68: =IFERROR(C68/C67-1,"") -> 0.87167735 | G68: =SUM($C$60:C68) -> 160444.73 | H68: =MIN(B68,MAX('Raw Data'!$B$2:$B$251))-MAX(A68,MIN('Raw Data'!$B$2:$B$251))+1 -> 31 | I68: =C68/H68 -> 743.20323 | J68: =J67+1 -> 9 | K68: =IF(AND(A68>=MIN('Raw Data'!$B$2:$B$251),B68<=MAX('Raw Data'!$B$2:$B$251)),"Full","Partial") -> Full
A69: =EDATE(A68,1) -> 45658 | B69: =EOMONTH(A69,0) -> 45688 | C69: =SUMIFS('Raw Data'!$N$2:$N$251,'Raw Data'!$B$2:$B$251,">="&A69,'Raw Data'!$B$2:$B$251,"<="&B69) -> 25799.15 | D69: =COUNTIFS('Raw Data'!$B$2:$B$251,">="&A69,'Raw Data'!$B$2:$B$251,"<="&B69) -> 26 | E69: =SUMIFS('Raw Data'!$H$2:$H$251,'Raw Data'!$B$2:$B$251,">="&A69,'Raw Data'!$B$2:$B$251,"<="&B69) -> 85 | F69: =IFERROR(C69/C68-1,"") -> 0.1197888 | G69: =SUM($C$60:C69) -> 186243.88 | H69: =MIN(B69,MAX('Raw Data'!$B$2:$B$251))-MAX(A69,MIN('Raw Data'!$B$2:$B$251))+1 -> 31 | I69: =C69/H69 -> 832.23065 | J69: =J68+1 -> 10 | K69: =IF(AND(A69>=MIN('Raw Data'!$B$2:$B$251),B69<=MAX('Raw Data'!$B$2:$B$251)),"Full","Partial") -> Full
A70: =EDATE(A69,1) -> 45689 | B70: =EOMONTH(A70,0) -> 45716 | C70: =SUMIFS('Raw Data'!$N$2:$N$251,'Raw Data'!$B$2:$B$251,">="&A70,'Raw Data'!$B$2:$B$251,"<="&B70) -> 16069.38 | D70: =COUNTIFS('Raw Data'!$B$2:$B$251,">="&A70,'Raw Data'!$B$2:$B$251,"<="&B70) -> 20 | E70: =SUMIFS('Raw Data'!$H$2:$H$251,'Raw Data'!$B$2:$B$251,">="&A70,'Raw Data'!$B$2:$B$251,"<="&B70) -> 62 | F70: =IFERROR(C70/C69-1,"") -> -0.37713529 | G70: =SUM($C$60:C70) -> 202313.26 | H70: =MIN(B70,MAX('Raw Data'!$B$2:$B$251))-MAX(A70,MIN('Raw Data'!$B$2:$B$251))+1 -> 28 | I70: =C70/H70 -> 573.90643 | J70: =J69+1 -> 11 | K70: =IF(AND(A70>=MIN('Raw Data'!$B$2:$B$251),B70<=MAX('Raw Data'!$B$2:$B$251)),"Full","Partial") -> Full
A71: =EDATE(A70,1) -> 45717 | B71: =EOMONTH(A71,0) -> 45747 | C71: =SUMIFS('Raw Data'!$N$2:$N$251,'Raw Data'!$B$2:$B$251,">="&A71,'Raw Data'!$B$2:$B$251,"<="&B71) -> 19899.38 | D71: =COUNTIFS('Raw Data'!$B$2:$B$251,">="&A71,'Raw Data'!$B$2:$B$251,"<="&B71) -> 19 | E71: =SUMIFS('Raw Data'!$H$2:$H$251,'Raw Data'!$B$2:$B$251,">="&A71,'Raw Data'!$B$2:$B$251,"<="&B71) -> 62 | F71: =IFERROR(C71/C70-1,"") -> 0.23834149 | G71: =SUM($C$60:C71) -> 222212.64 | H71: =MIN(B71,MAX('Raw Data'!$B$2:$B$251))-MAX(A71,MIN('Raw Data'!$B$2:$B$251))+1 -> 31 | I71: =C71/H71 -> 641.91548 | J71: =J70+1 -> 12 | K71: =IF(AND(A71>=MIN('Raw Data'!$B$2:$B$251),B71<=MAX('Raw Data'!$B$2:$B$251)),"Full","Partial") -> Full
A72: =EDATE(A71,1) -> 45748 | B72: =EOMONTH(A72,0) -> 45777 | C72: =SUMIFS('Raw Data'!$N$2:$N$251,'Raw Data'!$B$2:$B$251,">="&A72,'Raw Data'!$B$2:$B$251,"<="&B72) -> 6979.83 | D72: =COUNTIFS('Raw Data'!$B$2:$B$251,">="&A72,'Raw Data'!$B$2:$B$251,"<="&B72) -> 7 | E72: =SUMIFS('Raw Data'!$H$2:$H$251,'Raw Data'!$B$2:$B$251,">="&A72,'Raw Data'!$B$2:$B$251,"<="&B72) -> 17 | F72: =IFERROR(C72/C71-1,"") -> -0.64924385 | G72: =SUM($C$60:C72) -> 229192.47 | H72: =MIN(B72,MAX('Raw Data'!$B$2:$B$251))-MAX(A72,MIN('Raw Data'!$B$2:$B$251))+1 -> 11 | I72: =C72/H72 -> 634.53 | J72: =J71+1 -> 13 | K72: =IF(AND(A72>=MIN('Raw Data'!$B$2:$B$251),B72<=MAX('Raw Data'!$B$2:$B$251)),"Full","Partial") -> Partial
A73: Total | C73: =SUM(C60:C72) -> 229192.47 | D73: =SUM(D60:D72) -> 250 | E73: =SUM(E60:E72) -> 753

Sheet Customer Analysis
A1: Customer Analysis - GroupBy & High-Value Customers
A3: High-Value percentile cut-off | B3: 0.8 | D3: High-Value customers | E3: =COUNTIF($P$23:$P$72,"High-Value") -> 10 | G3: Repeat customers (2+ orders) | H3: =COUNTIF($Q$23:$Q$72,"Repeat") -> 47
A4: High-Value revenue threshold | B4: =PERCENTILE($G$23:$G$72,B3) -> 6557.8 | D4: Revenue from High-Value | E4: =SUMIF($P$23:$P$72,"High-Value",$G$23:$G$72) -> 93867.66 | G4: Repeat customer rate | H4: =H3/COUNTA($A$23:$A$72) -> 0.94
A5: H1 / H2 split date (mid-point of data) | B5: =MIN('Raw Data'!$B$2:$B$251)+ROUND((MAX('Raw Data'!$B$2:$B$251)-MIN('Raw Data'!$B$2:$B$251))/2,0) -> 45576 | D5: % of total revenue | E5: =E4/SUM($G$23:$G$72) -> 0.40955822 | G5: Customers with conflicting "Since" dates | H5: =COUNTIF($M$23:$M$72,"Yes") -> 47
A7: Top 10 Customers by Revenue
A8: Rank | B8: Customer ID | C8: Customer Name | D8: Revenue | E8: Orders | F8: % of Total Revenue | G8: Cumulative % | H8: Tier
A9: 1 | B9: =INDEX($A$23:$A$72,MATCH($A9,$O$23:$O$72,0)) -> CUST025 | C9: =INDEX($B$23:$B$72,MATCH($A9,$O$23:$O$72,0)) -> Mark Carter | D9: =INDEX($G$23:$G$72,MATCH($A9,$O$23:$O$72,0)) -> 15659.65 | E9: =INDEX($E$23:$E$72,MATCH($A9,$O$23:$O$72,0)) -> 12 | F9: =D9/'Sales Analysis'!$B$11 -> 0.068325325 | G9: =SUM($F$9:F9) -> 0.068325325 | H9: =INDEX($P$23:$P$72,MATCH($A9,$O$23:$O$72,0)) -> High-Value
A10: 2 | B10: =INDEX($A$23:$A$72,MATCH($A10,$O$23:$O$72,0)) -> CUST029 | C10: =INDEX($B$23:$B$72,MATCH($A10,$O$23:$O$72,0)) -> Edward Mitchell | D10: =INDEX($G$23:$G$72,MATCH($A10,$O$23:$O$72,0)) -> 11919.77 | E10: =INDEX($E$23:$E$72,MATCH($A10,$O$23:$O$72,0)) -> 6 | F10: =D10/'Sales Analysis'!$B$11 -> 0.052007686 | G10: =SUM($F$9:F10) -> 0.12033301 | H10: =INDEX($P$23:$P$72,MATCH($A10,$O$23:$O$72,0)) -> High-Value
A11: 3 | B11: =INDEX($A$23:$A$72,MATCH($A11,$O$23:$O$72,0)) -> CUST018 | C11: =INDEX($B$23:$B$72,MATCH($A11,$O$23:$O$72,0)) -> Barbara Young | D11: =INDEX($G$23:$G$72,MATCH($A11,$O$23:$O$72,0)) -> 10649.8 | E11: =INDEX($E$23:$E$72,MATCH($A11,$O$23:$O$72,0)) -> 5 | F11: =D11/'Sales Analysis'!$B$11 -> 0.046466623 | G11: =SUM($F$9:F11) -> 0.16679963 | H11: =INDEX($P$23:$P$72,MATCH($A11,$O$23:$O$72,0)) -> High-Value
A12: 4 | B12: =INDEX($A$23:$A$72,MATCH($A12,$O$23:$O$72,0)) -> CUST012 | C12: =INDEX($B$23:$B$72,MATCH($A12,$O$23:$O$72,0)) -> Patricia Moore | D12: =INDEX($G$23:$G$72,MATCH($A12,$O$23:$O$72,0)) -> 9799.73 | E12: =INDEX($E$23:$E$72,MATCH($A12,$O$23:$O$72,0)) -> 8 | F12: =D12/'Sales Analysis'!$B$11 -> 0.042757644 | G12: =SUM($F$9:F12) -> 0.20955728 | H12: =INDEX($P$23:$P$72,MATCH($A12,$O$23:$O$72,0)) -> High-Value
A13: 5 | B13: =INDEX($A$23:$A$72,MATCH($A13,$O$23:$O$72,0)) -> CUST023 | C13: =INDEX($B$23:$B$72,MATCH($A13,$O$23:$O$72,0)) -> Paul Baker | D13: =INDEX($G$23:$G$72,MATCH($A13,$O$23:$O$72,0)) -> 8309.74 | E13: =INDEX($E$23:$E$72,MATCH($A13,$O$23:$O$72,0)) -> 8 | F13: =D13/'Sales Analysis'!$B$11 -> 0.036256601 | G13: =SUM($F$9:F13) -> 0.24581388 | H13: =INDEX($P$23:$P$72,MATCH($A13,$O$23:$O$72,0)) -> High-Value
A14: 6 | B14: =INDEX($A$23:$A$72,MATCH($A14,$O$23:$O$72,0)) -> CUST024 | C14: =INDEX($B$23:$B$72,MATCH($A14,$O$23:$O$72,0)) -> Dorothy Nelson | D14: =INDEX($G$23:$G$72,MATCH($A14,$O$23:$O$72,0)) -> 8269.79 | E14: =INDEX($E$23:$E$72,MATCH($A14,$O$23:$O$72,0)) -> 6 | F14: =D14/'Sales Analysis'!$B$11 -> 0.036082294 | G14: =SUM($F$9:F14) -> 0.28189617 | H14: =INDEX($P$23:$P$72,MATCH($A14,$O$23:$O$72,0)) -> High-Value
A15: 7 | B15: =INDEX($A$23:$A$72,MATCH($A15,$O$23:$O$72,0)) -> CUST026 | C15: =INDEX($B$23:$B$72,MATCH($A15,$O$23:$O$72,0)) -> Karen Hill | D15: =INDEX($G$23:$G$72,MATCH($A15,$O$23:$O$72,0)) -> 8009.77 | E15: =INDEX($E$23:$E$72,MATCH($A15,$O$23:$O$72,0)) -> 8 | F15: =D15/'Sales Analysis'!$B$11 -> 0.034947789 | G15: =SUM($F$9:F15) -> 0.31684396 | H15: =INDEX($P$23:$P$72,MATCH($A15,$O$23:$O$72,0)) -> High-Value
A16: 8 | B16: =INDEX($A$23:$A$72,MATCH($A16,$O$23:$O$72,0)) -> CUST019 | C16: =INDEX($B$23:$B$72,MATCH($A16,$O$23:$O$72,0)) -> Daniel King | D16: =INDEX($G$23:$G$72,MATCH($A16,$O$23:$O$72,0)) -> 7309.8 | E16: =INDEX($E$23:$E$72,MATCH($A16,$O$23:$O$72,0)) -> 7 | F16: =D16/'Sales Analysis'!$B$11 -> 0.031893718 | G16: =SUM($F$9:F16) -> 0.34873768 | H16: =INDEX($P$23:$P$72,MATCH($A16,$O$23:$O$72,0)) -> High-Value
A17: 9 | B17: =INDEX($A$23:$A$72,MATCH($A17,$O$23:$O$72,0)) -> CUST039 | C17: =INDEX($B$23:$B$72,MATCH($A17,$O$23:$O$72,0)) -> Lawrence Reed | D17: =INDEX($G$23:$G$72,MATCH($A17,$O$23:$O$72,0)) -> 6989.77 | E17: =INDEX($E$23:$E$72,MATCH($A17,$O$23:$O$72,0)) -> 8 | F17: =D17/'Sales Analysis'!$B$11 -> 0.030497381 | G17: =SUM($F$9:F17) -> 0.37923506 | H17: =INDEX($P$23:$P$72,MATCH($A17,$O$23:$O$72,0)) -> High-Value
A18: 10 | B18: =INDEX($A$23:$A$72,MATCH($A18,$O$23:$O$72,0)) -> CUST013 | C18: =INDEX($B$23:$B$72,MATCH($A18,$O$23:$O$72,0)) -> Joseph Jackson | D18: =INDEX($G$23:$G$72,MATCH($A18,$O$23:$O$72,0)) -> 6949.84 | E18: =INDEX($E$23:$E$72,MATCH($A18,$O$23:$O$72,0)) -> 5 | F18: =D18/'Sales Analysis'!$B$11 -> 0.03032316 | G18: =SUM($F$9:F18) -> 0.40955822 | H18: =INDEX($P$23:$P$72,MATCH($A18,$O$23:$O$72,0)) -> High-Value
A19: Top 10 | D19: =SUM(D9:D18) -> 93867.66 | E19: =SUM(E9:E18) -> 73 | F19: =SUM(F9:F18) -> 0.40955822
A21: Customer Master (one row per customer) - GroupBy by Customer_ID
A22: Customer ID | B22: Customer Name | C22: Initials | D22: Short Code | E22: Orders | F22: Units | G22: Revenue | H22: Avg Order Value | I22: First Purchase | J22: Last Purchase | K22: Customer Since (earliest) | L22: Tenure (Yrs, to TODAY) | M22: Since-date Conflict? | N22: Revenue Rank | O22: Unique Rank (tie-break) | P22: Value Tier | Q22: Repeat? | R22: Orders Unique Rank | S22: Active H1 | T22: Active H2 | U22: H1 Seq | V22: H2 Seq | W22: Days Since Last Purchase
A23: CUST001 | B23: =INDEX('Raw Data'!$D$2:$D$251,MATCH($A23,'Raw Data'!$C$2:$C$251,0)) -> John Smith | C23: =UPPER(LEFT(B23,1)&MID(B23,FIND(" ",B23)+1,1)) -> JS | D23: =UPPER(LEFT(B23,1)&MID(B23,FIND(" ",B23)+1,3))&"-"&TEXT(VALUE(RIGHT(A23,3)),"000") -> JSMI-001 | E23: =COUNTIF('Raw Data'!$C$2:$C$251,$A23) -> 1 | F23: =SUMIF('Raw Data'!$C$2:$C$251,$A23,'Raw Data'!$H$2:$H$251) -> 4 | G23: =SUMIF('Raw Data'!$C$2:$C$251,$A23,'Raw Data'!$N$2:$N$251) -> 599.96 | H23: =IFERROR(G23/E23,0) -> 599.96 | I23: =_xlfn.MINIFS('Raw Data'!$B$2:$B$251,'Raw Data'!$C$2:$C$251,$A23) -> 45740 | J23: =_xlfn.MAXIFS('Raw Data'!$B$2:$B$251,'Raw Data'!$C$2:$C$251,$A23) -> 45740 | K23: =_xlfn.MINIFS('Raw Data'!$M$2:$M$251,'Raw Data'!$C$2:$C$251,$A23) -> 44560 | L23: =DATEDIF(K23,TODAY(),"Y") -> 4 | M23: =IF(_xlfn.MAXIFS('Raw Data'!$M$2:$M$251,'Raw Data'!$C$2:$C$251,$A23)-_xlfn.MINIFS('Raw Data'!$M$2:$M$251,'Raw Data'!$C$2:$C$251,$A23)>0,"Yes","No") -> No | N23: =RANK(G23,$G$23:$G$72,0) -> 47 | O23: =N23+COUNTIF($N$23:N23,N23)-1 -> 47 | P23: =IF(G23>=$B$4,"High-Value","Standard") -> Standard | Q23: =IF(E23>1,"Repeat","One-time") -> One-time | R23: =RANK(E23,$E$23:$E$72,0)+COUNTIF($E$23:E23,E23)-1 -> 48 | S23: =IF(COUNTIFS('Raw Data'!$C$2:$C$251,$A23,'Raw Data'!$B$2:$B$251,"<="&$B$5)>0,1,0) -> 0 | T23: =IF(COUNTIFS('Raw Data'!$C$2:$C$251,$A23,'Raw Data'!$B$2:$B$251,">"&$B$5)>0,1,0) -> 1 | U23: =IF(S23=1,SUM($S$23:S23),"") | V23: =IF(T23=1,SUM($T$23:T23),"") -> 1 | W23: =TODAY()-J23 -> 570
A24: CUST002 | B24: =INDEX('Raw Data'!$D$2:$D$251,MATCH($A24,'Raw Data'!$C$2:$C$251,0)) -> Emma Wilson | C24: =UPPER(LEFT(B24,1)&MID(B24,FIND(" ",B24)+1,1)) -> EW | D24: =UPPER(LEFT(B24,1)&MID(B24,FIND(" ",B24)+1,3))&"-"&TEXT(VALUE(RIGHT(A24,3)),"000") -> EWIL-002 | E24: =COUNTIF('Raw Data'!$C$2:$C$251,$A24) -> 5 | F24: =SUMIF('Raw Data'!$C$2:$C$251,$A24,'Raw Data'!$H$2:$H$251) -> 12 | G24: =SUMIF('Raw Data'!$C$2:$C$251,$A24,'Raw Data'!$N$2:$N$251) -> 1229.88 | H24: =IFERROR(G24/E24,0) -> 245.976 | I24: =_xlfn.MINIFS('Raw Data'!$B$2:$B$251,'Raw Data'!$C$2:$C$251,$A24) -> 45430 | J24: =_xlfn.MAXIFS('Raw Data'!$B$2:$B$251,'Raw Data'!$C$2:$C$251,$A24) -> 45737 | K24: =_xlfn.MINIFS('Raw Data'!$M$2:$M$251,'Raw Data'!$C$2:$C$251,$A24) -> 44748 | L24: =DATEDIF(K24,TODAY(),"Y") -> 4 | M24: =IF(_xlfn.MAXIFS('Raw Data'!$M$2:$M$251,'Raw Data'!$C$2:$C$251,$A24)-_xlfn.MINIFS('Raw Data'!$M$2:$M$251,'Raw Data'!$C$2:$C$251,$A24)>0,"Yes","No") -> Yes | N24: =RANK(G24,$G$23:$G$72,0) -> 44 | O24: =N24+COUNTIF($N$23:N24,N24)-1 -> 44 | P24: =IF(G24>=$B$4,"High-Value","Standard") -> Standard | Q24: =IF(E24>1,"Repeat","One-time") -> Repeat | R24: =RANK(E24,$E$23:$E$72,0)+COUNTIF($E$23:E24,E24)-1 -> 19 | S24: =IF(COUNTIFS('Raw Data'!$C$2:$C$251,$A24,'Raw Data'!$B$2:$B$251,"<="&$B$5)>0,1,0) -> 1 | T24: =IF(COUNTIFS('Raw Data'!$C$2:$C$251,$A24,'Raw Data'!$B$2:$B$251,">"&$B$5)>0,1,0) -> 1 | U24: =IF(S24=1,SUM($S$23:S24),"") -> 1 | V24: =IF(T24=1,SUM($T$23:T24),"") -> 2 | W24: =TODAY()-J24 -> 573
A25: CUST003 | B25: =INDEX('Raw Data'!$D$2:$D$251,MATCH($A25,'Raw Data'!$C$2:$C$251,0)) -> Michael Brown | C25: =UPPER(LEFT(B25,1)&MID(B25,FIND(" ",B25)+1,1)) -> MB | D25: =UPPER(LEFT(B25,1)&MID(B25,FIND(" ",B25)+1,3))&"-"&TEXT(VALUE(RIGHT(A25,3)),"000") -> MBRO-003 | E25: =COUNTIF('Raw Data'!$C$2:$C$251,$A25) -> 9 | F25: =SUMIF('Raw Data'!$C$2:$C$251,$A25,'Raw Data'!$H$2:$H$251) -> 26 | G25: =SUMIF('Raw Data'!$C$2:$C$251,$A25,'Raw Data'!$N$2:$N$251) -> 6169.74 | H25: =IFERROR(G25/E25,0) -> 685.52667 | I25: =_xlfn.MINIFS('Raw Data'!$B$2:$B$251,'Raw Data'!$C$2:$C$251,$A25) -> 45400 | J25: =_xlfn.MAXIFS('Raw Data'!$B$2:$B$251,'Raw Data'!$C$2:$C$251,$A25) -> 45707 | K25: =_xlfn.MINIFS('Raw Data'!$M$2:$M$251,'Raw Data'!$C$2:$C$251,$A25) -> 44422 | L25: =DATEDIF(K25,TODAY(),"Y") -> 5 | M25: =IF(_xlfn.MAXIFS('Raw Data'!$M$2:$M$251,'Raw Data'!$C$2:$C$251,$A25)-_xlfn.MINIFS('Raw Data'!$M$2:$M$251,'Raw Data'!$C$2:$C$251,$A25)>0,"Yes","No") -> Yes | N25: =RANK(G25,$G$23:$G$72,0) -> 14 | O25: =N25+COUNTIF($N$23:N25,N25)-1 -> 14 | P25: =IF(G25>=$B$4,"High-Value","Standard") -> Standard | Q25: =IF(E25>1,"Repeat","One-time") -> Repeat | R25: =RANK(E25,$E$23:$E$72,0)+COUNTIF($E$23:E25,E25)-1 -> 2 | S25: =IF(COUNTIFS('Raw Data'!$C$2:$C$251,$A25,'Raw Data'!$B$2:$B$251,"<="&$B$5)>0,1,0) -> 1 | T25: =IF(COUNTIFS('Raw Data'!$C$2:$C$251,$A25,'Raw Data'!$B$2:$B$251,">"&$B$5)>0,1,0) -> 1 | U25: =IF(S25=1,SUM($S$23:S25),"") -> 2 | V25: =IF(T25=1,SUM($T$23:T25),"") -> 3 | W25: =TODAY()-J25 -> 603
A26: CUST004 | B26: =INDEX('Raw Data'!$D$2:$D$251,MATCH($A26,'Raw Data'!$C$2:$C$251,0)) -> Sarah Davis | C26: =UPPER(LEFT(B26,1)&MID(B26,FIND(" ",B26)+1,1)) -> SD | D26: =UPPER(LEFT(B26,1)&MID(B26,FIND(" ",B26)+1,3))&"-"&TEXT(VALUE(RIGHT(A26,3)),"000") -> SDAV-004 | E26: =COUNTIF('Raw Data'!$C$2:$C$251,$A26) -> 5 | F26: =SUMIF('Raw Data'!$C$2:$C$251,$A26,'Raw Data'!$H$2:$H$251) -> 19 | G26: =SUMIF('Raw Data'!$C$2:$C$251,$A26,'Raw Data'!$N$2:$N$251) -> 5499.81 | H26: =IFERROR(G26/E26,0) -> 1099.962 | I26: =_xlfn.MINIFS('Raw Data'!$B$2:$B$251,'Raw Data'!$C$2:$C$251,$A26) -> 45446 | J26: =_xlfn.MAXIFS('Raw Data'!$B$2:$B$251,'Raw Data'!$C$2:$C$251,$A26) -> 45619 | K26: =_xlfn.MINIFS('Raw Data'!$M$2:$M$251,'Raw Data'!$C$2:$C$251,$A26) -> 44458 | L26: =DATEDIF(K26,TODAY(),"Y") -> 5 | M26: =IF(_xlfn.MAXIFS('Raw Data'!$M$2:$M$251,'Raw Data'!$C$2:$C$251,$A26)-_xlfn.MINIFS('Raw Data'!$M$2:$M$251,'Raw Data'!$C$2:$C$251,$A26)>0,"Yes","No") -> Yes | N26: =RANK(G26,$G$23:$G$72,0) -> 19 | O26: =N26+COUNTIF($N$23:N26,N26)-1 -> 19 | P26: =IF(G26>=$B$4,"High-Value","Standard") -> Standard | Q26: =IF(E26>1,"Repeat","One-time") -> Repeat | R26: =RANK(E26,$E$23:$E$72,0)+COUNTIF($E$23:E26,E26)-1 -> 20 | S26: =IF(COUNTIFS('Raw Data'!$C$2:$C$251,$A26,'Raw Data'!$B$2:$B$251,"<="&$B$5)>0,1,0) -> 1 | T26: =IF(COUNTIFS('Raw Data'!$C$2:$C$251,$A26,'Raw Data'!$B$2:$B$251,">"&$B$5)>0,1,0) -> 1 | U26: =IF(S26=1,SUM($S$23:S26),"") -> 3 | V26: =IF(T26=1,SUM($T$23:T26),"") -> 4 | W26: =TODAY()-J26 -> 691
A27: CUST005 | B27: =INDEX('Raw Data'!$D$2:$D$251,MATCH($A27,'Raw Data'!$C$2:$C$251,0)) -> James Johnson | C27: =UPPER(LEFT(B27,1)&MID(B27,FIND(" ",B27)+1,1)) -> JJ | D27: =UPPER(LEFT(B27,1)&MID(B27,FIND(" ",B27)+1,3))&"-"&TEXT(VALUE(RIGHT(A27,3)),"000") -> JJOH-005 | E27: =COUNTIF('Raw Data'!$C$2:$C$251,$A27) -> 1 | F27: =SUMIF('Raw Data'!$C$2:$C$251,$A27,'Raw Data'!$H$2:$H$251) -> 3 | G27: =SUMIF('Raw Data'!$C$2:$C$251,$A27,'Raw Data'!$N$2:$N$251) -> 179.97 | H27: =IFERROR(G27/E27,0) -> 179.97 | I27: =_xlfn.MINIFS('Raw Data'!$B$2:$B$251,'Raw Data'!$C$2:$C$251,$A27) -> 45635 | J27: =_xlfn.MAXIFS('Raw Data'!$B$2:$B$251,'Raw Data'!$C$2:$C$251,$A27) -> 45635 | K27: =_xlfn.MINIFS('Raw Data'!$M$2:$M$251,'Raw Data'!$C$2:$C$251,$A27) -> 45052 | L27: =DATEDIF(K27,TODAY(),"Y") -> 3 | M27: =IF(_xlfn.MAXIFS('Raw Data'!$M$2:$M$251,'Raw Data'!$C$2:$C$251,$A27)-_xlfn.MINIFS('Raw Data'!$M$2:$M$251,'Raw Data'!$C$2:$C$251,$A27)>0,"Yes","No") -> No | N27: =RANK(G27,$G$23:$G$72,0) -> 50 | O27: =N27+COUNTIF($N$23:N27,N27)-1 -> 50 | P27: =IF(G27>=$B$4,"High-Value","Standard") -> Standard | Q27: =IF(E27>1,"Repeat","One-time") -> One-time | R27: =RANK(E27,$E$23:$E$72,0)+COUNTIF($E$23:E27,E27)-1 -> 49 | S27: =IF(COUNTIFS('Raw Data'!$C$2:$C$251,$A27,'Raw Data'!$B$2:$B$251,"<="&$B$5)>0,1,0) -> 0 | T27: =IF(COUNTIFS('Raw Data'!$C$2:$C$251,$A27,'Raw Data'!$B$2:$B$251,">"&$B$5)>0,1,0) -> 1 | U27: =IF(S27=1,SUM($S$23:S27),"") | V27: =IF(T27=1,SUM($T$23:T27),"") -> 5 | W27: =TODAY()-J27 -> 675
A28: CUST006 | B28: =INDEX('Raw Data'!$D$2:$D$251,MATCH($A28,'Raw Data'!$C$2:$C$251,0)) -> Lisa Anderson | C28: =UPPER(LEFT(B28,1)&MID(B28,FIND(" ",B28)+1,1)) -> LA | D28: =UPPER(LEFT(B28,1)&MID(B28,FIND(" ",B28)+1,3))&"-"&TEXT(VALUE(RIGHT(A28,3)),"000") -> LAND-006 | E28: =COUNTIF('Raw Data'!$C$2:$C$251,$A28) -> 5 | F28: =SUMIF('Raw Data'!$C$2:$C$251,$A28,'Raw Data'!$H$2:$H$251) -> 20 | G28: =SUMIF('Raw Data'!$C$2:$C$251,$A28,'Raw Data'!$N$2:$N$251) -> 2039.8 | H28: =IFERROR(G28/E28,0) -> 407.96 | I28: =_xlfn.MINIFS('Raw Data'!$B$2:$B$251,'Raw Data'!$C$2:$C$251,$A28) -> 45428 | J28: =_xlfn.MAXIFS('Raw Data'!$B$2:$B$251,'Raw Data'!$C$2:$C$251,$A28) -> 45676 | K28: =_xlfn.MINIFS('Raw Data'!$M$2:$M$251,'Raw Data'!$C$2:$C$251,$A28) -> 44579 | L28: =DATEDIF(K28,TODAY(),"Y") -> 4 | M28: =IF(_xlfn.MAXIFS('Raw Data'!$M$2:$M$251,'Raw Data'!$C$2:$C$251,$A28)-_xlfn.MINIFS('Raw Data'!$M$2:$M$251,'Raw Data'!$C$2:$C$251,$A28)>0,"Yes","No") -> Yes | N28: =RANK(G28,$G$23:$G$72,0) -> 36 | O28: =N28+COUNTIF($N$23:N28,N28)-1 -> 36 | P28: =IF(G28>=$B$4,"High-Value","Standard") -> Standard | Q28: =IF(E28>1,"Repeat","One-time") -> Repeat | R28: =RANK(E28,$E$23:$E$72,0)+COUNTIF($E$23:E28,E28)-1 -> 21 | S28: =IF(COUNTIFS('Raw Data'!$C$2:$C$251,$A28,'Raw Data'!$B$2:$B$251,"<="&$B$5)>0,1,0) -> 1 | T28: =IF(COUNTIFS('Raw Data'!$C$2:$C$251,$A28,'Raw Data'!$B$2:$B$251,">"&$B$5)>0,1,0) -> 1 | U28: =IF(S28=1,SUM($S$23:S28),"") -> 4 | V28: =IF(T28=1,SUM($T$23:T28),"") -> 6 | W28: =TODAY()-J28 -> 634
A29: CUST007 | B29: =INDEX('Raw Data'!$D$2:$D$251,MATCH($A29,'Raw Data'!$C$2:$C$251,0)) -> David Martinez | C29: =UPPER(LEFT(B29,1)&MID(B29,FIND(" ",B29)+1,1)) -> DM | D29: =UPPER(LEFT(B29,1)&MID(B29,FIND(" ",B29)+1,3))&"-"&TEXT(VALUE(RIGHT(A29,3)),"000") -> DMAR-007 | E29: =COUNTIF('Raw Data'!$C$2:$C$251,$A29) -> 6 | F29: =SUMIF('Raw Data'!$C$2:$C$251,$A29,'Raw Data'!$H$2:$H$251) -> 16 | G29: =SUMIF('Raw Data'!$C$2:$C$251,$A29,'Raw Data'!$N$2:$N$251) -> 1809.84 | H29: =IFERROR(G29/E29,0) -> 301.64 | I29: =_xlfn.MINIFS('Raw Data'!$B$2:$B$251,'Raw Data'!$C$2:$C$251,$A29) -> 45476 | J29: =_xlfn.MAXIFS('Raw Data'!$B$2:$B$251,'Raw Data'!$C$2:$C$251,$A29) -> 45648 | K29: =_xlfn.MINIFS('Raw Data'!$M$2:$M$251,'Raw Data'!$C$2:$C$251,$A29) -> 44522 | L29: =DATEDIF(K29,TODAY(),"Y") -> 4 | M29: =IF(_xlfn.MAXIFS('Raw Data'!$M$2:$M$251,'Raw Data'!$C$2:$C$251,$A29)-_xlfn.MINIFS('Raw Data'!$M$2:$M$251,'Raw Data'!$C$2:$C$251,$A29)>0,"Yes","No") -> Yes | N29: =RANK(G29,$G$23:$G$72,0) -> 39 | O29: =N29+COUNTIF($N$23:N29,N29)-1 -> 39 | P29: =IF(G29>=$B$4,"High-Value","Standard") -> Standard | Q29: =IF(E29>1,"Repeat","One-time") -> Repeat | R29: =RANK(E29,$E$23:$E$72,0)+COUNTIF($E$23:E29,E29)-1 -> 10 | S29: =IF(COUNTIFS('Raw Data'!$C$2:$C$251,$A29,'Raw Data'!$B$2:$B$251,"<="&$B$5)>0,1,0) -> 1 | T29: =IF(COUNTIFS('Raw Data'!$C$2:$C$251,$A29,'Raw Data'!$B$2:$B$251,">"&$B$5)>0,1,0) -> 1 | U29: =IF(S29=1,SUM($S$23:S29),"") -> 5 | V29: =IF(T29=1,SUM($T$23:T29),"") -> 7 | W29: =TODAY()-J29 -> 662
A30: CUST008 | B30: =INDEX('Raw Data'!$D$2:$D$251,MATCH($A30,'Raw Data'!$C$2:$C$251,0)) -> Jennifer Taylor | C30: =UPPER(LEFT(B30,1)&MID(B30,FIND(" ",B30)+1,1)) -> JT | D30: =UPPER(LEFT(B30,1)&MID(B30,FIND(" ",B30)+1,3))&"-"&TEXT(VALUE(RIGHT(A30,3)),"000") -> JTAY-008 | E30: =COUNTIF('Raw Data'!$C$2:$C$251,$A30) -> 4 | F30: =SUMIF('Raw Data'!$C$2:$C$251,$A30,'Raw Data'!$H$2:$H$251) -> 15 | G30: =SUMIF('Raw Data'!$C$2:$C$251,$A30,'Raw Data'!$N$2:$N$251) -> 4739.85 | H30: =IFERROR(G30/E30,0) -> 1184.9625 | I30: =_xlfn.MINIFS('Raw Data'!$B$2:$B$251,'Raw Data'!$C$2:$C$251,$A30) -> 45440 | J30: =_xlfn.MAXIFS('Raw Data'!$B$2:$B$251,'Raw Data'!$C$2:$C$251,$A30) -> 45635 | K30: =_xlfn.MINIFS('Raw Data'!$M$2:$M$251,'Raw Data'!$C$2:$C$251,$A30) -> 44407 | L30: =DATEDIF(K30,TODAY(),"Y") -> 5 | M30: =IF(_xlfn.MAXIFS('Raw Data'!$M$2:$M$251,'Raw Data'!$C$2:$C$251,$A30)-_xlfn.MINIFS('Raw Data'!$M$2:$M$251,'Raw Data'!$C$2:$C$251,$A30)>0,"Yes","No") -> Yes | N30: =RANK(G30,$G$23:$G$72,0) -> 24 | O30: =N30+COUNTIF($N$23:N30,N30)-1 -> 24 | P30: =IF(G30>=$B$4,"High-Value","Standard") -> Standard | Q30: =IF(E30>1,"Repeat","One-time") -> Repeat | R30: =RANK(E30,$E$23:$E$72,0)+COUNTIF($E$23:E30,E30)-1 -> 30 | S30: =IF(COUNTIFS('Raw Data'!$C$2:$C$251,$A30,'Raw Data'!$B$2:$B$251,"<="&$B$5)>0,1,0) -> 1 | T30: =IF(COUNTIFS('Raw Data'!$C$2:$C$251,$A30,'Raw Data'!$B$2:$B$251,">"&$B$5)>0,1,0) -> 1 | U30: =IF(S30=1,SUM($S$23:S30),"") -> 6 | V30: =IF(T30=1,SUM($T$23:T30),"") -> 8 | W30: =TODAY()-J30 -> 675
A31: CUST009 | B31: =INDEX('Raw Data'!$D$2:$D$251,MATCH($A31,'Raw Data'!$C$2:$C$251,0)) -> Robert Thomas | C31: =UPPER(LEFT(B31,1)&MID(B31,FIND(" ",B31)+1,1)) -> RT | D31: =UPPER(LEFT(B31,1)&MID(B31,FIND(" ",B31)+1,3))&"-"&TEXT(VALUE(RIGHT(A31,3)),"000") -> RTHO-009 | E31: =COUNTIF('Raw Data'!$C$2:$C$251,$A31) -> 5 | F31: =SUMIF('Raw Data'!$C$2:$C$251,$A31,'Raw Data'!$H$2:$H$251) -> 10 | G31: =SUMIF('Raw Data'!$C$2:$C$251,$A31,'Raw Data'!$N$2:$N$251) -> 3509.9 | H31: =IFERROR(G31/E31,0) -> 701.98 | I31: =_xlfn.MINIFS('Raw Data'!$B$2:$B$251,'Raw Data'!$C$2:$C$251,$A31) -> 45405 | J31: =_xlfn.MAXIFS('Raw Data'!$B$2:$B$251,'Raw Data'!$C$2:$C$251,$A31) -> 45756 | K31: =_xlfn.MINIFS('Raw Data'!$M$2:$M$251,'Raw Data'!$C$2:$C$251,$A31) -> 44395 | L31: =DATEDIF(K31,TODAY(),"Y") -> 5 | M31: =IF(_xlfn.MAXIFS('Raw Data'!$M$2:$M$251,'Raw Data'!$C$2:$C$251,$A31)-_xlfn.MINIFS('Raw Data'!$M$2:$M$251,'Raw Data'!$C$2:$C$251,$A31)>0,"Yes","No") -> Yes | N31: =RANK(G31,$G$23:$G$72,0) -> 32 | O31: =N31+COUNTIF($N$23:N31,N31)-1 -> 32 | P31: =IF(G31>=$B$4,"High-Value","Standard") -> Standard | Q31: =IF(E31>1,"Repeat","One-time") -> Repeat | R31: =RANK(E31,$E$23:$E$72,0)+COUNTIF($E$23:E31,E31)-1 -> 22 | S31: =IF(COUNTIFS('Raw Data'!$C$2:$C$251,$A31,'Raw Data'!$B$2:$B$251,"<="&$B$5)>0,1,0) -> 1 | T31: =IF(COUNTIFS('Raw Data'!$C$2:$C$251,$A31,'Raw Data'!$B$2:$B$251,">"&$B$5)>0,1,0) -> 1 | U31: =IF(S31=1,SUM($S$23:S31),"") -> 7 | V31: =IF(T31=1,SUM($T$23:T31),"") -> 9 | W31: =TODAY()-J31 -> 554
A32: CUST010 | B32: =INDEX('Raw Data'!$D$2:$D$251,MATCH($A32,'Raw Data'!$C$2:$C$251,0)) -> Maria Garcia | C32: =UPPER(LEFT(B32,1)&MID(B32,FIND(" ",B32)+1,1)) -> MG | D32: =UPPER(LEFT(B32,1)&MID(B32,FIND(" ",B32)+1,3))&"-"&TEXT(VALUE(RIGHT(A32,3)),"000") -> MGAR-010 | E32: =COUNTIF('Raw Data'!$C$2:$C$251,$A32) -> 4 | F32: =SUMIF('Raw Data'!$C$2:$C$251,$A32,'Raw Data'!$H$2:$H$251) -> 7 | G32: =SUMIF('Raw Data'!$C$2:$C$251,$A32,'Raw Data'!$N$2:$N$251) -> 1909.93 | H32: =IFERROR(G32/E32,0) -> 477.4825 | I32: =_xlfn.MINIFS('Raw Data'!$B$2:$B$251,'Raw Data'!$C$2:$C$251,$A32) -> 45410 | J32: =_xlfn.MAXIFS('Raw Data'!$B$2:$B$251,'Raw Data'!$C$2:$C$251,$A32) -> 45604 | K32: =_xlfn.MINIFS('Raw Data'!$M$2:$M$251,'Raw Data'!$C$2:$C$251,$A32) -> 44579 | L32: =DATEDIF(K32,TODAY(),"Y") -> 4 | M32: =IF(_xlfn.MAXIFS('Raw Data'!$M$2:$M$251,'Raw Data'!$C$2:$C$251,$A32)-_xlfn.MINIFS('Raw Data'!$M$2:$M$251,'Raw Data'!$C$2:$C$251,$A32)>0,"Yes","No") -> Yes | N32: =RANK(G32,$G$23:$G$72,0) -> 38 | O32: =N32+COUNTIF($N$23:N32,N32)-1 -> 38 | P32: =IF(G32>=$B$4,"High-Value","Standard") -> Standard | Q32: =IF(E32>1,"Repeat","One-time") -> Repeat | R32: =RANK(E32,$E$23:$E$72,0)+COUNTIF($E$23:E32,E32)-1 -> 31 | S32: =IF(COUNTIFS('Raw Data'!$C$2:$C$251,$A32,'Raw Data'!$B$2:$B$251,"<="&$B$5)>0,1,0) -> 1 | T32: =IF(COUNTIFS('Raw Data'!$C$2:$C$251,$A32,'Raw Data'!$B$2:$B$251,">"&$B$5)>0,1,0) -> 1 | U32: =IF(S32=1,SUM($S$23:S32),"") -> 8 | V32: =IF(T32=1,SUM($T$23:T32),"") -> 10 | W32: =TODAY()-J32 -> 706
A33: CUST011 | B33: =INDEX('Raw Data'!$D$2:$D$251,MATCH($A33,'Raw Data'!$C$2:$C$251,0)) -> William White | C33: =UPPER(LEFT(B33,1)&MID(B33,FIND(" ",B33)+1,1)) -> WW | D33: =UPPER(LEFT(B33,1)&MID(B33,FIND(" ",B33)+1,3))&"-"&TEXT(VALUE(RIGHT(A33,3)),"000") -> WWHI-011 | E33: =COUNTIF('Raw Data'!$C$2:$C$251,$A33) -> 3 | F33: =SUMIF('Raw Data'!$C$2:$C$251,$A33,'Raw Data'!$H$2:$H$251) -> 9 | G33: =SUMIF('Raw Data'!$C$2:$C$251,$A33,'Raw Data'!$N$2:$N$251) -> 4749.91 | H33: =IFERROR(G33/E33,0) -> 1583.3033 | I33: =_xlfn.MINIFS('Raw Data'!$B$2:$B$251,'Raw Data'!$C$2:$C$251,$A33) -> 45554 | J33: =_xlfn.MAXIFS('Raw Data'!$B$2:$B$251,'Raw Data'!$C$2:$C$251,$A33) -> 45686 | K33: =_xlfn.MINIFS('Raw Data'!$M$2:$M$251,'Raw Data'!$C$2:$C$251,$A33) -> 44482 | L33: =DATEDIF(K33,TODAY(),"Y") -> 5 | M33: =IF(_xlfn.MAXIFS('Raw Data'!$M$2:$M$251,'Raw Data'!$C$2:$C$251,$A33)-_xlfn.MINIFS('Raw Data'!$M$2:$M$251,'Raw Data'!$C$2:$C$251,$A33)>0,"Yes","No") -> Yes | N33: =RANK(G33,$G$23:$G$72,0) -> 23 | O33: =N33+COUNTIF($N$23:N33,N33)-1 -> 23 | P33: =IF(G33>=$B$4,"High-Value","Standard") -> Standard | Q33: =IF(E33>1,"Repeat","One-time") -> Repeat | R33: =RANK(E33,$E$23:$E$72,0)+COUNTIF($E$23:E33,E33)-1 -> 40 | S33: =IF(COUNTIFS('Raw Data'!$C$2:$C$251,$A33,'Raw Data'!$B$2:$B$251,"<="&$B$5)>0,1,0) -> 1 | T33: =IF(COUNTIFS('Raw Data'!$C$2:$C$251,$A33,'Raw Data'!$B$2:$B$251,">"&$B$5)>0,1,0) -> 1 | U33: =IF(S33=1,SUM($S$23:S33),"") -> 9 | V33: =IF(T33=1,SUM($T$23:T33),"") -> 11 | W33: =TODAY()-J33 -> 624
A34: CUST012 | B34: =INDEX('Raw Data'!$D$2:$D$251,MATCH($A34,'Raw Data'!$C$2:$C$251,0)) -> Patricia Moore | C34: =UPPER(LEFT(B34,1)&MID(B34,FIND(" ",B34)+1,1)) -> PM | D34: =UPPER(LEFT(B34,1)&MID(B34,FIND(" ",B34)+1,3))&"-"&TEXT(VALUE(RIGHT(A34,3)),"000") -> PMOO-012 | E34: =COUNTIF('Raw Data'!$C$2:$C$251,$A34) -> 8 | F34: =SUMIF('Raw Data'!$C$2:$C$251,$A34,'Raw Data'!$H$2:$H$251) -> 27 | G34: =SUMIF('Raw Data'!$C$2:$C$251,$A34,'Raw Data'!$N$2:$N$251) -> 9799.73 | H34: =IFERROR(G34/E34,0) -> 1224.9662 | I34: =_xlfn.MINIFS('Raw Data'!$B$2:$B$251,'Raw Data'!$C$2:$C$251,$A34) -> 45413 | J34: =_xlfn.MAXIFS('Raw Data'!$B$2:$B$251,'Raw Data'!$C$2:$C$251,$A34) -> 45607 | K34: =_xlfn.MINIFS('Raw Data'!$M$2:$M$251,'Raw Data'!$C$2:$C$251,$A34) -> 44409 | L34: =DATEDIF(K34,TODAY(),"Y") -> 5 | M34: =IF(_xlfn.MAXIFS('Raw Data'!$M$2:$M$251,'Raw Data'!$C$2:$C$251,$A34)-_xlfn.MINIFS('Raw Data'!$M$2:$M$251,'Raw Data'!$C$2:$C$251,$A34)>0,"Yes","No") -> Yes | N34: =RANK(G34,$G$23:$G$72,0) -> 4 | O34: =N34+COUNTIF($N$23:N34,N34)-1 -> 4 | P34: =IF(G34>=$B$4,"High-Value","Standard") -> High-Value | Q34: =IF(E34>1,"Repeat","One-time") -> Repeat | R34: =RANK(E34,$E$23:$E$72,0)+COUNTIF($E$23:E34,E34)-1 -> 4 | S34: =IF(COUNTIFS('Raw Data'!$C$2:$C$251,$A34,'Raw Data'!$B$2:$B$251,"<="&$B$5)>0,1,0) -> 1 | T34: =IF(COUNTIFS('Raw Data'!$C$2:$C$251,$A34,'Raw Data'!$B$2:$B$251,">"&$B$5)>0,1,0) -> 1 | U34: =IF(S34=1,SUM($S$23:S34),"") -> 10 | V34: =IF(T34=1,SUM($T$23:T34),"") -> 12 | W34: =TODAY()-J34 -> 703
... A72: CUST050 | B72: =INDEX('Raw Data'!$D$2:$D$251,MATCH($A72,'Raw Data'!$C$2:$C$251,0)) -> Julie Foster | C72: =UPPER(LEFT(B72,1)&MID(B72,FIND(" ",B72)+1,1)) -> JF | D72: =UPPER(LEFT(B72,1)&MID(B72,FIND(" ",B72)+1,3))&"-"&TEXT(VALUE(RIGHT(A72,3)),"000") -> JFOS-050 | E72: =COUNTIF('Raw Data'!$C$2:$C$251,$A72) -> 1 | F72: =SUMIF('Raw Data'!$C$2:$C$251,$A72,'Raw Data'!$H$2:$H$251) -> 4 | G72: =SUMIF('Raw Data'!$C$2:$C$251,$A72,'Raw Data'!$N$2:$N$251) -> 239.96 | H72: =IFERROR(G72/E72,0) -> 239.96 | I72: =_xlfn.MINIFS('Raw Data'!$B$2:$B$251,'Raw Data'!$C$2:$C$251,$A72) -> 45452 | J72: =_xlfn.MAXIFS('Raw Data'!$B$2:$B$251,'Raw Data'!$C$2:$C$251,$A72) -> 45452 | K72: =_xlfn.MINIFS('Raw Data'!$M$2:$M$251,'Raw Data'!$C$2:$C$251,$A72) -> 44435 | L72: =DATEDIF(K72,TODAY(),"Y") -> 5 | M72: =IF(_xlfn.MAXIFS('Raw Data'!$M$2:$M$251,'Raw Data'!$C$2:$C$251,$A72)-_xlfn.MINIFS('Raw Data'!$M$2:$M$251,'Raw Data'!$C$2:$C$251,$A72)>0,"Yes","No") -> No | N72: =RANK(G72,$G$23:$G$72,0) -> 49 | O72: =N72+COUNTIF($N$23:N72,N72)-1 -> 49 | P72: =IF(G72>=$B$4,"High-Value","Standard") -> Standard | Q72: =IF(E72>1,"Repeat","One-time") -> One-time | R72: =RANK(E72,$E$23:$E$72,0)+COUNTIF($E$23:E72,E72)-1 -> 50 | S72: =IF(COUNTIFS('Raw Data'!$C$2:$C$251,$A72,'Raw Data'!$B$2:$B$251,"<="&$B$5)>0,1,0) -> 1 | T72: =IF(COUNTIFS('Raw Data'!$C$2:$C$251,$A72,'Raw Data'!$B$2:$B$251,">"&$B$5)>0,1,0) -> 0 | U72: =IF(S72=1,SUM($S$23:S72),"") -> 46 | V72: =IF(T72=1,SUM($T$23:T72),"") | W72: =TODAY()-J72 -> 858

Sheet Names & Lists
A1: Names & Lists - Frequent Products, Repeating Names, List Comparison, Abbreviations
A4: 1. Most Frequently Purchased Product (COUNTIF / SUMIF on Raw Data) | H4: 4. Abbreviations with TEXT / string functions
A5: Product | B5: Orders (count) | C5: Units | D5: Revenue | E5: Orders Rank | H5: Product | I5: Abbreviation | J5: Category Code
A6: ='Sales Analysis'!$A$37 -> Laptop | B6: =COUNTIF('Raw Data'!$F$2:$F$251,A6) -> 24 | C6: =SUMIF('Raw Data'!$F$2:$F$251,A6,'Raw Data'!$H$2:$H$251) -> 75 | D6: =SUMIF('Raw Data'!$F$2:$F$251,A6,'Raw Data'!$N$2:$N$251) -> 67499.25 | E6: =RANK(B6,$B$6:$B$15,0) -> 7 | H6: ='Sales Analysis'!$A$37 -> Laptop | I6: ='Sales Analysis'!$J$37 -> LAP | J6: =UPPER(LEFT('Sales Analysis'!$I$37,3)) -> ELE
A7: ='Sales Analysis'!$A$38 -> Smartphone | B7: =COUNTIF('Raw Data'!$F$2:$F$251,A7) -> 31 | C7: =SUMIF('Raw Data'!$F$2:$F$251,A7,'Raw Data'!$H$2:$H$251) -> 96 | D7: =SUMIF('Raw Data'!$F$2:$F$251,A7,'Raw Data'!$N$2:$N$251) -> 67199.04 | E7: =RANK(B7,$B$6:$B$15,0) -> 3 | H7: ='Sales Analysis'!$A$38 -> Smartphone | I7: ='Sales Analysis'!$J$38 -> SMA | J7: =UPPER(LEFT('Sales Analysis'!$I$38,3)) -> ELE
A8: ='Sales Analysis'!$A$39 -> Headphones | B8: =COUNTIF('Raw Data'!$F$2:$F$251,A8) -> 16 | C8: =SUMIF('Raw Data'!$F$2:$F$251,A8,'Raw Data'!$H$2:$H$251) -> 47 | D8: =SUMIF('Raw Data'!$F$2:$F$251,A8,'Raw Data'!$N$2:$N$251) -> 7049.53 | E8: =RANK(B8,$B$6:$B$15,0) -> 8 | H8: ='Sales Analysis'!$A$39 -> Headphones | I8: ='Sales Analysis'!$J$39 -> HEA | J8: =UPPER(LEFT('Sales Analysis'!$I$39,3)) -> ELE
A9: ='Sales Analysis'!$A$40 -> Coffee Maker | B9: =COUNTIF('Raw Data'!$F$2:$F$251,A9) -> 14 | C9: =SUMIF('Raw Data'!$F$2:$F$251,A9,'Raw Data'!$H$2:$H$251) -> 39 | D9: =SUMIF('Raw Data'!$F$2:$F$251,A9,'Raw Data'!$N$2:$N$251) -> 3119.61 | E9: =RANK(B9,$B$6:$B$15,0) -> 10 | H9: ='Sales Analysis'!$A$40 -> Coffee Maker | I9: ='Sales Analysis'!$J$40 -> CM | J9: =UPPER(LEFT('Sales Analysis'!$I$40,3)) -> APP
A10: ='Sales Analysis'!$A$41 -> Blender | B10: =COUNTIF('Raw Data'!$F$2:$F$251,A10) -> 29 | C10: =SUMIF('Raw Data'!$F$2:$F$251,A10,'Raw Data'!$H$2:$H$251) -> 87 | D10: =SUMIF('Raw Data'!$F$2:$F$251,A10,'Raw Data'!$N$2:$N$251) -> 5219.13 | E10: =RANK(B10,$B$6:$B$15,0) -> 4 | H10: ='Sales Analysis'!$A$41 -> Blender | I10: ='Sales Analysis'!$J$41 -> BLE | J10: =UPPER(LEFT('Sales Analysis'!$I$41,3)) -> APP
A11: ='Sales Analysis'!$A$42 -> Office Chair | B11: =COUNTIF('Raw Data'!$F$2:$F$251,A11) -> 15 | C11: =SUMIF('Raw Data'!$F$2:$F$251,A11,'Raw Data'!$H$2:$H$251) -> 52 | D11: =SUMIF('Raw Data'!$F$2:$F$251,A11,'Raw Data'!$N$2:$N$251) -> 10399.48 | E11: =RANK(B11,$B$6:$B$15,0) -> 9 | H11: ='Sales Analysis'!$A$42 -> Office Chair | I11: ='Sales Analysis'!$J$42 -> OC | J11: =UPPER(LEFT('Sales Analysis'!$I$42,3)) -> FUR
A12: ='Sales Analysis'!$A$43 -> Desk | B12: =COUNTIF('Raw Data'!$F$2:$F$251,A12) -> 26 | C12: =SUMIF('Raw Data'!$F$2:$F$251,A12,'Raw Data'!$H$2:$H$251) -> 78 | D12: =SUMIF('Raw Data'!$F$2:$F$251,A12,'Raw Data'!$N$2:$N$251) -> 23399.22 | E12: =RANK(B12,$B$6:$B$15,0) -> 5 | H12: ='Sales Analysis'!$A$43 -> Desk | I12: ='Sales Analysis'!$J$43 -> DES | J12: =UPPER(LEFT('Sales Analysis'!$I$43,3)) -> FUR
A13: ='Sales Analysis'!$A$44 -> Bookshelf | B13: =COUNTIF('Raw Data'!$F$2:$F$251,A13) -> 35 | C13: =SUMIF('Raw Data'!$F$2:$F$251,A13,'Raw Data'!$H$2:$H$251) -> 102 | D13: =SUMIF('Raw Data'!$F$2:$F$251,A13,'Raw Data'!$N$2:$N$251) -> 15298.98 | E13: =RANK(B13,$B$6:$B$15,0) -> 1 | H13: ='Sales Analysis'!$A$44 -> Bookshelf | I13: ='Sales Analysis'!$J$44 -> BOO | J13: =UPPER(LEFT('Sales Analysis'!$I$44,3)) -> FUR
A14: ='Sales Analysis'!$A$45 -> Monitor | B14: =COUNTIF('Raw Data'!$F$2:$F$251,A14) -> 26 | C14: =SUMIF('Raw Data'!$F$2:$F$251,A14,'Raw Data'!$H$2:$H$251) -> 88 | D14: =SUMIF('Raw Data'!$F$2:$F$251,A14,'Raw Data'!$N$2:$N$251) -> 21999.12 | E14: =RANK(B14,$B$6:$B$15,0) -> 5 | H14: ='Sales Analysis'!$A$45 -> Monitor | I14: ='Sales Analysis'!$J$45 -> MON | J14: =UPPER(LEFT('Sales Analysis'!$I$45,3)) -> ELE
A15: ='Sales Analysis'!$A$46 -> Keyboard | B15: =COUNTIF('Raw Data'!$F$2:$F$251,A15) -> 34 | C15: =SUMIF('Raw Data'!$F$2:$F$251,A15,'Raw Data'!$H$2:$H$251) -> 89 | D15: =SUMIF('Raw Data'!$F$2:$F$251,A15,'Raw Data'!$N$2:$N$251) -> 8009.11 | E15: =RANK(B15,$B$6:$B$15,0) -> 2 | H15: ='Sales Analysis'!$A$46 -> Keyboard | I15: ='Sales Analysis'!$J$46 -> KEY | J15: =UPPER(LEFT('Sales Analysis'!$I$46,3)) -> ELE
A17: Most frequently ordered product | B17: =INDEX($A$6:$A$15,MATCH(MAX($B$6:$B$15),$B$6:$B$15,0)) -> Bookshelf | C17: =MAX($B$6:$B$15)&" orders" -> 35 orders
A18: Most units sold | B18: =INDEX($A$6:$A$15,MATCH(MAX($C$6:$C$15),$C$6:$C$15,0)) -> Bookshelf | C18: =TEXT(MAX($C$6:$C$15),"#,##0")&" units" -> 102 units | H18: Region | I18: Code | J18: Rule
A19: Highest revenue product | B19: =INDEX($A$6:$A$15,MATCH(MAX($D$6:$D$15),$D$6:$D$15,0)) -> Laptop | C19: =TEXT(MAX($D$6:$D$15),"$#,##0") -> $67,499 | H19: ='Sales Analysis'!$A$6 -> Central | I19: =UPPER(LEFT(H19,3)) -> CEN | J19: UPPER(LEFT(x,3))
H20: ='Sales Analysis'!$A$7 -> East | I20: =UPPER(LEFT(H20,3)) -> EAS | J20: UPPER(LEFT(x,3))
A21: 2. Repeating Names (repeat-buyer analysis) | H21: ='Sales Analysis'!$A$8 -> North | I21: =UPPER(LEFT(H21,3)) -> NOR | J21: UPPER(LEFT(x,3))
A22: Distinct customer names | B22: =SUMPRODUCT(1/COUNTIF('Raw Data'!$D$2:$D$251,'Raw Data'!$D$2:$D$251)) -> 50 | H22: ='Sales Analysis'!$A$9 -> South | I22: =UPPER(LEFT(H22,3)) -> SOU | J22: UPPER(LEFT(x,3))
A23: Names appearing more than once | B23: ='Customer Analysis'!H3 -> 47 | H23: ='Sales Analysis'!$A$10 -> West | I23: =UPPER(LEFT(H23,3)) -> WES | J23: UPPER(LEFT(x,3))
A24: Names appearing only once | B24: =B22-B23 -> 3
A25: Most repeated name | B25: =INDEX('Customer Analysis'!$B$23:$B$72,MATCH(MAX('Customer Analysis'!$E$23:$E$72),'Customer Analysis'!$E$23:$E$72,0)) -> Mark Carter | C25: =MAX('Customer Analysis'!$E$23:$E$72)&" transactions" -> 12 transactions
H26: Transaction | I26: Date (TEXT) | J26: Category | K26: Transaction Code
A27: Rank | B27: Customer Name | C27: Orders | D27: Revenue | H27: ='Raw Data'!A2 -> TRX0155 | I27: =TEXT('Raw Data'!B2,"ddd, dd-mmm-yy") -> Thu, 11-Apr-24 | J27: ='Raw Data'!G2 -> Electronics | K27: =UPPER(LEFT('Raw Data'!G2,3))&"-"&TEXT('Raw Data'!B2,"yymm")&"-"&RIGHT('Raw Data'!A2,4) -> ELE-2404-0155
A28: 1 | B28: =INDEX('Customer Analysis'!$B$23:$B$72,MATCH($A28,'Customer Analysis'!$R$23:$R$72,0)) -> Mark Carter | C28: =INDEX('Customer Analysis'!$E$23:$E$72,MATCH($A28,'Customer Analysis'!$R$23:$R$72,0)) -> 12 | D28: =INDEX('Customer Analysis'!$G$23:$G$72,MATCH($A28,'Customer Analysis'!$R$23:$R$72,0)) -> 15659.65 | H28: ='Raw Data'!A3 -> TRX0023 | I28: =TEXT('Raw Data'!B3,"ddd, dd-mmm-yy") -> Sun, 14-Apr-24 | J28: ='Raw Data'!G3 -> Electronics | K28: =UPPER(LEFT('Raw Data'!G3,3))&"-"&TEXT('Raw Data'!B3,"yymm")&"-"&RIGHT('Raw Data'!A3,4) -> ELE-2404-0023
A29: 2 | B29: =INDEX('Customer Analysis'!$B$23:$B$72,MATCH($A29,'Customer Analysis'!$R$23:$R$72,0)) -> Michael Brown | C29: =INDEX('Customer Analysis'!$E$23:$E$72,MATCH($A29,'Customer Analysis'!$R$23:$R$72,0)) -> 9 | D29: =INDEX('Customer Analysis'!$G$23:$G$72,MATCH($A29,'Customer Analysis'!$R$23:$R$72,0)) -> 6169.74 | H29: ='Raw Data'!A4 -> TRX0139 | I29: =TEXT('Raw Data'!B4,"ddd, dd-mmm-yy") -> Wed, 17-Apr-24 | J29: ='Raw Data'!G4 -> Appliances | K29: =UPPER(LEFT('Raw Data'!G4,3))&"-"&TEXT('Raw Data'!B4,"yymm")&"-"&RIGHT('Raw Data'!A4,4) -> APP-2404-0139
A30: 3 | B30: =INDEX('Customer Analysis'!$B$23:$B$72,MATCH($A30,'Customer Analysis'!$R$23:$R$72,0)) -> Charles Allen | C30: =INDEX('Customer Analysis'!$E$23:$E$72,MATCH($A30,'Customer Analysis'!$R$23:$R$72,0)) -> 9 | D30: =INDEX('Customer Analysis'!$G$23:$G$72,MATCH($A30,'Customer Analysis'!$R$23:$R$72,0)) -> 5089.73 | H30: ='Raw Data'!A5 -> TRX0043 | I30: =TEXT('Raw Data'!B5,"ddd, dd-mmm-yy") -> Thu, 18-Apr-24 | J30: ='Raw Data'!G5 -> Appliances | K30: =UPPER(LEFT('Raw Data'!G5,3))&"-"&TEXT('Raw Data'!B5,"yymm")&"-"&RIGHT('Raw Data'!A5,4) -> APP-2404-0043
A31: 4 | B31: =INDEX('Customer Analysis'!$B$23:$B$72,MATCH($A31,'Customer Analysis'!$R$23:$R$72,0)) -> Patricia Moore | C31: =INDEX('Customer Analysis'!$E$23:$E$72,MATCH($A31,'Customer Analysis'!$R$23:$R$72,0)) -> 8 | D31: =INDEX('Customer Analysis'!$G$23:$G$72,MATCH($A31,'Customer Analysis'!$R$23:$R$72,0)) -> 9799.73 | H31: ='Raw Data'!A6 -> TRX0212 | I31: =TEXT('Raw Data'!B6,"ddd, dd-mmm-yy") -> Thu, 18-Apr-24 | J31: ='Raw Data'!G6 -> Furniture | K31: =UPPER(LEFT('Raw Data'!G6,3))&"-"&TEXT('Raw Data'!B6,"yymm")&"-"&RIGHT('Raw Data'!A6,4) -> FUR-2404-0212
A32: 5 | B32: =INDEX('Customer Analysis'!$B$23:$B$72,MATCH($A32,'Customer Analysis'!$R$23:$R$72,0)) -> Paul Baker | C32: =INDEX('Customer Analysis'!$E$23:$E$72,MATCH($A32,'Customer Analysis'!$R$23:$R$72,0)) -> 8 | D32: =INDEX('Customer Analysis'!$G$23:$G$72,MATCH($A32,'Customer Analysis'!$R$23:$R$72,0)) -> 8309.74 | H32: ='Raw Data'!A7 -> TRX0092 | I32: =TEXT('Raw Data'!B7,"ddd, dd-mmm-yy") -> Sun, 21-Apr-24 | J32: ='Raw Data'!G7 -> Appliances | K32: =UPPER(LEFT('Raw Data'!G7,3))&"-"&TEXT('Raw Data'!B7,"yymm")&"-"&RIGHT('Raw Data'!A7,4) -> APP-2404-0092
A33: 6 | B33: =INDEX('Customer Analysis'!$B$23:$B$72,MATCH($A33,'Customer Analysis'!$R$23:$R$72,0)) -> Karen Hill | C33: =INDEX('Customer Analysis'!$E$23:$E$72,MATCH($A33,'Customer Analysis'!$R$23:$R$72,0)) -> 8 | D33: =INDEX('Customer Analysis'!$G$23:$G$72,MATCH($A33,'Customer Analysis'!$R$23:$R$72,0)) -> 8009.77 | H33: ='Raw Data'!A8 -> TRX0193 | I33: =TEXT('Raw Data'!B8,"ddd, dd-mmm-yy") -> Sun, 21-Apr-24 | J33: ='Raw Data'!G8 -> Electronics | K33: =UPPER(LEFT('Raw Data'!G8,3))&"-"&TEXT('Raw Data'!B8,"yymm")&"-"&RIGHT('Raw Data'!A8,4) -> ELE-2404-0193
A34: 7 | B34: =INDEX('Customer Analysis'!$B$23:$B$72,MATCH($A34,'Customer Analysis'!$R$23:$R$72,0)) -> Lawrence Reed | C34: =INDEX('Customer Analysis'!$E$23:$E$72,MATCH($A34,'Customer Analysis'!$R$23:$R$72,0)) -> 8 | D34: =INDEX('Customer Analysis'!$G$23:$G$72,MATCH($A34,'Customer Analysis'!$R$23:$R$72,0)) -> 6989.77 | H34: ='Raw Data'!A9 -> TRX0240 | I34: =TEXT('Raw Data'!B9,"ddd, dd-mmm-yy") -> Sun, 21-Apr-24 | J34: ='Raw Data'!G9 -> Appliances | K34: =UPPER(LEFT('Raw Data'!G9,3))&"-"&TEXT('Raw Data'!B9,"yymm")&"-"&RIGHT('Raw Data'!A9,4) -> APP-2404-0240
A35: 8 | B35: =INDEX('Customer Analysis'!$B$23:$B$72,MATCH($A35,'Customer Analysis'!$R$23:$R$72,0)) -> Daniel King | C35: =INDEX('Customer Analysis'!$E$23:$E$72,MATCH($A35,'Customer Analysis'!$R$23:$R$72,0)) -> 7 | D35: =INDEX('Customer Analysis'!$G$23:$G$72,MATCH($A35,'Customer Analysis'!$R$23:$R$72,0)) -> 7309.8 | H35: ='Raw Data'!A10 -> TRX0135 | I35: =TEXT('Raw Data'!B10,"ddd, dd-mmm-yy") -> Tue, 23-Apr-24 | J35: ='Raw Data'!G10 -> Electronics | K35: =UPPER(LEFT('Raw Data'!G10,3))&"-"&TEXT('Raw Data'!B10,"yymm")&"-"&RIGHT('Raw Data'!A10,4) -> ELE-2404-0135
A36: 9 | B36: =INDEX('Customer Analysis'!$B$23:$B$72,MATCH($A36,'Customer Analysis'!$R$23:$R$72,0)) -> Helen Roberts | C36: =INDEX('Customer Analysis'!$E$23:$E$72,MATCH($A36,'Customer Analysis'!$R$23:$R$72,0)) -> 7 | D36: =INDEX('Customer Analysis'!$G$23:$G$72,MATCH($A36,'Customer Analysis'!$R$23:$R$72,0)) -> 6459.79 | H36: ='Raw Data'!A11 -> TRX0185 | I36: =TEXT('Raw Data'!B11,"ddd, dd-mmm-yy") -> Fri, 26-Apr-24 | J36: ='Raw Data'!G11 -> Appliances | K36: =UPPER(LEFT('Raw Data'!G11,3))&"-"&TEXT('Raw Data'!B11,"yymm")&"-"&RIGHT('Raw Data'!A11,4) -> APP-2404-0185
A37: 10 | B37: =INDEX('Customer Analysis'!$B$23:$B$72,MATCH($A37,'Customer Analysis'!$R$23:$R$72,0)) -> David Martinez | C37: =INDEX('Customer Analysis'!$E$23:$E$72,MATCH($A37,'Customer Analysis'!$R$23:$R$72,0)) -> 6 | D37: =INDEX('Customer Analysis'!$G$23:$G$72,MATCH($A37,'Customer Analysis'!$R$23:$R$72,0)) -> 1809.84
H39: Customer (Top 10) | I39: Initials | J39: Short Code
A40: 3. Compare Two Lists - extract matching names into a new column | H40: ='Customer Analysis'!$C$9 -> Mark Carter | I40: =INDEX('Customer Analysis'!$C$23:$C$72,MATCH('Customer Analysis'!$B$9,'Customer Analysis'!$A$23:$A$72,0)) -> MC | J40: =INDEX('Customer Analysis'!$D$23:$D$72,MATCH('Customer Analysis'!$B$9,'Customer Analysis'!$A$23:$A$72,0)) -> MCAR-025
H41: ='Customer Analysis'!$C$10 -> Edward Mitchell | I41: =INDEX('Customer Analysis'!$C$23:$C$72,MATCH('Customer Analysis'!$B$10,'Customer Analysis'!$A$23:$A$72,0)) -> EM | J41: =INDEX('Customer Analysis'!$D$23:$D$72,MATCH('Customer Analysis'!$B$10,'Customer Analysis'!$A$23:$A$72,0)) -> EMIT-029
A42: In both lists | B42: =COUNTIF(D45:D94,"?*") -> 43 | C42: Only in List A | D42: =COUNTIF(E45:E94,"?*") -> 3 | E42: Only in List B | F42: =COUNTIF(F45:F94,"?*") -> 4 | H42: ='Customer Analysis'!$C$11 -> Barbara Young | I42: =INDEX('Customer Analysis'!$C$23:$C$72,MATCH('Customer Analysis'!$B$11,'Customer Analysis'!$A$23:$A$72,0)) -> BY | J42: =INDEX('Customer Analysis'!$D$23:$D$72,MATCH('Customer Analysis'!$B$11,'Customer Analysis'!$A$23:$A$72,0)) -> BYOU-018
H43: ='Customer Analysis'!$C$12 -> Patricia Moore | I43: =INDEX('Customer Analysis'!$C$23:$C$72,MATCH('Customer Analysis'!$B$12,'Customer Analysis'!$A$23:$A$72,0)) -> PM | J43: =INDEX('Customer Analysis'!$D$23:$D$72,MATCH('Customer Analysis'!$B$12,'Customer Analysis'!$A$23:$A$72,0)) -> PMOO-012
A44: # | B44: List A (H1 active) | C44: List B (H2 active) | D44: Matching names (in both) | E44: Only in List A | F44: Only in List B | H44: ='Customer Analysis'!$C$13 -> Paul Baker | I44: =INDEX('Customer Analysis'!$C$23:$C$72,MATCH('Customer Analysis'!$B$13,'Customer Analysis'!$A$23:$A$72,0)) -> PB | J44: =INDEX('Customer Analysis'!$D$23:$D$72,MATCH('Customer Analysis'!$B$13,'Customer Analysis'!$A$23:$A$72,0)) -> PBAK-023
A45: 1 | B45: =IFERROR(INDEX('Customer Analysis'!$B$23:$B$72,MATCH($A45,'Customer Analysis'!$U$23:$U$72,0)),"") -> Emma Wilson | C45: =IFERROR(INDEX('Customer Analysis'!$B$23:$B$72,MATCH($A45,'Customer Analysis'!$V$23:$V$72,0)),"") -> John Smith | D45: =IF(B45="","",IF(COUNTIF($C$45:$C$94,B45)>0,B45,"")) -> Emma Wilson | E45: =IF(B45="","",IF(COUNTIF($C$45:$C$94,B45)=0,B45,"")) | F45: =IF(C45="","",IF(COUNTIF($B$45:$B$94,C45)=0,C45,"")) -> John Smith | H45: ='Customer Analysis'!$C$14 -> Dorothy Nelson | I45: =INDEX('Customer Analysis'!$C$23:$C$72,MATCH('Customer Analysis'!$B$14,'Customer Analysis'!$A$23:$A$72,0)) -> DN | J45: =INDEX('Customer Analysis'!$D$23:$D$72,MATCH('Customer Analysis'!$B$14,'Customer Analysis'!$A$23:$A$72,0)) -> DNEL-024
A46: 2 | B46: =IFERROR(INDEX('Customer Analysis'!$B$23:$B$72,MATCH($A46,'Customer Analysis'!$U$23:$U$72,0)),"") -> Michael Brown | C46: =IFERROR(INDEX('Customer Analysis'!$B$23:$B$72,MATCH($A46,'Customer Analysis'!$V$23:$V$72,0)),"") -> Emma Wilson | D46: =IF(B46="","",IF(COUNTIF($C$45:$C$94,B46)>0,B46,"")) -> Michael Brown | E46: =IF(B46="","",IF(COUNTIF($C$45:$C$94,B46)=0,B46,"")) | F46: =IF(C46="","",IF(COUNTIF($B$45:$B$94,C46)=0,C46,"")) | H46: ='Customer Analysis'!$C$15 -> Karen Hill | I46: =INDEX('Customer Analysis'!$C$23:$C$72,MATCH('Customer Analysis'!$B$15,'Customer Analysis'!$A$23:$A$72,0)) -> KH | J46: =INDEX('Customer Analysis'!$D$23:$D$72,MATCH('Customer Analysis'!$B$15,'Customer Analysis'!$A$23:$A$72,0)) -> KHIL-026
A47: 3 | B47: =IFERROR(INDEX('Customer Analysis'!$B$23:$B$72,MATCH($A47,'Customer Analysis'!$U$23:$U$72,0)),"") -> Sarah Davis | C47: =IFERROR(INDEX('Customer Analysis'!$B$23:$B$72,MATCH($A47,'Customer Analysis'!$V$23:$V$72,0)),"") -> Michael Brown | D47: =IF(B47="","",IF(COUNTIF($C$45:$C$94,B47)>0,B47,"")) -> Sarah Davis | E47: =IF(B47="","",IF(COUNTIF($C$45:$C$94,B47)=0,B47,"")) | F47: =IF(C47="","",IF(COUNTIF($B$45:$B$94,C47)=0,C47,"")) | H47: ='Customer Analysis'!$C$16 -> Daniel King | I47: =INDEX('Customer Analysis'!$C$23:$C$72,MATCH('Customer Analysis'!$B$16,'Customer Analysis'!$A$23:$A$72,0)) -> DK | J47: =INDEX('Customer Analysis'!$D$23:$D$72,MATCH('Customer Analysis'!$B$16,'Customer Analysis'!$A$23:$A$72,0)) -> DKIN-019
A48: 4 | B48: =IFERROR(INDEX('Customer Analysis'!$B$23:$B$72,MATCH($A48,'Customer Analysis'!$U$23:$U$72,0)),"") -> Lisa Anderson | C48: =IFERROR(INDEX('Customer Analysis'!$B$23:$B$72,MATCH($A48,'Customer Analysis'!$V$23:$V$72,0)),"") -> Sarah Davis | D48: =IF(B48="","",IF(COUNTIF($C$45:$C$94,B48)>0,B48,"")) -> Lisa Anderson | E48: =IF(B48="","",IF(COUNTIF($C$45:$C$94,B48)=0,B48,"")) | F48: =IF(C48="","",IF(COUNTIF($B$45:$B$94,C48)=0,C48,"")) | H48: ='Customer Analysis'!$C$17 -> Lawrence Reed | I48: =INDEX('Customer Analysis'!$C$23:$C$72,MATCH('Customer Analysis'!$B$17,'Customer Analysis'!$A$23:$A$72,0)) -> LR | J48: =INDEX('Customer Analysis'!$D$23:$D$72,MATCH('Customer Analysis'!$B$17,'Customer Analysis'!$A$23:$A$72,0)) -> LREE-039
A49: 5 | B49: =IFERROR(INDEX('Customer Analysis'!$B$23:$B$72,MATCH($A49,'Customer Analysis'!$U$23:$U$72,0)),"") -> David Martinez | C49: =IFERROR(INDEX('Customer Analysis'!$B$23:$B$72,MATCH($A49,'Customer Analysis'!$V$23:$V$72,0)),"") -> James Johnson | D49: =IF(B49="","",IF(COUNTIF($C$45:$C$94,B49)>0,B49,"")) -> David Martinez | E49: =IF(B49="","",IF(COUNTIF($C$45:$C$94,B49)=0,B49,"")) | F49: =IF(C49="","",IF(COUNTIF($B$45:$B$94,C49)=0,C49,"")) -> James Johnson | H49: ='Customer Analysis'!$C$18 -> Joseph Jackson | I49: =INDEX('Customer Analysis'!$C$23:$C$72,MATCH('Customer Analysis'!$B$18,'Customer Analysis'!$A$23:$A$72,0)) -> JJ | J49: =INDEX('Customer Analysis'!$D$23:$D$72,MATCH('Customer Analysis'!$B$18,'Customer Analysis'!$A$23:$A$72,0)) -> JJAC-013
A50: 6 | B50: =IFERROR(INDEX('Customer Analysis'!$B$23:$B$72,MATCH($A50,'Customer Analysis'!$U$23:$U$72,0)),"") -> Jennifer Taylor | C50: =IFERROR(INDEX('Customer Analysis'!$B$23:$B$72,MATCH($A50,'Customer Analysis'!$V$23:$V$72,0)),"") -> Lisa Anderson | D50: =IF(B50="","",IF(COUNTIF($C$45:$C$94,B50)>0,B50,"")) -> Jennifer Taylor | E50: =IF(B50="","",IF(COUNTIF($C$45:$C$94,B50)=0,B50,"")) | F50: =IF(C50="","",IF(COUNTIF($B$45:$B$94,C50)=0,C50,""))
A51: 7 | B51: =IFERROR(INDEX('Customer Analysis'!$B$23:$B$72,MATCH($A51,'Customer Analysis'!$U$23:$U$72,0)),"") -> Robert Thomas | C51: =IFERROR(INDEX('Customer Analysis'!$B$23:$B$72,MATCH($A51,'Customer Analysis'!$V$23:$V$72,0)),"") -> David Martinez | D51: =IF(B51="","",IF(COUNTIF($C$45:$C$94,B51)>0,B51,"")) -> Robert Thomas | E51: =IF(B51="","",IF(COUNTIF($C$45:$C$94,B51)=0,B51,"")) | F51: =IF(C51="","",IF(COUNTIF($B$45:$B$94,C51)=0,C51,""))
A52: 8 | B52: =IFERROR(INDEX('Customer Analysis'!$B$23:$B$72,MATCH($A52,'Customer Analysis'!$U$23:$U$72,0)),"") -> Maria Garcia | C52: =IFERROR(INDEX('Customer Analysis'!$B$23:$B$72,MATCH($A52,'Customer Analysis'!$V$23:$V$72,0)),"") -> Jennifer Taylor | D52: =IF(B52="","",IF(COUNTIF($C$45:$C$94,B52)>0,B52,"")) -> Maria Garcia | E52: =IF(B52="","",IF(COUNTIF($C$45:$C$94,B52)=0,B52,"")) | F52: =IF(C52="","",IF(COUNTIF($B$45:$B$94,C52)=0,C52,""))
A53: 9 | B53: =IFERROR(INDEX('Customer Analysis'!$B$23:$B$72,MATCH($A53,'Customer Analysis'!$U$23:$U$72,0)),"") -> William White | C53: =IFERROR(INDEX('Customer Analysis'!$B$23:$B$72,MATCH($A53,'Customer Analysis'!$V$23:$V$72,0)),"") -> Robert Thomas | D53: =IF(B53="","",IF(COUNTIF($C$45:$C$94,B53)>0,B53,"")) -> William White | E53: =IF(B53="","",IF(COUNTIF($C$45:$C$94,B53)=0,B53,"")) | F53: =IF(C53="","",IF(COUNTIF($B$45:$B$94,C53)=0,C53,""))
A54: 10 | B54: =IFERROR(INDEX('Customer Analysis'!$B$23:$B$72,MATCH($A54,'Customer Analysis'!$U$23:$U$72,0)),"") -> Patricia Moore | C54: =IFERROR(INDEX('Customer Analysis'!$B$23:$B$72,MATCH($A54,'Customer Analysis'!$V$23:$V$72,0)),"") -> Maria Garcia | D54: =IF(B54="","",IF(COUNTIF($C$45:$C$94,B54)>0,B54,"")) -> Patricia Moore | E54: =IF(B54="","",IF(COUNTIF($C$45:$C$94,B54)=0,B54,"")) | F54: =IF(C54="","",IF(COUNTIF($B$45:$B$94,C54)=0,C54,""))
A55: 11 | B55: =IFERROR(INDEX('Customer Analysis'!$B$23:$B$72,MATCH($A55,'Customer Analysis'!$U$23:$U$72,0)),"") -> Joseph Jackson | C55: =IFERROR(INDEX('Customer Analysis'!$B$23:$B$72,MATCH($A55,'Customer Analysis'!$V$23:$V$72,0)),"") -> William White | D55: =IF(B55="","",IF(COUNTIF($C$45:$C$94,B55)>0,B55,"")) -> Joseph Jackson | E55: =IF(B55="","",IF(COUNTIF($C$45:$C$94,B55)=0,B55,"")) | F55: =IF(C55="","",IF(COUNTIF($B$45:$B$94,C55)=0,C55,""))
A56: 12 | B56: =IFERROR(INDEX('Customer Analysis'!$B$23:$B$72,MATCH($A56,'Customer Analysis'!$U$23:$U$72,0)),"") -> Linda Martin | C56: =IFERROR(INDEX('Customer Analysis'!$B$23:$B$72,MATCH($A56,'Customer Analysis'!$V$23:$V$72,0)),"") -> Patricia Moore | D56: =IF(B56="","",IF(COUNTIF($C$45:$C$94,B56)>0,B56,"")) -> Linda Martin | E56: =IF(B56="","",IF(COUNTIF($C$45:$C$94,B56)=0,B56,"")) | F56: =IF(C56="","",IF(COUNTIF($B$45:$B$94,C56)=0,C56,""))
A57: 13 | B57: =IFERROR(INDEX('Customer Analysis'!$B$23:$B$72,MATCH($A57,'Customer Analysis'!$U$23:$U$72,0)),"") -> Richard Lee | C57: =IFERROR(INDEX('Customer Analysis'!$B$23:$B$72,MATCH($A57,'Customer Analysis'!$V$23:$V$72,0)),"") -> Joseph Jackson | D57: =IF(B57="","",IF(COUNTIF($C$45:$C$94,B57)>0,B57,"")) -> Richard Lee | E57: =IF(B57="","",IF(COUNTIF($C$45:$C$94,B57)=0,B57,"")) | F57: =IF(C57="","",IF(COUNTIF($B$45:$B$94,C57)=0,C57,""))
A58: 14 | B58: =IFERROR(INDEX('Customer Analysis'!$B$23:$B$72,MATCH($A58,'Customer Analysis'!$U$23:$U$72,0)),"") -> Elizabeth Hall | C58: =IFERROR(INDEX('Customer Analysis'!$B$23:$B$72,MATCH($A58,'Customer Analysis'!$V$23:$V$72,0)),"") -> Linda Martin | D58: =IF(B58="","",IF(COUNTIF($C$45:$C$94,B58)>0,B58,"")) -> Elizabeth Hall | E58: =IF(B58="","",IF(COUNTIF($C$45:$C$94,B58)=0,B58,"")) | F58: =IF(C58="","",IF(COUNTIF($B$45:$B$94,C58)=0,C58,""))
A59: 15 | B59: =IFERROR(INDEX('Customer Analysis'!$B$23:$B$72,MATCH($A59,'Customer Analysis'!$U$23:$U$72,0)),"") -> Charles Allen | C59: =IFERROR(INDEX('Customer Analysis'!$B$23:$B$72,MATCH($A59,'Customer Analysis'!$V$23:$V$72,0)),"") -> Richard Lee | D59: =IF(B59="","",IF(COUNTIF($C$45:$C$94,B59)>0,B59,"")) -> Charles Allen | E59: =IF(B59="","",IF(COUNTIF($C$45:$C$94,B59)=0,B59,"")) | F59: =IF(C59="","",IF(COUNTIF($B$45:$B$94,C59)=0,C59,""))
A60: 16 | B60: =IFERROR(INDEX('Customer Analysis'!$B$23:$B$72,MATCH($A60,'Customer Analysis'!$U$23:$U$72,0)),"") -> Barbara Young | C60: =IFERROR(INDEX('Customer Analysis'!$B$23:$B$72,MATCH($A60,'Customer Analysis'!$V$23:$V$72,0)),"") -> Elizabeth Hall | D60: =IF(B60="","",IF(COUNTIF($C$45:$C$94,B60)>0,B60,"")) -> Barbara Young | E60: =IF(B60="","",IF(COUNTIF($C$45:$C$94,B60)=0,B60,"")) | F60: =IF(C60="","",IF(COUNTIF($B$45:$B$94,C60)=0,C60,""))
A61: 17 | B61: =IFERROR(INDEX('Customer Analysis'!$B$23:$B$72,MATCH($A61,'Customer Analysis'!$U$23:$U$72,0)),"") -> Daniel King | C61: =IFERROR(INDEX('Customer Analysis'!$B$23:$B$72,MATCH($A61,'Customer Analysis'!$V$23:$V$72,0)),"") -> Charles Allen | D61: =IF(B61="","",IF(COUNTIF($C$45:$C$94,B61)>0,B61,"")) -> Daniel King | E61: =IF(B61="","",IF(COUNTIF($C$45:$C$94,B61)=0,B61,"")) | F61: =IF(C61="","",IF(COUNTIF($B$45:$B$94,C61)=0,C61,""))
... A94: 50 | B94: =IFERROR(INDEX('Customer Analysis'!$B$23:$B$72,MATCH($A94,'Customer Analysis'!$U$23:$U$72,0)),"") | C94: =IFERROR(INDEX('Customer Analysis'!$B$23:$B$72,MATCH($A94,'Customer Analysis'!$V$23:$V$72,0)),"") | D94: =IF(B94="","",IF(COUNTIF($C$45:$C$94,B94)>0,B94,"")) | E94: =IF(B94="","",IF(COUNTIF($C$45:$C$94,B94)=0,B94,"")) | F94: =IF(C94="","",IF(COUNTIF($B$45:$B$94,C94)=0,C94,""))

Sheet Date & Time
A1: Date & Time Functions - TODAY, NOW, DATEDIF, EOMONTH, Timestamp
A3: 1. Live Date / Time Calculations
A4: Measure | B4: Result | C4: Function used
A5: Today | B5: =TODAY() -> 46310 | C5: TODAY()
A6: Now (date & time) | B6: =NOW() -> 46310.466 | C6: NOW()
A7: Weekday today | B7: =TEXT(B5,"dddd") -> Thursday | C7: TEXT(date,"dddd")
A8: First transaction date | B8: =MIN('Raw Data'!$B$2:$B$251) -> 45393 | C8: MIN()
A9: Last transaction date | B9: =MAX('Raw Data'!$B$2:$B$251) -> 45758 | C9: MAX()
A10: Data coverage (days) | B10: =B9-B8 -> 365 | C10: date subtraction
A11: Data coverage (complete months) | B11: =DATEDIF(B8,B9,"M") -> 12 | C11: DATEDIF(...,"M")
A12: Data coverage (Y / M / D) | B12: =DATEDIF(B8,B9,"Y")&"y "&DATEDIF(B8,B9,"YM")&"m "&DATEDIF(B8,B9,"MD")&"d" -> 1y 0m 0d | C12: DATEDIF "Y","YM","MD"
A13: Days since last transaction | B13: =B5-B9 -> 552 | C13: TODAY() - MAX()
A14: Time since last transaction | B14: =DATEDIF(B9,B5,"Y")&"y "&DATEDIF(B9,B5,"YM")&"m "&DATEDIF(B9,B5,"MD")&"d" -> 1y 6m 4d | C14: DATEDIF
A15: Month-end of last transaction | B15: =EOMONTH(B9,0) -> 45777 | C15: EOMONTH(date,0)
A16: Month-end of current month | B16: =EOMONTH(B5,0) -> 46326 | C16: EOMONTH(TODAY(),0)
A17: Days left in current month | B17: =B16-B5 -> 16 | C17: EOMONTH - TODAY
A18: Start of next month | B18: =EOMONTH(B5,0)+1 -> 46327 | C18: EOMONTH + 1
A19: Quarter-end of current quarter | B19: =EOMONTH(DATE(YEAR(B5),ROUNDUP(MONTH(B5)/3,0)*3,1),0) -> 46387 | C19: EOMONTH + ROUNDUP
A20: Month-end 3 months ahead | B20: =EOMONTH(B5,3) -> 46418 | C20: EOMONTH(date,3)
A23: 2. Customer Tenure with DATEDIF (Top 10 customers, measured to TODAY)
A24: Customer | B24: Customer Since | C24: Years | D24: Months | E24: Days | F24: Tenure
A25: ='Customer Analysis'!$C$9 -> Mark Carter | B25: =INDEX('Customer Analysis'!$K$23:$K$72,MATCH('Customer Analysis'!$B$9,'Customer Analysis'!$A$23:$A$72,0)) -> 44436 | C25: =DATEDIF(B25,TODAY(),"Y") -> 5 | D25: =DATEDIF(B25,TODAY(),"YM") -> 1 | E25: =DATEDIF(B25,TODAY(),"MD") -> 17 | F25: =C25&" yrs "&D25&" mths "&E25&" days" -> 5 yrs 1 mths 17 days
A26: ='Customer Analysis'!$C$10 -> Edward Mitchell | B26: =INDEX('Customer Analysis'!$K$23:$K$72,MATCH('Customer Analysis'!$B$10,'Customer Analysis'!$A$23:$A$72,0)) -> 44427 | C26: =DATEDIF(B26,TODAY(),"Y") -> 5 | D26: =DATEDIF(B26,TODAY(),"YM") -> 1 | E26: =DATEDIF(B26,TODAY(),"MD") -> 26 | F26: =C26&" yrs "&D26&" mths "&E26&" days" -> 5 yrs 1 mths 26 days
A27: ='Customer Analysis'!$C$11 -> Barbara Young | B27: =INDEX('Customer Analysis'!$K$23:$K$72,MATCH('Customer Analysis'!$B$11,'Customer Analysis'!$A$23:$A$72,0)) -> 44613 | C27: =DATEDIF(B27,TODAY(),"Y") -> 4 | D27: =DATEDIF(B27,TODAY(),"YM") -> 7 | E27: =DATEDIF(B27,TODAY(),"MD") -> 24 | F27: =C27&" yrs "&D27&" mths "&E27&" days" -> 4 yrs 7 mths 24 days
A28: ='Customer Analysis'!$C$12 -> Patricia Moore | B28: =INDEX('Customer Analysis'!$K$23:$K$72,MATCH('Customer Analysis'!$B$12,'Customer Analysis'!$A$23:$A$72,0)) -> 44409 | C28: =DATEDIF(B28,TODAY(),"Y") -> 5 | D28: =DATEDIF(B28,TODAY(),"YM") -> 2 | E28: =DATEDIF(B28,TODAY(),"MD") -> 14 | F28: =C28&" yrs "&D28&" mths "&E28&" days" -> 5 yrs 2 mths 14 days
A29: ='Customer Analysis'!$C$13 -> Paul Baker | B29: =INDEX('Customer Analysis'!$K$23:$K$72,MATCH('Customer Analysis'!$B$13,'Customer Analysis'!$A$23:$A$72,0)) -> 44425 | C29: =DATEDIF(B29,TODAY(),"Y") -> 5 | D29: =DATEDIF(B29,TODAY(),"YM") -> 1 | E29: =DATEDIF(B29,TODAY(),"MD") -> 28 | F29: =C29&" yrs "&D29&" mths "&E29&" days" -> 5 yrs 1 mths 28 days
A30: ='Customer Analysis'!$C$14 -> Dorothy Nelson | B30: =INDEX('Customer Analysis'!$K$23:$K$72,MATCH('Customer Analysis'!$B$14,'Customer Analysis'!$A$23:$A$72,0)) -> 44418 | C30: =DATEDIF(B30,TODAY(),"Y") -> 5 | D30: =DATEDIF(B30,TODAY(),"YM") -> 2 | E30: =DATEDIF(B30,TODAY(),"MD") -> 5 | F30: =C30&" yrs "&D30&" mths "&E30&" days" -> 5 yrs 2 mths 5 days
A31: ='Customer Analysis'!$C$15 -> Karen Hill | B31: =INDEX('Customer Analysis'!$K$23:$K$72,MATCH('Customer Analysis'!$B$15,'Customer Analysis'!$A$23:$A$72,0)) -> 44465 | C31: =DATEDIF(B31,TODAY(),"Y") -> 5 | D31: =DATEDIF(B31,TODAY(),"YM") -> 0 | E31: =DATEDIF(B31,TODAY(),"MD") -> 19 | F31: =C31&" yrs "&D31&" mths "&E31&" days" -> 5 yrs 0 mths 19 days
A32: ='Customer Analysis'!$C$16 -> Daniel King | B32: =INDEX('Customer Analysis'!$K$23:$K$72,MATCH('Customer Analysis'!$B$16,'Customer Analysis'!$A$23:$A$72,0)) -> 44446 | C32: =DATEDIF(B32,TODAY(),"Y") -> 5 | D32: =DATEDIF(B32,TODAY(),"YM") -> 1 | E32: =DATEDIF(B32,TODAY(),"MD") -> 8 | F32: =C32&" yrs "&D32&" mths "&E32&" days" -> 5 yrs 1 mths 8 days
A33: ='Customer Analysis'!$C$17 -> Lawrence Reed | B33: =INDEX('Customer Analysis'!$K$23:$K$72,MATCH('Customer Analysis'!$B$17,'Customer Analysis'!$A$23:$A$72,0)) -> 44544 | C33: =DATEDIF(B33,TODAY(),"Y") -> 4 | D33: =DATEDIF(B33,TODAY(),"YM") -> 10 | E33: =DATEDIF(B33,TODAY(),"MD") -> 1 | F33: =C33&" yrs "&D33&" mths "&E33&" days" -> 4 yrs 10 mths 1 days
A34: ='Customer Analysis'!$C$18 -> Joseph Jackson | B34: =INDEX('Customer Analysis'!$K$23:$K$72,MATCH('Customer Analysis'!$B$18,'Customer Analysis'!$A$23:$A$72,0)) -> 44475 | C34: =DATEDIF(B34,TODAY(),"Y") -> 5 | D34: =DATEDIF(B34,TODAY(),"YM") -> 0 | E34: =DATEDIF(B34,TODAY(),"MD") -> 9 | F34: =C34&" yrs "&D34&" mths "&E34&" days" -> 5 yrs 0 mths 9 days
A37: 3. Create Timestamp (NOW + iterative calculation) - freezes when an entry is made
A40: Entry / Reference (type here) | B40: Timestamp (auto)
A41: TRX0001 | B41: =IF(A41="","",IF(N(B41)=0,NOW(),B41)) -> 46310.233
A42: TRX0002 | B42: =IF(A42="","",IF(N(B42)=0,NOW(),B42)) -> 46310.233
A43: TRX0003 | B43: =IF(A43="","",IF(N(B43)=0,NOW(),B43)) -> 46310.233
B44: =IF(A44="","",IF(N(B44)=0,NOW(),B44))
B45: =IF(A45="","",IF(N(B45)=0,NOW(),B45))
B46: =IF(A46="","",IF(N(B46)=0,NOW(),B46))
B47: =IF(A47="","",IF(N(B47)=0,NOW(),B47))
B48: =IF(A48="","",IF(N(B48)=0,NOW(),B48))

Sheet Filter Demo
A1: FILTER - Multi-value Return
B4: Region | C4: All | E4: Matching revenue | F4: =SUMIF('Raw Data'!$T$2:$T$251,">0",'Raw Data'!$N$2:$N$251) -> 137197.98
B5: Category | C5: Electronics | E5: Average per match | F5: =IFERROR(F4/C7,0) -> 2540.7033
B6: Min Total Amount ($) | C6: 1000
B7: Matching transactions | C7: =COUNT('Raw Data'!$T$2:$T$251) -> 54
A9: # | B9: Transaction ID | C9: Date | D9: Customer | E9: Product | F9: Category | G9: Region | H9: Qty | I9: Total Amount
A10: =IF(1<=$C$7,1,"") -> 1 | B10: =IF($A10="","",INDEX('Raw Data'!$A$2:$A$251,MATCH($A10,'Raw Data'!$T$2:$T$251,0))) -> TRX0135 | C10: =IF($A10="","",INDEX('Raw Data'!$B$2:$B$251,MATCH($A10,'Raw Data'!$T$2:$T$251,0))) -> 45405 | D10: =IF($A10="","",INDEX('Raw Data'!$D$2:$D$251,MATCH($A10,'Raw Data'!$T$2:$T$251,0))) -> Robert Thomas | E10: =IF($A10="","",INDEX('Raw Data'!$F$2:$F$251,MATCH($A10,'Raw Data'!$T$2:$T$251,0))) -> Laptop | F10: =IF($A10="","",INDEX('Raw Data'!$G$2:$G$251,MATCH($A10,'Raw Data'!$T$2:$T$251,0))) -> Electronics | G10: =IF($A10="","",INDEX('Raw Data'!$K$2:$K$251,MATCH($A10,'Raw Data'!$T$2:$T$251,0))) -> East | H10: =IF($A10="","",INDEX('Raw Data'!$H$2:$H$251,MATCH($A10,'Raw Data'!$T$2:$T$251,0))) -> 3 | I10: =IF($A10="","",INDEX('Raw Data'!$N$2:$N$251,MATCH($A10,'Raw Data'!$T$2:$T$251,0))) -> 2699.97
A11: =IF(2<=$C$7,2,"") -> 2 | B11: =IF($A11="","",INDEX('Raw Data'!$A$2:$A$251,MATCH($A11,'Raw Data'!$T$2:$T$251,0))) -> TRX0191 | C11: =IF($A11="","",INDEX('Raw Data'!$B$2:$B$251,MATCH($A11,'Raw Data'!$T$2:$T$251,0))) -> 45409 | D11: =IF($A11="","",INDEX('Raw Data'!$D$2:$D$251,MATCH($A11,'Raw Data'!$T$2:$T$251,0))) -> Michelle Rogers | E11: =IF($A11="","",INDEX('Raw Data'!$F$2:$F$251,MATCH($A11,'Raw Data'!$T$2:$T$251,0))) -> Smartphone | F11: =IF($A11="","",INDEX('Raw Data'!$G$2:$G$251,MATCH($A11,'Raw Data'!$T$2:$T$251,0))) -> Electronics | G11: =IF($A11="","",INDEX('Raw Data'!$K$2:$K$251,MATCH($A11,'Raw Data'!$T$2:$T$251,0))) -> West | H11: =IF($A11="","",INDEX('Raw Data'!$H$2:$H$251,MATCH($A11,'Raw Data'!$T$2:$T$251,0))) -> 3 | I11: =IF($A11="","",INDEX('Raw Data'!$N$2:$N$251,MATCH($A11,'Raw Data'!$T$2:$T$251,0))) -> 2099.97
A12: =IF(3<=$C$7,3,"") -> 3 | B12: =IF($A12="","",INDEX('Raw Data'!$A$2:$A$251,MATCH($A12,'Raw Data'!$T$2:$T$251,0))) -> TRX0134 | C12: =IF($A12="","",INDEX('Raw Data'!$B$2:$B$251,MATCH($A12,'Raw Data'!$T$2:$T$251,0))) -> 45410 | D12: =IF($A12="","",INDEX('Raw Data'!$D$2:$D$251,MATCH($A12,'Raw Data'!$T$2:$T$251,0))) -> Maria Garcia | E12: =IF($A12="","",INDEX('Raw Data'!$F$2:$F$251,MATCH($A12,'Raw Data'!$T$2:$T$251,0))) -> Smartphone | F12: =IF($A12="","",INDEX('Raw Data'!$G$2:$G$251,MATCH($A12,'Raw Data'!$T$2:$T$251,0))) -> Electronics | G12: =IF($A12="","",INDEX('Raw Data'!$K$2:$K$251,MATCH($A12,'Raw Data'!$T$2:$T$251,0))) -> North | H12: =IF($A12="","",INDEX('Raw Data'!$H$2:$H$251,MATCH($A12,'Raw Data'!$T$2:$T$251,0))) -> 2 | I12: =IF($A12="","",INDEX('Raw Data'!$N$2:$N$251,MATCH($A12,'Raw Data'!$T$2:$T$251,0))) -> 1399.98
A13: =IF(4<=$C$7,4,"") -> 4 | B13: =IF($A13="","",INDEX('Raw Data'!$A$2:$A$251,MATCH($A13,'Raw Data'!$T$2:$T$251,0))) -> TRX0122 | C13: =IF($A13="","",INDEX('Raw Data'!$B$2:$B$251,MATCH($A13,'Raw Data'!$T$2:$T$251,0))) -> 45410 | D13: =IF($A13="","",INDEX('Raw Data'!$D$2:$D$251,MATCH($A13,'Raw Data'!$T$2:$T$251,0))) -> Mark Carter | E13: =IF($A13="","",INDEX('Raw Data'!$F$2:$F$251,MATCH($A13,'Raw Data'!$T$2:$T$251,0))) -> Laptop | F13: =IF($A13="","",INDEX('Raw Data'!$G$2:$G$251,MATCH($A13,'Raw Data'!$T$2:$T$251,0))) -> Electronics | G13: =IF($A13="","",INDEX('Raw Data'!$K$2:$K$251,MATCH($A13,'Raw Data'!$T$2:$T$251,0))) -> West | H13: =IF($A13="","",INDEX('Raw Data'!$H$2:$H$251,MATCH($A13,'Raw Data'!$T$2:$T$251,0))) -> 4 | I13: =IF($A13="","",INDEX('Raw Data'!$N$2:$N$251,MATCH($A13,'Raw Data'!$T$2:$T$251,0))) -> 3599.96
A14: =IF(5<=$C$7,5,"") -> 5 | B14: =IF($A14="","",INDEX('Raw Data'!$A$2:$A$251,MATCH($A14,'Raw Data'!$T$2:$T$251,0))) -> TRX0231 | C14: =IF($A14="","",INDEX('Raw Data'!$B$2:$B$251,MATCH($A14,'Raw Data'!$T$2:$T$251,0))) -> 45412 | D14: =IF($A14="","",INDEX('Raw Data'!$D$2:$D$251,MATCH($A14,'Raw Data'!$T$2:$T$251,0))) -> Barbara Young | E14: =IF($A14="","",INDEX('Raw Data'!$F$2:$F$251,MATCH($A14,'Raw Data'!$T$2:$T$251,0))) -> Smartphone | F14: =IF($A14="","",INDEX('Raw Data'!$G$2:$G$251,MATCH($A14,'Raw Data'!$T$2:$T$251,0))) -> Electronics | G14: =IF($A14="","",INDEX('Raw Data'!$K$2:$K$251,MATCH($A14,'Raw Data'!$T$2:$T$251,0))) -> West | H14: =IF($A14="","",INDEX('Raw Data'!$H$2:$H$251,MATCH($A14,'Raw Data'!$T$2:$T$251,0))) -> 5 | I14: =IF($A14="","",INDEX('Raw Data'!$N$2:$N$251,MATCH($A14,'Raw Data'!$T$2:$T$251,0))) -> 3499.95
A15: =IF(6<=$C$7,6,"") -> 6 | B15: =IF($A15="","",INDEX('Raw Data'!$A$2:$A$251,MATCH($A15,'Raw Data'!$T$2:$T$251,0))) -> TRX0239 | C15: =IF($A15="","",INDEX('Raw Data'!$B$2:$B$251,MATCH($A15,'Raw Data'!$T$2:$T$251,0))) -> 45413 | D15: =IF($A15="","",INDEX('Raw Data'!$D$2:$D$251,MATCH($A15,'Raw Data'!$T$2:$T$251,0))) -> Patricia Moore | E15: =IF($A15="","",INDEX('Raw Data'!$F$2:$F$251,MATCH($A15,'Raw Data'!$T$2:$T$251,0))) -> Smartphone | F15: =IF($A15="","",INDEX('Raw Data'!$G$2:$G$251,MATCH($A15,'Raw Data'!$T$2:$T$251,0))) -> Electronics | G15: =IF($A15="","",INDEX('Raw Data'!$K$2:$K$251,MATCH($A15,'Raw Data'!$T$2:$T$251,0))) -> East | H15: =IF($A15="","",INDEX('Raw Data'!$H$2:$H$251,MATCH($A15,'Raw Data'!$T$2:$T$251,0))) -> 4 | I15: =IF($A15="","",INDEX('Raw Data'!$N$2:$N$251,MATCH($A15,'Raw Data'!$T$2:$T$251,0))) -> 2799.96
A16: =IF(7<=$C$7,7,"") -> 7 | B16: =IF($A16="","",INDEX('Raw Data'!$A$2:$A$251,MATCH($A16,'Raw Data'!$T$2:$T$251,0))) -> TRX0071 | C16: =IF($A16="","",INDEX('Raw Data'!$B$2:$B$251,MATCH($A16,'Raw Data'!$T$2:$T$251,0))) -> 45422 | D16: =IF($A16="","",INDEX('Raw Data'!$D$2:$D$251,MATCH($A16,'Raw Data'!$T$2:$T$251,0))) -> Nancy Collins | E16: =IF($A16="","",INDEX('Raw Data'!$F$2:$F$251,MATCH($A16,'Raw Data'!$T$2:$T$251,0))) -> Monitor | F16: =IF($A16="","",INDEX('Raw Data'!$G$2:$G$251,MATCH($A16,'Raw Data'!$T$2:$T$251,0))) -> Electronics | G16: =IF($A16="","",INDEX('Raw Data'!$K$2:$K$251,MATCH($A16,'Raw Data'!$T$2:$T$251,0))) -> West | H16: =IF($A16="","",INDEX('Raw Data'!$H$2:$H$251,MATCH($A16,'Raw Data'!$T$2:$T$251,0))) -> 5 | I16: =IF($A16="","",INDEX('Raw Data'!$N$2:$N$251,MATCH($A16,'Raw Data'!$T$2:$T$251,0))) -> 1249.95
A17: =IF(8<=$C$7,8,"") -> 8 | B17: =IF($A17="","",INDEX('Raw Data'!$A$2:$A$251,MATCH($A17,'Raw Data'!$T$2:$T$251,0))) -> TRX0015 | C17: =IF($A17="","",INDEX('Raw Data'!$B$2:$B$251,MATCH($A17,'Raw Data'!$T$2:$T$251,0))) -> 45440 | D17: =IF($A17="","",INDEX('Raw Data'!$D$2:$D$251,MATCH($A17,'Raw Data'!$T$2:$T$251,0))) -> Jennifer Taylor | E17: =IF($A17="","",INDEX('Raw Data'!$F$2:$F$251,MATCH($A17,'Raw Data'!$T$2:$T$251,0))) -> Smartphone | F17: =IF($A17="","",INDEX('Raw Data'!$G$2:$G$251,MATCH($A17,'Raw Data'!$T$2:$T$251,0))) -> Electronics | G17: =IF($A17="","",INDEX('Raw Data'!$K$2:$K$251,MATCH($A17,'Raw Data'!$T$2:$T$251,0))) -> West | H17: =IF($A17="","",INDEX('Raw Data'!$H$2:$H$251,MATCH($A17,'Raw Data'!$T$2:$T$251,0))) -> 5 | I17: =IF($A17="","",INDEX('Raw Data'!$N$2:$N$251,MATCH($A17,'Raw Data'!$T$2:$T$251,0))) -> 3499.95
A18: =IF(9<=$C$7,9,"") -> 9 | B18: =IF($A18="","",INDEX('Raw Data'!$A$2:$A$251,MATCH($A18,'Raw Data'!$T$2:$T$251,0))) -> TRX0234 | C18: =IF($A18="","",INDEX('Raw Data'!$B$2:$B$251,MATCH($A18,'Raw Data'!$T$2:$T$251,0))) -> 45449 | D18: =IF($A18="","",INDEX('Raw Data'!$D$2:$D$251,MATCH($A18,'Raw Data'!$T$2:$T$251,0))) -> Joseph Jackson | E18: =IF($A18="","",INDEX('Raw Data'!$F$2:$F$251,MATCH($A18,'Raw Data'!$T$2:$T$251,0))) -> Monitor | F18: =IF($A18="","",INDEX('Raw Data'!$G$2:$G$251,MATCH($A18,'Raw Data'!$T$2:$T$251,0))) -> Electronics | G18: =IF($A18="","",INDEX('Raw Data'!$K$2:$K$251,MATCH($A18,'Raw Data'!$T$2:$T$251,0))) -> East | H18: =IF($A18="","",INDEX('Raw Data'!$H$2:$H$251,MATCH($A18,'Raw Data'!$T$2:$T$251,0))) -> 5 | I18: =IF($A18="","",INDEX('Raw Data'!$N$2:$N$251,MATCH($A18,'Raw Data'!$T$2:$T$251,0))) -> 1249.95
A19: =IF(10<=$C$7,10,"") -> 10 | B19: =IF($A19="","",INDEX('Raw Data'!$A$2:$A$251,MATCH($A19,'Raw Data'!$T$2:$T$251,0))) -> TRX0154 | C19: =IF($A19="","",INDEX('Raw Data'!$B$2:$B$251,MATCH($A19,'Raw Data'!$T$2:$T$251,0))) -> 45459 | D19: =IF($A19="","",INDEX('Raw Data'!$D$2:$D$251,MATCH($A19,'Raw Data'!$T$2:$T$251,0))) -> Paul Baker | E19: =IF($A19="","",INDEX('Raw Data'!$F$2:$F$251,MATCH($A19,'Raw Data'!$T$2:$T$251,0))) -> Laptop | F19: =IF($A19="","",INDEX('Raw Data'!$G$2:$G$251,MATCH($A19,'Raw Data'!$T$2:$T$251,0))) -> Electronics | G19: =IF($A19="","",INDEX('Raw Data'!$K$2:$K$251,MATCH($A19,'Raw Data'!$T$2:$T$251,0))) -> South | H19: =IF($A19="","",INDEX('Raw Data'!$H$2:$H$251,MATCH($A19,'Raw Data'!$T$2:$T$251,0))) -> 5 | I19: =IF($A19="","",INDEX('Raw Data'!$N$2:$N$251,MATCH($A19,'Raw Data'!$T$2:$T$251,0))) -> 4499.95
A20: =IF(11<=$C$7,11,"") -> 11 | B20: =IF($A20="","",INDEX('Raw Data'!$A$2:$A$251,MATCH($A20,'Raw Data'!$T$2:$T$251,0))) -> TRX0044 | C20: =IF($A20="","",INDEX('Raw Data'!$B$2:$B$251,MATCH($A20,'Raw Data'!$T$2:$T$251,0))) -> 45459 | D20: =IF($A20="","",INDEX('Raw Data'!$D$2:$D$251,MATCH($A20,'Raw Data'!$T$2:$T$251,0))) -> Edward Mitchell | E20: =IF($A20="","",INDEX('Raw Data'!$F$2:$F$251,MATCH($A20,'Raw Data'!$T$2:$T$251,0))) -> Laptop | F20: =IF($A20="","",INDEX('Raw Data'!$G$2:$G$251,MATCH($A20,'Raw Data'!$T$2:$T$251,0))) -> Electronics | G20: =IF($A20="","",INDEX('Raw Data'!$K$2:$K$251,MATCH($A20,'Raw Data'!$T$2:$T$251,0))) -> East | H20: =IF($A20="","",INDEX('Raw Data'!$H$2:$H$251,MATCH($A20,'Raw Data'!$T$2:$T$251,0))) -> 5 | I20: =IF($A20="","",INDEX('Raw Data'!$N$2:$N$251,MATCH($A20,'Raw Data'!$T$2:$T$251,0))) -> 4499.95
A21: =IF(12<=$C$7,12,"") -> 12 | B21: =IF($A21="","",INDEX('Raw Data'!$A$2:$A$251,MATCH($A21,'Raw Data'!$T$2:$T$251,0))) -> TRX0184 | C21: =IF($A21="","",INDEX('Raw Data'!$B$2:$B$251,MATCH($A21,'Raw Data'!$T$2:$T$251,0))) -> 45471 | D21: =IF($A21="","",INDEX('Raw Data'!$D$2:$D$251,MATCH($A21,'Raw Data'!$T$2:$T$251,0))) -> Kathleen Bennett | E21: =IF($A21="","",INDEX('Raw Data'!$F$2:$F$251,MATCH($A21,'Raw Data'!$T$2:$T$251,0))) -> Smartphone | F21: =IF($A21="","",INDEX('Raw Data'!$G$2:$G$251,MATCH($A21,'Raw Data'!$T$2:$T$251,0))) -> Electronics | G21: =IF($A21="","",INDEX('Raw Data'!$K$2:$K$251,MATCH($A21,'Raw Data'!$T$2:$T$251,0))) -> East | H21: =IF($A21="","",INDEX('Raw Data'!$H$2:$H$251,MATCH($A21,'Raw Data'!$T$2:$T$251,0))) -> 3 | I21: =IF($A21="","",INDEX('Raw Data'!$N$2:$N$251,MATCH($A21,'Raw Data'!$T$2:$T$251,0))) -> 2099.97
A22: =IF(13<=$C$7,13,"") -> 13 | B22: =IF($A22="","",INDEX('Raw Data'!$A$2:$A$251,MATCH($A22,'Raw Data'!$T$2:$T$251,0))) -> TRX0104 | C22: =IF($A22="","",INDEX('Raw Data'!$B$2:$B$251,MATCH($A22,'Raw Data'!$T$2:$T$251,0))) -> 45471 | D22: =IF($A22="","",INDEX('Raw Data'!$D$2:$D$251,MATCH($A22,'Raw Data'!$T$2:$T$251,0))) -> Patricia Moore | E22: =IF($A22="","",INDEX('Raw Data'!$F$2:$F$251,MATCH($A22,'Raw Data'!$T$2:$T$251,0))) -> Laptop | F22: =IF($A22="","",INDEX('Raw Data'!$G$2:$G$251,MATCH($A22,'Raw Data'!$T$2:$T$251,0))) -> Electronics | G22: =IF($A22="","",INDEX('Raw Data'!$K$2:$K$251,MATCH($A22,'Raw Data'!$T$2:$T$251,0))) -> East | H22: =IF($A22="","",INDEX('Raw Data'!$H$2:$H$251,MATCH($A22,'Raw Data'!$T$2:$T$251,0))) -> 4 | I22: =IF($A22="","",INDEX('Raw Data'!$N$2:$N$251,MATCH($A22,'Raw Data'!$T$2:$T$251,0))) -> 3599.96
A23: =IF(14<=$C$7,14,"") -> 14 | B23: =IF($A23="","",INDEX('Raw Data'!$A$2:$A$251,MATCH($A23,'Raw Data'!$T$2:$T$251,0))) -> TRX0113 | C23: =IF($A23="","",INDEX('Raw Data'!$B$2:$B$251,MATCH($A23,'Raw Data'!$T$2:$T$251,0))) -> 45481 | D23: =IF($A23="","",INDEX('Raw Data'!$D$2:$D$251,MATCH($A23,'Raw Data'!$T$2:$T$251,0))) -> Michael Brown | E23: =IF($A23="","",INDEX('Raw Data'!$F$2:$F$251,MATCH($A23,'Raw Data'!$T$2:$T$251,0))) -> Smartphone | F23: =IF($A23="","",INDEX('Raw Data'!$G$2:$G$251,MATCH($A23,'Raw Data'!$T$2:$T$251,0))) -> Electronics | G23: =IF($A23="","",INDEX('Raw Data'!$K$2:$K$251,MATCH($A23,'Raw Data'!$T$2:$T$251,0))) -> East | H23: =IF($A23="","",INDEX('Raw Data'!$H$2:$H$251,MATCH($A23,'Raw Data'!$T$2:$T$251,0))) -> 2 | I23: =IF($A23="","",INDEX('Raw Data'!$N$2:$N$251,MATCH($A23,'Raw Data'!$T$2:$T$251,0))) -> 1399.98
A24: =IF(15<=$C$7,15,"") -> 15 | B24: =IF($A24="","",INDEX('Raw Data'!$A$2:$A$251,MATCH($A24,'Raw Data'!$T$2:$T$251,0))) -> TRX0244 | C24: =IF($A24="","",INDEX('Raw Data'!$B$2:$B$251,MATCH($A24,'Raw Data'!$T$2:$T$251,0))) -> 45497 | D24: =IF($A24="","",INDEX('Raw Data'!$D$2:$D$251,MATCH($A24,'Raw Data'!$T$2:$T$251,0))) -> Joseph Jackson | E24: =IF($A24="","",INDEX('Raw Data'!$F$2:$F$251,MATCH($A24,'Raw Data'!$T$2:$T$251,0))) -> Laptop | F24: =IF($A24="","",INDEX('Raw Data'!$G$2:$G$251,MATCH($A24,'Raw Data'!$T$2:$T$251,0))) -> Electronics | G24: =IF($A24="","",INDEX('Raw Data'!$K$2:$K$251,MATCH($A24,'Raw Data'!$T$2:$T$251,0))) -> South | H24: =IF($A24="","",INDEX('Raw Data'!$H$2:$H$251,MATCH($A24,'Raw Data'!$T$2:$T$251,0))) -> 5 | I24: =IF($A24="","",INDEX('Raw Data'!$N$2:$N$251,MATCH($A24,'Raw Data'!$T$2:$T$251,0))) -> 4499.95
A25: =IF(16<=$C$7,16,"") -> 16 | B25: =IF($A25="","",INDEX('Raw Data'!$A$2:$A$251,MATCH($A25,'Raw Data'!$T$2:$T$251,0))) -> TRX0217 | C25: =IF($A25="","",INDEX('Raw Data'!$B$2:$B$251,MATCH($A25,'Raw Data'!$T$2:$T$251,0))) -> 45503 | D25: =IF($A25="","",INDEX('Raw Data'!$D$2:$D$251,MATCH($A25,'Raw Data'!$T$2:$T$251,0))) -> Mark Carter | E25: =IF($A25="","",INDEX('Raw Data'!$F$2:$F$251,MATCH($A25,'Raw Data'!$T$2:$T$251,0))) -> Smartphone | F25: =IF($A25="","",INDEX('Raw Data'!$G$2:$G$251,MATCH($A25,'Raw Data'!$T$2:$T$251,0))) -> Electronics | G25: =IF($A25="","",INDEX('Raw Data'!$K$2:$K$251,MATCH($A25,'Raw Data'!$T$2:$T$251,0))) -> North | H25: =IF($A25="","",INDEX('Raw Data'!$H$2:$H$251,MATCH($A25,'Raw Data'!$T$2:$T$251,0))) -> 2 | I25: =IF($A25="","",INDEX('Raw Data'!$N$2:$N$251,MATCH($A25,'Raw Data'!$T$2:$T$251,0))) -> 1399.98
A26: =IF(17<=$C$7,17,"") -> 17 | B26: =IF($A26="","",INDEX('Raw Data'!$A$2:$A$251,MATCH($A26,'Raw Data'!$T$2:$T$251,0))) -> TRX0249 | C26: =IF($A26="","",INDEX('Raw Data'!$B$2:$B$251,MATCH($A26,'Raw Data'!$T$2:$T$251,0))) -> 45504 | D26: =IF($A26="","",INDEX('Raw Data'!$D$2:$D$251,MATCH($A26,'Raw Data'!$T$2:$T$251,0))) -> Helen Roberts | E26: =IF($A26="","",INDEX('Raw Data'!$F$2:$F$251,MATCH($A26,'Raw Data'!$T$2:$T$251,0))) -> Laptop | F26: =IF($A26="","",INDEX('Raw Data'!$G$2:$G$251,MATCH($A26,'Raw Data'!$T$2:$T$251,0))) -> Electronics | G26: =IF($A26="","",INDEX('Raw Data'!$K$2:$K$251,MATCH($A26,'Raw Data'!$T$2:$T$251,0))) -> South | H26: =IF($A26="","",INDEX('Raw Data'!$H$2:$H$251,MATCH($A26,'Raw Data'!$T$2:$T$251,0))) -> 4 | I26: =IF($A26="","",INDEX('Raw Data'!$N$2:$N$251,MATCH($A26,'Raw Data'!$T$2:$T$251,0))) -> 3599.96
A27: =IF(18<=$C$7,18,"") -> 18 | B27: =IF($A27="","",INDEX('Raw Data'!$A$2:$A$251,MATCH($A27,'Raw Data'!$T$2:$T$251,0))) -> TRX0075 | C27: =IF($A27="","",INDEX('Raw Data'!$B$2:$B$251,MATCH($A27,'Raw Data'!$T$2:$T$251,0))) -> 45517 | D27: =IF($A27="","",INDEX('Raw Data'!$D$2:$D$251,MATCH($A27,'Raw Data'!$T$2:$T$251,0))) -> Margaret Wright | E27: =IF($A27="","",INDEX('Raw Data'!$F$2:$F$251,MATCH($A27,'Raw Data'!$T$2:$T$251,0))) -> Monitor | F27: =IF($A27="","",INDEX('Raw Data'!$G$2:$G$251,MATCH($A27,'Raw Data'!$T$2:$T$251,0))) -> Electronics | G27: =IF($A27="","",INDEX('Raw Data'!$K$2:$K$251,MATCH($A27,'Raw Data'!$T$2:$T$251,0))) -> East | H27: =IF($A27="","",INDEX('Raw Data'!$H$2:$H$251,MATCH($A27,'Raw Data'!$T$2:$T$251,0))) -> 5 | I27: =IF($A27="","",INDEX('Raw Data'!$N$2:$N$251,MATCH($A27,'Raw Data'!$T$2:$T$251,0))) -> 1249.95
A28: =IF(19<=$C$7,19,"") -> 19 | B28: =IF($A28="","",INDEX('Raw Data'!$A$2:$A$251,MATCH($A28,'Raw Data'!$T$2:$T$251,0))) -> TRX0132 | C28: =IF($A28="","",INDEX('Raw Data'!$B$2:$B$251,MATCH($A28,'Raw Data'!$T$2:$T$251,0))) -> 45523 | D28: =IF($A28="","",INDEX('Raw Data'!$D$2:$D$251,MATCH($A28,'Raw Data'!$T$2:$T$251,0))) -> Gerald Murphy | E28: =IF($A28="","",INDEX('Raw Data'!$F$2:$F$251,MATCH($A28,'Raw Data'!$T$2:$T$251,0))) -> Laptop | F28: =IF($A28="","",INDEX('Raw Data'!$G$2:$G$251,MATCH($A28,'Raw Data'!$T$2:$T$251,0))) -> Electronics | G28: =IF($A28="","",INDEX('Raw Data'!$K$2:$K$251,MATCH($A28,'Raw Data'!$T$2:$T$251,0))) -> East | H28: =IF($A28="","",INDEX('Raw Data'!$H$2:$H$251,MATCH($A28,'Raw Data'!$T$2:$T$251,0))) -> 5 | I28: =IF($A28="","",INDEX('Raw Data'!$N$2:$N$251,MATCH($A28,'Raw Data'!$T$2:$T$251,0))) -> 4499.95
A29: =IF(20<=$C$7,20,"") -> 20 | B29: =IF($A29="","",INDEX('Raw Data'!$A$2:$A$251,MATCH($A29,'Raw Data'!$T$2:$T$251,0))) -> TRX0248 | C29: =IF($A29="","",INDEX('Raw Data'!$B$2:$B$251,MATCH($A29,'Raw Data'!$T$2:$T$251,0))) -> 45534 | D29: =IF($A29="","",INDEX('Raw Data'!$D$2:$D$251,MATCH($A29,'Raw Data'!$T$2:$T$251,0))) -> Sandra Phillips | E29: =IF($A29="","",INDEX('Raw Data'!$F$2:$F$251,MATCH($A29,'Raw Data'!$T$2:$T$251,0))) -> Smartphone | F29: =IF($A29="","",INDEX('Raw Data'!$G$2:$G$251,MATCH($A29,'Raw Data'!$T$2:$T$251,0))) -> Electronics | G29: =IF($A29="","",INDEX('Raw Data'!$K$2:$K$251,MATCH($A29,'Raw Data'!$T$2:$T$251,0))) -> North | H29: =IF($A29="","",INDEX('Raw Data'!$H$2:$H$251,MATCH($A29,'Raw Data'!$T$2:$T$251,0))) -> 2 | I29: =IF($A29="","",INDEX('Raw Data'!$N$2:$N$251,MATCH($A29,'Raw Data'!$T$2:$T$251,0))) -> 1399.98
A30: =IF(21<=$C$7,21,"") -> 21 | B30: =IF($A30="","",INDEX('Raw Data'!$A$2:$A$251,MATCH($A30,'Raw Data'!$T$2:$T$251,0))) -> TRX0225 | C30: =IF($A30="","",INDEX('Raw Data'!$B$2:$B$251,MATCH($A30,'Raw Data'!$T$2:$T$251,0))) -> 45538 | D30: =IF($A30="","",INDEX('Raw Data'!$D$2:$D$251,MATCH($A30,'Raw Data'!$T$2:$T$251,0))) -> Lawrence Reed | E30: =IF($A30="","",INDEX('Raw Data'!$F$2:$F$251,MATCH($A30,'Raw Data'!$T$2:$T$251,0))) -> Smartphone | F30: =IF($A30="","",INDEX('Raw Data'!$G$2:$G$251,MATCH($A30,'Raw Data'!$T$2:$T$251,0))) -> Electronics | G30: =IF($A30="","",INDEX('Raw Data'!$K$2:$K$251,MATCH($A30,'Raw Data'!$T$2:$T$251,0))) -> Central | H30: =IF($A30="","",INDEX('Raw Data'!$H$2:$H$251,MATCH($A30,'Raw Data'!$T$2:$T$251,0))) -> 2 | I30: =IF($A30="","",INDEX('Raw Data'!$N$2:$N$251,MATCH($A30,'Raw Data'!$T$2:$T$251,0))) -> 1399.98
A31: =IF(22<=$C$7,22,"") -> 22 | B31: =IF($A31="","",INDEX('Raw Data'!$A$2:$A$251,MATCH($A31,'Raw Data'!$T$2:$T$251,0))) -> TRX0123 | C31: =IF($A31="","",INDEX('Raw Data'!$B$2:$B$251,MATCH($A31,'Raw Data'!$T$2:$T$251,0))) -> 45554 | D31: =IF($A31="","",INDEX('Raw Data'!$D$2:$D$251,MATCH($A31,'Raw Data'!$T$2:$T$251,0))) -> Peter Richardson | E31: =IF($A31="","",INDEX('Raw Data'!$F$2:$F$251,MATCH($A31,'Raw Data'!$T$2:$T$251,0))) -> Smartphone | F31: =IF($A31="","",INDEX('Raw Data'!$G$2:$G$251,MATCH($A31,'Raw Data'!$T$2:$T$251,0))) -> Electronics | G31: =IF($A31="","",INDEX('Raw Data'!$K$2:$K$251,MATCH($A31,'Raw Data'!$T$2:$T$251,0))) -> South | H31: =IF($A31="","",INDEX('Raw Data'!$H$2:$H$251,MATCH($A31,'Raw Data'!$T$2:$T$251,0))) -> 4 | I31: =IF($A31="","",INDEX('Raw Data'!$N$2:$N$251,MATCH($A31,'Raw Data'!$T$2:$T$251,0))) -> 2799.96
A32: =IF(23<=$C$7,23,"") -> 23 | B32: =IF($A32="","",INDEX('Raw Data'!$A$2:$A$251,MATCH($A32,'Raw Data'!$T$2:$T$251,0))) -> TRX0177 | C32: =IF($A32="","",INDEX('Raw Data'!$B$2:$B$251,MATCH($A32,'Raw Data'!$T$2:$T$251,0))) -> 45559 | D32: =IF($A32="","",INDEX('Raw Data'!$D$2:$D$251,MATCH($A32,'Raw Data'!$T$2:$T$251,0))) -> Sandra Phillips | E32: =IF($A32="","",INDEX('Raw Data'!$F$2:$F$251,MATCH($A32,'Raw Data'!$T$2:$T$251,0))) -> Laptop | F32: =IF($A32="","",INDEX('Raw Data'!$G$2:$G$251,MATCH($A32,'Raw Data'!$T$2:$T$251,0))) -> Electronics | G32: =IF($A32="","",INDEX('Raw Data'!$K$2:$K$251,MATCH($A32,'Raw Data'!$T$2:$T$251,0))) -> North | H32: =IF($A32="","",INDEX('Raw Data'!$H$2:$H$251,MATCH($A32,'Raw Data'!$T$2:$T$251,0))) -> 3 | I32: =IF($A32="","",INDEX('Raw Data'!$N$2:$N$251,MATCH($A32,'Raw Data'!$T$2:$T$251,0))) -> 2699.97
A33: =IF(24<=$C$7,24,"") -> 24 | B33: =IF($A33="","",INDEX('Raw Data'!$A$2:$A$251,MATCH($A33,'Raw Data'!$T$2:$T$251,0))) -> TRX0055 | C33: =IF($A33="","",INDEX('Raw Data'!$B$2:$B$251,MATCH($A33,'Raw Data'!$T$2:$T$251,0))) -> 45573 | D33: =IF($A33="","",INDEX('Raw Data'!$D$2:$D$251,MATCH($A33,'Raw Data'!$T$2:$T$251,0))) -> Elizabeth Hall | E33: =IF($A33="","",INDEX('Raw Data'!$F$2:$F$251,MATCH($A33,'Raw Data'!$T$2:$T$251,0))) -> Smartphone | F33: =IF($A33="","",INDEX('Raw Data'!$G$2:$G$251,MATCH($A33,'Raw Data'!$T$2:$T$251,0))) -> Electronics | G33: =IF($A33="","",INDEX('Raw Data'!$K$2:$K$251,MATCH($A33,'Raw Data'!$T$2:$T$251,0))) -> East | H33: =IF($A33="","",INDEX('Raw Data'!$H$2:$H$251,MATCH($A33,'Raw Data'!$T$2:$T$251,0))) -> 2 | I33: =IF($A33="","",INDEX('Raw Data'!$N$2:$N$251,MATCH($A33,'Raw Data'!$T$2:$T$251,0))) -> 1399.98
A34: =IF(25<=$C$7,25,"") -> 25 | B34: =IF($A34="","",INDEX('Raw Data'!$A$2:$A$251,MATCH($A34,'Raw Data'!$T$2:$T$251,0))) -> TRX0158 | C34: =IF($A34="","",INDEX('Raw Data'!$B$2:$B$251,MATCH($A34,'Raw Data'!$T$2:$T$251,0))) -> 45579 | D34: =IF($A34="","",INDEX('Raw Data'!$D$2:$D$251,MATCH($A34,'Raw Data'!$T$2:$T$251,0))) -> George Adams | E34: =IF($A34="","",INDEX('Raw Data'!$F$2:$F$251,MATCH($A34,'Raw Data'!$T$2:$T$251,0))) -> Laptop | F34: =IF($A34="","",INDEX('Raw Data'!$G$2:$G$251,MATCH($A34,'Raw Data'!$T$2:$T$251,0))) -> Electronics | G34: =IF($A34="","",INDEX('Raw Data'!$K$2:$K$251,MATCH($A34,'Raw Data'!$T$2:$T$251,0))) -> West | H34: =IF($A34="","",INDEX('Raw Data'!$H$2:$H$251,MATCH($A34,'Raw Data'!$T$2:$T$251,0))) -> 3 | I34: =IF($A34="","",INDEX('Raw Data'!$N$2:$N$251,MATCH($A34,'Raw Data'!$T$2:$T$251,0))) -> 2699.97
A35: =IF(26<=$C$7,26,"") -> 26 | B35: =IF($A35="","",INDEX('Raw Data'!$A$2:$A$251,MATCH($A35,'Raw Data'!$T$2:$T$251,0))) -> TRX0173 | C35: =IF($A35="","",INDEX('Raw Data'!$B$2:$B$251,MATCH($A35,'Raw Data'!$T$2:$T$251,0))) -> 45581 | D35: =IF($A35="","",INDEX('Raw Data'!$D$2:$D$251,MATCH($A35,'Raw Data'!$T$2:$T$251,0))) -> Barbara Young | E35: =IF($A35="","",INDEX('Raw Data'!$F$2:$F$251,MATCH($A35,'Raw Data'!$T$2:$T$251,0))) -> Smartphone | F35: =IF($A35="","",INDEX('Raw Data'!$G$2:$G$251,MATCH($A35,'Raw Data'!$T$2:$T$251,0))) -> Electronics | G35: =IF($A35="","",INDEX('Raw Data'!$K$2:$K$251,MATCH($A35,'Raw Data'!$T$2:$T$251,0))) -> East | H35: =IF($A35="","",INDEX('Raw Data'!$H$2:$H$251,MATCH($A35,'Raw Data'!$T$2:$T$251,0))) -> 5 | I35: =IF($A35="","",INDEX('Raw Data'!$N$2:$N$251,MATCH($A35,'Raw Data'!$T$2:$T$251,0))) -> 3499.95
A36: =IF(27<=$C$7,27,"") -> 27 | B36: =IF($A36="","",INDEX('Raw Data'!$A$2:$A$251,MATCH($A36,'Raw Data'!$T$2:$T$251,0))) -> TRX0034 | C36: =IF($A36="","",INDEX('Raw Data'!$B$2:$B$251,MATCH($A36,'Raw Data'!$T$2:$T$251,0))) -> 45581 | D36: =IF($A36="","",INDEX('Raw Data'!$D$2:$D$251,MATCH($A36,'Raw Data'!$T$2:$T$251,0))) -> Raymond Ross | E36: =IF($A36="","",INDEX('Raw Data'!$F$2:$F$251,MATCH($A36,'Raw Data'!$T$2:$T$251,0))) -> Smartphone | F36: =IF($A36="","",INDEX('Raw Data'!$G$2:$G$251,MATCH($A36,'Raw Data'!$T$2:$T$251,0))) -> Electronics | G36: =IF($A36="","",INDEX('Raw Data'!$K$2:$K$251,MATCH($A36,'Raw Data'!$T$2:$T$251,0))) -> Central | H36: =IF($A36="","",INDEX('Raw Data'!$H$2:$H$251,MATCH($A36,'Raw Data'!$T$2:$T$251,0))) -> 4 | I36: =IF($A36="","",INDEX('Raw Data'!$N$2:$N$251,MATCH($A36,'Raw Data'!$T$2:$T$251,0))) -> 2799.96
A37: =IF(28<=$C$7,28,"") -> 28 | B37: =IF($A37="","",INDEX('Raw Data'!$A$2:$A$251,MATCH($A37,'Raw Data'!$T$2:$T$251,0))) -> TRX0009 | C37: =IF($A37="","",INDEX('Raw Data'!$B$2:$B$251,MATCH($A37,'Raw Data'!$T$2:$T$251,0))) -> 45588 | D37: =IF($A37="","",INDEX('Raw Data'!$D$2:$D$251,MATCH($A37,'Raw Data'!$T$2:$T$251,0))) -> Sarah Davis | E37: =IF($A37="","",INDEX('Raw Data'!$F$2:$F$251,MATCH($A37,'Raw Data'!$T$2:$T$251,0))) -> Smartphone | F37: =IF($A37="","",INDEX('Raw Data'!$G$2:$G$251,MATCH($A37,'Raw Data'!$T$2:$T$251,0))) -> Electronics | G37: =IF($A37="","",INDEX('Raw Data'!$K$2:$K$251,MATCH($A37,'Raw Data'!$T$2:$T$251,0))) -> Central | H37: =IF($A37="","",INDEX('Raw Data'!$H$2:$H$251,MATCH($A37,'Raw Data'!$T$2:$T$251,0))) -> 2 | I37: =IF($A37="","",INDEX('Raw Data'!$N$2:$N$251,MATCH($A37,'Raw Data'!$T$2:$T$251,0))) -> 1399.98
A38: =IF(29<=$C$7,29,"") -> 29 | B38: =IF($A38="","",INDEX('Raw Data'!$A$2:$A$251,MATCH($A38,'Raw Data'!$T$2:$T$251,0))) -> TRX0167 | C38: =IF($A38="","",INDEX('Raw Data'!$B$2:$B$251,MATCH($A38,'Raw Data'!$T$2:$T$251,0))) -> 45589 | D38: =IF($A38="","",INDEX('Raw Data'!$D$2:$D$251,MATCH($A38,'Raw Data'!$T$2:$T$251,0))) -> Betty Campbell | E38: =IF($A38="","",INDEX('Raw Data'!$F$2:$F$251,MATCH($A38,'Raw Data'!$T$2:$T$251,0))) -> Smartphone | F38: =IF($A38="","",INDEX('Raw Data'!$G$2:$G$251,MATCH($A38,'Raw Data'!$T$2:$T$251,0))) -> Electronics | G38: =IF($A38="","",INDEX('Raw Data'!$K$2:$K$251,MATCH($A38,'Raw Data'!$T$2:$T$251,0))) -> North | H38: =IF($A38="","",INDEX('Raw Data'!$H$2:$H$251,MATCH($A38,'Raw Data'!$T$2:$T$251,0))) -> 5 | I38: =IF($A38="","",INDEX('Raw Data'!$N$2:$N$251,MATCH($A38,'Raw Data'!$T$2:$T$251,0))) -> 3499.95
A39: =IF(30<=$C$7,30,"") -> 30 | B39: =IF($A39="","",INDEX('Raw Data'!$A$2:$A$251,MATCH($A39,'Raw Data'!$T$2:$T$251,0))) -> TRX0057 | C39: =IF($A39="","",INDEX('Raw Data'!$B$2:$B$251,MATCH($A39,'Raw Data'!$T$2:$T$251,0))) -> 45597 | D39: =IF($A39="","",INDEX('Raw Data'!$D$2:$D$251,MATCH($A39,'Raw Data'!$T$2:$T$251,0))) -> Paul Baker | E39: =IF($A39="","",INDEX('Raw Data'!$F$2:$F$251,MATCH($A39,'Raw Data'!$T$2:$T$251,0))) -> Monitor | F39: =IF($A39="","",INDEX('Raw Data'!$G$2:$G$251,MATCH($A39,'Raw Data'!$T$2:$T$251,0))) -> Electronics | G39: =IF($A39="","",INDEX('Raw Data'!$K$2:$K$251,MATCH($A39,'Raw Data'!$T$2:$T$251,0))) -> South | H39: =IF($A39="","",INDEX('Raw Data'!$H$2:$H$251,MATCH($A39,'Raw Data'!$T$2:$T$251,0))) -> 5 | I39: =IF($A39="","",INDEX('Raw Data'!$N$2:$N$251,MATCH($A39,'Raw Data'!$T$2:$T$251,0))) -> 1249.95
A40: =IF(31<=$C$7,31,"") -> 31 | B40: =IF($A40="","",INDEX('Raw Data'!$A$2:$A$251,MATCH($A40,'Raw Data'!$T$2:$T$251,0))) -> TRX0033 | C40: =IF($A40="","",INDEX('Raw Data'!$B$2:$B$251,MATCH($A40,'Raw Data'!$T$2:$T$251,0))) -> 45613 | D40: =IF($A40="","",INDEX('Raw Data'!$D$2:$D$251,MATCH($A40,'Raw Data'!$T$2:$T$251,0))) -> Mark Carter | E40: =IF($A40="","",INDEX('Raw Data'!$F$2:$F$251,MATCH($A40,'Raw Data'!$T$2:$T$251,0))) -> Smartphone | F40: =IF($A40="","",INDEX('Raw Data'!$G$2:$G$251,MATCH($A40,'Raw Data'!$T$2:$T$251,0))) -> Electronics | G40: =IF($A40="","",INDEX('Raw Data'!$K$2:$K$251,MATCH($A40,'Raw Data'!$T$2:$T$251,0))) -> West | H40: =IF($A40="","",INDEX('Raw Data'!$H$2:$H$251,MATCH($A40,'Raw Data'!$T$2:$T$251,0))) -> 2 | I40: =IF($A40="","",INDEX('Raw Data'!$N$2:$N$251,MATCH($A40,'Raw Data'!$T$2:$T$251,0))) -> 1399.98
A41: =IF(32<=$C$7,32,"") -> 32 | B41: =IF($A41="","",INDEX('Raw Data'!$A$2:$A$251,MATCH($A41,'Raw Data'!$T$2:$T$251,0))) -> TRX0148 | C41: =IF($A41="","",INDEX('Raw Data'!$B$2:$B$251,MATCH($A41,'Raw Data'!$T$2:$T$251,0))) -> 45619 | D41: =IF($A41="","",INDEX('Raw Data'!$D$2:$D$251,MATCH($A41,'Raw Data'!$T$2:$T$251,0))) -> Sarah Davis | E41: =IF($A41="","",INDEX('Raw Data'!$F$2:$F$251,MATCH($A41,'Raw Data'!$T$2:$T$251,0))) -> Smartphone | F41: =IF($A41="","",INDEX('Raw Data'!$G$2:$G$251,MATCH($A41,'Raw Data'!$T$2:$T$251,0))) -> Electronics | G41: =IF($A41="","",INDEX('Raw Data'!$K$2:$K$251,MATCH($A41,'Raw Data'!$T$2:$T$251,0))) -> West | H41: =IF($A41="","",INDEX('Raw Data'!$H$2:$H$251,MATCH($A41,'Raw Data'!$T$2:$T$251,0))) -> 3 | I41: =IF($A41="","",INDEX('Raw Data'!$N$2:$N$251,MATCH($A41,'Raw Data'!$T$2:$T$251,0))) -> 2099.97
A42: =IF(33<=$C$7,33,"") -> 33 | B42: =IF($A42="","",INDEX('Raw Data'!$A$2:$A$251,MATCH($A42,'Raw Data'!$T$2:$T$251,0))) -> TRX0012 | C42: =IF($A42="","",INDEX('Raw Data'!$B$2:$B$251,MATCH($A42,'Raw Data'!$T$2:$T$251,0))) -> 45622 | D42: =IF($A42="","",INDEX('Raw Data'!$D$2:$D$251,MATCH($A42,'Raw Data'!$T$2:$T$251,0))) -> Douglas Watson | E42: =IF($A42="","",INDEX('Raw Data'!$F$2:$F$251,MATCH($A42,'Raw Data'!$T$2:$T$251,0))) -> Monitor | F42: =IF($A42="","",INDEX('Raw Data'!$G$2:$G$251,MATCH($A42,'Raw Data'!$T$2:$T$251,0))) -> Electronics | G42: =IF($A42="","",INDEX('Raw Data'!$K$2:$K$251,MATCH($A42,'Raw Data'!$T$2:$T$251,0))) -> North | H42: =IF($A42="","",INDEX('Raw Data'!$H$2:$H$251,MATCH($A42,'Raw Data'!$T$2:$T$251,0))) -> 5 | I42: =IF($A42="","",INDEX('Raw Data'!$N$2:$N$251,MATCH($A42,'Raw Data'!$T$2:$T$251,0))) -> 1249.95
A43: =IF(34<=$C$7,34,"") -> 34 | B43: =IF($A43="","",INDEX('Raw Data'!$A$2:$A$251,MATCH($A43,'Raw Data'!$T$2:$T$251,0))) -> TRX0094 | C43: =IF($A43="","",INDEX('Raw Data'!$B$2:$B$251,MATCH($A43,'Raw Data'!$T$2:$T$251,0))) -> 45627 | D43: =IF($A43="","",INDEX('Raw Data'!$D$2:$D$251,MATCH($A43,'Raw Data'!$T$2:$T$251,0))) -> Charles Allen | E43: =IF($A43="","",INDEX('Raw Data'!$F$2:$F$251,MATCH($A43,'Raw Data'!$T$2:$T$251,0))) -> Monitor | F43: =IF($A43="","",INDEX('Raw Data'!$G$2:$G$251,MATCH($A43,'Raw Data'!$T$2:$T$251,0))) -> Electronics | G43: =IF($A43="","",INDEX('Raw Data'!$K$2:$K$251,MATCH($A43,'Raw Data'!$T$2:$T$251,0))) -> Central | H43: =IF($A43="","",INDEX('Raw Data'!$H$2:$H$251,MATCH($A43,'Raw Data'!$T$2:$T$251,0))) -> 5 | I43: =IF($A43="","",INDEX('Raw Data'!$N$2:$N$251,MATCH($A43,'Raw Data'!$T$2:$T$251,0))) -> 1249.95
A44: =IF(35<=$C$7,35,"") -> 35 | B44: =IF($A44="","",INDEX('Raw Data'!$A$2:$A$251,MATCH($A44,'Raw Data'!$T$2:$T$251,0))) -> TRX0201 | C44: =IF($A44="","",INDEX('Raw Data'!$B$2:$B$251,MATCH($A44,'Raw Data'!$T$2:$T$251,0))) -> 45627 | D44: =IF($A44="","",INDEX('Raw Data'!$D$2:$D$251,MATCH($A44,'Raw Data'!$T$2:$T$251,0))) -> Mark Carter | E44: =IF($A44="","",INDEX('Raw Data'!$F$2:$F$251,MATCH($A44,'Raw Data'!$T$2:$T$251,0))) -> Smartphone | F44: =IF($A44="","",INDEX('Raw Data'!$G$2:$G$251,MATCH($A44,'Raw Data'!$T$2:$T$251,0))) -> Electronics | G44: =IF($A44="","",INDEX('Raw Data'!$K$2:$K$251,MATCH($A44,'Raw Data'!$T$2:$T$251,0))) -> West | H44: =IF($A44="","",INDEX('Raw Data'!$H$2:$H$251,MATCH($A44,'Raw Data'!$T$2:$T$251,0))) -> 5 | I44: =IF($A44="","",INDEX('Raw Data'!$N$2:$N$251,MATCH($A44,'Raw Data'!$T$2:$T$251,0))) -> 3499.95
A45: =IF(36<=$C$7,36,"") -> 36 | B45: =IF($A45="","",INDEX('Raw Data'!$A$2:$A$251,MATCH($A45,'Raw Data'!$T$2:$T$251,0))) -> TRX0066 | C45: =IF($A45="","",INDEX('Raw Data'!$B$2:$B$251,MATCH($A45,'Raw Data'!$T$2:$T$251,0))) -> 45630 | D45: =IF($A45="","",INDEX('Raw Data'!$D$2:$D$251,MATCH($A45,'Raw Data'!$T$2:$T$251,0))) -> Dorothy Nelson | E45: =IF($A45="","",INDEX('Raw Data'!$F$2:$F$251,MATCH($A45,'Raw Data'!$T$2:$T$251,0))) -> Smartphone | F45: =IF($A45="","",INDEX('Raw Data'!$G$2:$G$251,MATCH($A45,'Raw Data'!$T$2:$T$251,0))) -> Electronics | G45: =IF($A45="","",INDEX('Raw Data'!$K$2:$K$251,MATCH($A45,'Raw Data'!$T$2:$T$251,0))) -> North | H45: =IF($A45="","",INDEX('Raw Data'!$H$2:$H$251,MATCH($A45,'Raw Data'!$T$2:$T$251,0))) -> 4 | I45: =IF($A45="","",INDEX('Raw Data'!$N$2:$N$251,MATCH($A45,'Raw Data'!$T$2:$T$251,0))) -> 2799.96
A46: =IF(37<=$C$7,37,"") -> 37 | B46: =IF($A46="","",INDEX('Raw Data'!$A$2:$A$251,MATCH($A46,'Raw Data'!$T$2:$T$251,0))) -> TRX0032 | C46: =IF($A46="","",INDEX('Raw Data'!$B$2:$B$251,MATCH($A46,'Raw Data'!$T$2:$T$251,0))) -> 45638 | D46: =IF($A46="","",INDEX('Raw Data'!$D$2:$D$251,MATCH($A46,'Raw Data'!$T$2:$T$251,0))) -> Peter Richardson | E46: =IF($A46="","",INDEX('Raw Data'!$F$2:$F$251,MATCH($A46,'Raw Data'!$T$2:$T$251,0))) -> Laptop | F46: =IF($A46="","",INDEX('Raw Data'!$G$2:$G$251,MATCH($A46,'Raw Data'!$T$2:$T$251,0))) -> Electronics | G46: =IF($A46="","",INDEX('Raw Data'!$K$2:$K$251,MATCH($A46,'Raw Data'!$T$2:$T$251,0))) -> North | H46: =IF($A46="","",INDEX('Raw Data'!$H$2:$H$251,MATCH($A46,'Raw Data'!$T$2:$T$251,0))) -> 2 | I46: =IF($A46="","",INDEX('Raw Data'!$N$2:$N$251,MATCH($A46,'Raw Data'!$T$2:$T$251,0))) -> 1799.98
A47: =IF(38<=$C$7,38,"") -> 38 | B47: =IF($A47="","",INDEX('Raw Data'!$A$2:$A$251,MATCH($A47,'Raw Data'!$T$2:$T$251,0))) -> TRX0163 | C47: =IF($A47="","",INDEX('Raw Data'!$B$2:$B$251,MATCH($A47,'Raw Data'!$T$2:$T$251,0))) -> 45645 | D47: =IF($A47="","",INDEX('Raw Data'!$D$2:$D$251,MATCH($A47,'Raw Data'!$T$2:$T$251,0))) -> Daniel King | E47: =IF($A47="","",INDEX('Raw Data'!$F$2:$F$251,MATCH($A47,'Raw Data'!$T$2:$T$251,0))) -> Laptop | F47: =IF($A47="","",INDEX('Raw Data'!$G$2:$G$251,MATCH($A47,'Raw Data'!$T$2:$T$251,0))) -> Electronics | G47: =IF($A47="","",INDEX('Raw Data'!$K$2:$K$251,MATCH($A47,'Raw Data'!$T$2:$T$251,0))) -> East | H47: =IF($A47="","",INDEX('Raw Data'!$H$2:$H$251,MATCH($A47,'Raw Data'!$T$2:$T$251,0))) -> 5 | I47: =IF($A47="","",INDEX('Raw Data'!$N$2:$N$251,MATCH($A47,'Raw Data'!$T$2:$T$251,0))) -> 4499.95
A48: =IF(39<=$C$7,39,"") -> 39 | B48: =IF($A48="","",INDEX('Raw Data'!$A$2:$A$251,MATCH($A48,'Raw Data'!$T$2:$T$251,0))) -> TRX0125 | C48: =IF($A48="","",INDEX('Raw Data'!$B$2:$B$251,MATCH($A48,'Raw Data'!$T$2:$T$251,0))) -> 45666 | D48: =IF($A48="","",INDEX('Raw Data'!$D$2:$D$251,MATCH($A48,'Raw Data'!$T$2:$T$251,0))) -> Karen Hill | E48: =IF($A48="","",INDEX('Raw Data'!$F$2:$F$251,MATCH($A48,'Raw Data'!$T$2:$T$251,0))) -> Smartphone | F48: =IF($A48="","",INDEX('Raw Data'!$G$2:$G$251,MATCH($A48,'Raw Data'!$T$2:$T$251,0))) -> Electronics | G48: =IF($A48="","",INDEX('Raw Data'!$K$2:$K$251,MATCH($A48,'Raw Data'!$T$2:$T$251,0))) -> Central | H48: =IF($A48="","",INDEX('Raw Data'!$H$2:$H$251,MATCH($A48,'Raw Data'!$T$2:$T$251,0))) -> 3 | I48: =IF($A48="","",INDEX('Raw Data'!$N$2:$N$251,MATCH($A48,'Raw Data'!$T$2:$T$251,0))) -> 2099.97
A49: =IF(40<=$C$7,40,"") -> 40 | B49: =IF($A49="","",INDEX('Raw Data'!$A$2:$A$251,MATCH($A49,'Raw Data'!$T$2:$T$251,0))) -> TRX0243 | C49: =IF($A49="","",INDEX('Raw Data'!$B$2:$B$251,MATCH($A49,'Raw Data'!$T$2:$T$251,0))) -> 45667 | D49: =IF($A49="","",INDEX('Raw Data'!$D$2:$D$251,MATCH($A49,'Raw Data'!$T$2:$T$251,0))) -> Virginia Sanders | E49: =IF($A49="","",INDEX('Raw Data'!$F$2:$F$251,MATCH($A49,'Raw Data'!$T$2:$T$251,0))) -> Monitor | F49: =IF($A49="","",INDEX('Raw Data'!$G$2:$G$251,MATCH($A49,'Raw Data'!$T$2:$T$251,0))) -> Electronics | G49: =IF($A49="","",INDEX('Raw Data'!$K$2:$K$251,MATCH($A49,'Raw Data'!$T$2:$T$251,0))) -> South | H49: =IF($A49="","",INDEX('Raw Data'!$H$2:$H$251,MATCH($A49,'Raw Data'!$T$2:$T$251,0))) -> 5 | I49: =IF($A49="","",INDEX('Raw Data'!$N$2:$N$251,MATCH($A49,'Raw Data'!$T$2:$T$251,0))) -> 1249.95
A50: =IF(41<=$C$7,41,"") -> 41 | B50: =IF($A50="","",INDEX('Raw Data'!$A$2:$A$251,MATCH($A50,'Raw Data'!$T$2:$T$251,0))) -> TRX0238 | C50: =IF($A50="","",INDEX('Raw Data'!$B$2:$B$251,MATCH($A50,'Raw Data'!$T$2:$T$251,0))) -> 45668 | D50: =IF($A50="","",INDEX('Raw Data'!$D$2:$D$251,MATCH($A50,'Raw Data'!$T$2:$T$251,0))) -> Michelle Rogers | E50: =IF($A50="","",INDEX('Raw Data'!$F$2:$F$251,MATCH($A50,'Raw Data'!$T$2:$T$251,0))) -> Smartphone | F50: =IF($A50="","",INDEX('Raw Data'!$G$2:$G$251,MATCH($A50,'Raw Data'!$T$2:$T$251,0))) -> Electronics | G50: =IF($A50="","",INDEX('Raw Data'!$K$2:$K$251,MATCH($A50,'Raw Data'!$T$2:$T$251,0))) -> North | H50: =IF($A50="","",INDEX('Raw Data'!$H$2:$H$251,MATCH($A50,'Raw Data'!$T$2:$T$251,0))) -> 3 | I50: =IF($A50="","",INDEX('Raw Data'!$N$2:$N$251,MATCH($A50,'Raw Data'!$T$2:$T$251,0))) -> 2099.97
A51: =IF(42<=$C$7,42,"") -> 42 | B51: =IF($A51="","",INDEX('Raw Data'!$A$2:$A$251,MATCH($A51,'Raw Data'!$T$2:$T$251,0))) -> TRX0030 | C51: =IF($A51="","",INDEX('Raw Data'!$B$2:$B$251,MATCH($A51,'Raw Data'!$T$2:$T$251,0))) -> 45686 | D51: =IF($A51="","",INDEX('Raw Data'!$D$2:$D$251,MATCH($A51,'Raw Data'!$T$2:$T$251,0))) -> William White | E51: =IF($A51="","",INDEX('Raw Data'!$F$2:$F$251,MATCH($A51,'Raw Data'!$T$2:$T$251,0))) -> Laptop | F51: =IF($A51="","",INDEX('Raw Data'!$G$2:$G$251,MATCH($A51,'Raw Data'!$T$2:$T$251,0))) -> Electronics | G51: =IF($A51="","",INDEX('Raw Data'!$K$2:$K$251,MATCH($A51,'Raw Data'!$T$2:$T$251,0))) -> Central | H51: =IF($A51="","",INDEX('Raw Data'!$H$2:$H$251,MATCH($A51,'Raw Data'!$T$2:$T$251,0))) -> 4 | I51: =IF($A51="","",INDEX('Raw Data'!$N$2:$N$251,MATCH($A51,'Raw Data'!$T$2:$T$251,0))) -> 3599.96
A52: =IF(43<=$C$7,43,"") -> 43 | B52: =IF($A52="","",INDEX('Raw Data'!$A$2:$A$251,MATCH($A52,'Raw Data'!$T$2:$T$251,0))) -> TRX0188 | C52: =IF($A52="","",INDEX('Raw Data'!$B$2:$B$251,MATCH($A52,'Raw Data'!$T$2:$T$251,0))) -> 45686 | D52: =IF($A52="","",INDEX('Raw Data'!$D$2:$D$251,MATCH($A52,'Raw Data'!$T$2:$T$251,0))) -> Douglas Watson | E52: =IF($A52="","",INDEX('Raw Data'!$F$2:$F$251,MATCH($A52,'Raw Data'!$T$2:$T$251,0))) -> Smartphone | F52: =IF($A52="","",INDEX('Raw Data'!$G$2:$G$251,MATCH($A52,'Raw Data'!$T$2:$T$251,0))) -> Electronics | G52: =IF($A52="","",INDEX('Raw Data'!$K$2:$K$251,MATCH($A52,'Raw Data'!$T$2:$T$251,0))) -> Central | H52: =IF($A52="","",INDEX('Raw Data'!$H$2:$H$251,MATCH($A52,'Raw Data'!$T$2:$T$251,0))) -> 2 | I52: =IF($A52="","",INDEX('Raw Data'!$N$2:$N$251,MATCH($A52,'Raw Data'!$T$2:$T$251,0))) -> 1399.98
A53: =IF(44<=$C$7,44,"") -> 44 | B53: =IF($A53="","",INDEX('Raw Data'!$A$2:$A$251,MATCH($A53,'Raw Data'!$T$2:$T$251,0))) -> TRX0010 | C53: =IF($A53="","",INDEX('Raw Data'!$B$2:$B$251,MATCH($A53,'Raw Data'!$T$2:$T$251,0))) -> 45688 | D53: =IF($A53="","",INDEX('Raw Data'!$D$2:$D$251,MATCH($A53,'Raw Data'!$T$2:$T$251,0))) -> Karen Hill | E53: =IF($A53="","",INDEX('Raw Data'!$F$2:$F$251,MATCH($A53,'Raw Data'!$T$2:$T$251,0))) -> Smartphone | F53: =IF($A53="","",INDEX('Raw Data'!$G$2:$G$251,MATCH($A53,'Raw Data'!$T$2:$T$251,0))) -> Electronics | G53: =IF($A53="","",INDEX('Raw Data'!$K$2:$K$251,MATCH($A53,'Raw Data'!$T$2:$T$251,0))) -> West | H53: =IF($A53="","",INDEX('Raw Data'!$H$2:$H$251,MATCH($A53,'Raw Data'!$T$2:$T$251,0))) -> 4 | I53: =IF($A53="","",INDEX('Raw Data'!$N$2:$N$251,MATCH($A53,'Raw Data'!$T$2:$T$251,0))) -> 2799.96
A54: =IF(45<=$C$7,45,"") -> 45 | B54: =IF($A54="","",INDEX('Raw Data'!$A$2:$A$251,MATCH($A54,'Raw Data'!$T$2:$T$251,0))) -> TRX0179 | C54: =IF($A54="","",INDEX('Raw Data'!$B$2:$B$251,MATCH($A54,'Raw Data'!$T$2:$T$251,0))) -> 45707 | D54: =IF($A54="","",INDEX('Raw Data'!$D$2:$D$251,MATCH($A54,'Raw Data'!$T$2:$T$251,0))) -> Edward Mitchell | E54: =IF($A54="","",INDEX('Raw Data'!$F$2:$F$251,MATCH($A54,'Raw Data'!$T$2:$T$251,0))) -> Smartphone | F54: =IF($A54="","",INDEX('Raw Data'!$G$2:$G$251,MATCH($A54,'Raw Data'!$T$2:$T$251,0))) -> Electronics | G54: =IF($A54="","",INDEX('Raw Data'!$K$2:$K$251,MATCH($A54,'Raw Data'!$T$2:$T$251,0))) -> South | H54: =IF($A54="","",INDEX('Raw Data'!$H$2:$H$251,MATCH($A54,'Raw Data'!$T$2:$T$251,0))) -> 5 | I54: =IF($A54="","",INDEX('Raw Data'!$N$2:$N$251,MATCH($A54,'Raw Data'!$T$2:$T$251,0))) -> 3499.95
A55: =IF(46<=$C$7,46,"") -> 46 | B55: =IF($A55="","",INDEX('Raw Data'!$A$2:$A$251,MATCH($A55,'Raw Data'!$T$2:$T$251,0))) -> TRX0214 | C55: =IF($A55="","",INDEX('Raw Data'!$B$2:$B$251,MATCH($A55,'Raw Data'!$T$2:$T$251,0))) -> 45708 | D55: =IF($A55="","",INDEX('Raw Data'!$D$2:$D$251,MATCH($A55,'Raw Data'!$T$2:$T$251,0))) -> Barbara Young | E55: =IF($A55="","",INDEX('Raw Data'!$F$2:$F$251,MATCH($A55,'Raw Data'!$T$2:$T$251,0))) -> Laptop | F55: =IF($A55="","",INDEX('Raw Data'!$G$2:$G$251,MATCH($A55,'Raw Data'!$T$2:$T$251,0))) -> Electronics | G55: =IF($A55="","",INDEX('Raw Data'!$K$2:$K$251,MATCH($A55,'Raw Data'!$T$2:$T$251,0))) -> East | H55: =IF($A55="","",INDEX('Raw Data'!$H$2:$H$251,MATCH($A55,'Raw Data'!$T$2:$T$251,0))) -> 3 | I55: =IF($A55="","",INDEX('Raw Data'!$N$2:$N$251,MATCH($A55,'Raw Data'!$T$2:$T$251,0))) -> 2699.97
A56: =IF(47<=$C$7,47,"") -> 47 | B56: =IF($A56="","",INDEX('Raw Data'!$A$2:$A$251,MATCH($A56,'Raw Data'!$T$2:$T$251,0))) -> TRX0226 | C56: =IF($A56="","",INDEX('Raw Data'!$B$2:$B$251,MATCH($A56,'Raw Data'!$T$2:$T$251,0))) -> 45720 | D56: =IF($A56="","",INDEX('Raw Data'!$D$2:$D$251,MATCH($A56,'Raw Data'!$T$2:$T$251,0))) -> Lawrence Reed | E56: =IF($A56="","",INDEX('Raw Data'!$F$2:$F$251,MATCH($A56,'Raw Data'!$T$2:$T$251,0))) -> Smartphone | F56: =IF($A56="","",INDEX('Raw Data'!$G$2:$G$251,MATCH($A56,'Raw Data'!$T$2:$T$251,0))) -> Electronics | G56: =IF($A56="","",INDEX('Raw Data'!$K$2:$K$251,MATCH($A56,'Raw Data'!$T$2:$T$251,0))) -> East | H56: =IF($A56="","",INDEX('Raw Data'!$H$2:$H$251,MATCH($A56,'Raw Data'!$T$2:$T$251,0))) -> 5 | I56: =IF($A56="","",INDEX('Raw Data'!$N$2:$N$251,MATCH($A56,'Raw Data'!$T$2:$T$251,0))) -> 3499.95
A57: =IF(48<=$C$7,48,"") -> 48 | B57: =IF($A57="","",INDEX('Raw Data'!$A$2:$A$251,MATCH($A57,'Raw Data'!$T$2:$T$251,0))) -> TRX0175 | C57: =IF($A57="","",INDEX('Raw Data'!$B$2:$B$251,MATCH($A57,'Raw Data'!$T$2:$T$251,0))) -> 45723 | D57: =IF($A57="","",INDEX('Raw Data'!$D$2:$D$251,MATCH($A57,'Raw Data'!$T$2:$T$251,0))) -> Helen Roberts | E57: =IF($A57="","",INDEX('Raw Data'!$F$2:$F$251,MATCH($A57,'Raw Data'!$T$2:$T$251,0))) -> Monitor | F57: =IF($A57="","",INDEX('Raw Data'!$G$2:$G$251,MATCH($A57,'Raw Data'!$T$2:$T$251,0))) -> Electronics | G57: =IF($A57="","",INDEX('Raw Data'!$K$2:$K$251,MATCH($A57,'Raw Data'!$T$2:$T$251,0))) -> East | H57: =IF($A57="","",INDEX('Raw Data'!$H$2:$H$251,MATCH($A57,'Raw Data'!$T$2:$T$251,0))) -> 5 | I57: =IF($A57="","",INDEX('Raw Data'!$N$2:$N$251,MATCH($A57,'Raw Data'!$T$2:$T$251,0))) -> 1249.95
A58: =IF(49<=$C$7,49,"") -> 49 | B58: =IF($A58="","",INDEX('Raw Data'!$A$2:$A$251,MATCH($A58,'Raw Data'!$T$2:$T$251,0))) -> TRX0016 | C58: =IF($A58="","",INDEX('Raw Data'!$B$2:$B$251,MATCH($A58,'Raw Data'!$T$2:$T$251,0))) -> 45724 | D58: =IF($A58="","",INDEX('Raw Data'!$D$2:$D$251,MATCH($A58,'Raw Data'!$T$2:$T$251,0))) -> Harry Morgan | E58: =IF($A58="","",INDEX('Raw Data'!$F$2:$F$251,MATCH($A58,'Raw Data'!$T$2:$T$251,0))) -> Laptop | F58: =IF($A58="","",INDEX('Raw Data'!$G$2:$G$251,MATCH($A58,'Raw Data'!$T$2:$T$251,0))) -> Electronics | G58: =IF($A58="","",INDEX('Raw Data'!$K$2:$K$251,MATCH($A58,'Raw Data'!$T$2:$T$251,0))) -> East | H58: =IF($A58="","",INDEX('Raw Data'!$H$2:$H$251,MATCH($A58,'Raw Data'!$T$2:$T$251,0))) -> 5 | I58: =IF($A58="","",INDEX('Raw Data'!$N$2:$N$251,MATCH($A58,'Raw Data'!$T$2:$T$251,0))) -> 4499.95
A59: =IF(50<=$C$7,50,"") -> 50 | B59: =IF($A59="","",INDEX('Raw Data'!$A$2:$A$251,MATCH($A59,'Raw Data'!$T$2:$T$251,0))) -> TRX0124 | C59: =IF($A59="","",INDEX('Raw Data'!$B$2:$B$251,MATCH($A59,'Raw Data'!$T$2:$T$251,0))) -> 45737 | D59: =IF($A59="","",INDEX('Raw Data'!$D$2:$D$251,MATCH($A59,'Raw Data'!$T$2:$T$251,0))) -> Sharon Butler | E59: =IF($A59="","",INDEX('Raw Data'!$F$2:$F$251,MATCH($A59,'Raw Data'!$T$2:$T$251,0))) -> Laptop | F59: =IF($A59="","",INDEX('Raw Data'!$G$2:$G$251,MATCH($A59,'Raw Data'!$T$2:$T$251,0))) -> Electronics | G59: =IF($A59="","",INDEX('Raw Data'!$K$2:$K$251,MATCH($A59,'Raw Data'!$T$2:$T$251,0))) -> North | H59: =IF($A59="","",INDEX('Raw Data'!$H$2:$H$251,MATCH($A59,'Raw Data'!$T$2:$T$251,0))) -> 3 | I59: =IF($A59="","",INDEX('Raw Data'!$N$2:$N$251,MATCH($A59,'Raw Data'!$T$2:$T$251,0))) -> 2699.97
A60: =IF(51<=$C$7,51,"") -> 51 | B60: =IF($A60="","",INDEX('Raw Data'!$A$2:$A$251,MATCH($A60,'Raw Data'!$T$2:$T$251,0))) -> TRX0013 | C60: =IF($A60="","",INDEX('Raw Data'!$B$2:$B$251,MATCH($A60,'Raw Data'!$T$2:$T$251,0))) -> 45737 | D60: =IF($A60="","",INDEX('Raw Data'!$D$2:$D$251,MATCH($A60,'Raw Data'!$T$2:$T$251,0))) -> Dorothy Nelson | E60: =IF($A60="","",INDEX('Raw Data'!$F$2:$F$251,MATCH($A60,'Raw Data'!$T$2:$T$251,0))) -> Laptop | F60: =IF($A60="","",INDEX('Raw Data'!$G$2:$G$251,MATCH($A60,'Raw Data'!$T$2:$T$251,0))) -> Electronics | G60: =IF($A60="","",INDEX('Raw Data'!$K$2:$K$251,MATCH($A60,'Raw Data'!$T$2:$T$251,0))) -> North | H60: =IF($A60="","",INDEX('Raw Data'!$H$2:$H$251,MATCH($A60,'Raw Data'!$T$2:$T$251,0))) -> 3 | I60: =IF($A60="","",INDEX('Raw Data'!$N$2:$N$251,MATCH($A60,'Raw Data'!$T$2:$T$251,0))) -> 2699.97
A61: =IF(52<=$C$7,52,"") -> 52 | B61: =IF($A61="","",INDEX('Raw Data'!$A$2:$A$251,MATCH($A61,'Raw Data'!$T$2:$T$251,0))) -> TRX0068 | C61: =IF($A61="","",INDEX('Raw Data'!$B$2:$B$251,MATCH($A61,'Raw Data'!$T$2:$T$251,0))) -> 45748 | D61: =IF($A61="","",INDEX('Raw Data'!$D$2:$D$251,MATCH($A61,'Raw Data'!$T$2:$T$251,0))) -> Cynthia Price | E61: =IF($A61="","",INDEX('Raw Data'!$F$2:$F$251,MATCH($A61,'Raw Data'!$T$2:$T$251,0))) -> Smartphone | F61: =IF($A61="","",INDEX('Raw Data'!$G$2:$G$251,MATCH($A61,'Raw Data'!$T$2:$T$251,0))) -> Electronics | G61: =IF($A61="","",INDEX('Raw Data'!$K$2:$K$251,MATCH($A61,'Raw Data'!$T$2:$T$251,0))) -> North | H61: =IF($A61="","",INDEX('Raw Data'!$H$2:$H$251,MATCH($A61,'Raw Data'!$T$2:$T$251,0))) -> 2 | I61: =IF($A61="","",INDEX('Raw Data'!$N$2:$N$251,MATCH($A61,'Raw Data'!$T$2:$T$251,0))) -> 1399.98
A62: =IF(53<=$C$7,53,"") -> 53 | B62: =IF($A62="","",INDEX('Raw Data'!$A$2:$A$251,MATCH($A62,'Raw Data'!$T$2:$T$251,0))) -> TRX0144 | C62: =IF($A62="","",INDEX('Raw Data'!$B$2:$B$251,MATCH($A62,'Raw Data'!$T$2:$T$251,0))) -> 45749 | D62: =IF($A62="","",INDEX('Raw Data'!$D$2:$D$251,MATCH($A62,'Raw Data'!$T$2:$T$251,0))) -> Edward Mitchell | E62: =IF($A62="","",INDEX('Raw Data'!$F$2:$F$251,MATCH($A62,'Raw Data'!$T$2:$T$251,0))) -> Laptop | F62: =IF($A62="","",INDEX('Raw Data'!$G$2:$G$251,MATCH($A62,'Raw Data'!$T$2:$T$251,0))) -> Electronics | G62: =IF($A62="","",INDEX('Raw Data'!$K$2:$K$251,MATCH($A62,'Raw Data'!$T$2:$T$251,0))) -> Central | H62: =IF($A62="","",INDEX('Raw Data'!$H$2:$H$251,MATCH($A62,'Raw Data'!$T$2:$T$251,0))) -> 3 | I62: =IF($A62="","",INDEX('Raw Data'!$N$2:$N$251,MATCH($A62,'Raw Data'!$T$2:$T$251,0))) -> 2699.97
A63: =IF(54<=$C$7,54,"") -> 54 | B63: =IF($A63="","",INDEX('Raw Data'!$A$2:$A$251,MATCH($A63,'Raw Data'!$T$2:$T$251,0))) -> TRX0120 | C63: =IF($A63="","",INDEX('Raw Data'!$B$2:$B$251,MATCH($A63,'Raw Data'!$T$2:$T$251,0))) -> 45758 | D63: =IF($A63="","",INDEX('Raw Data'!$D$2:$D$251,MATCH($A63,'Raw Data'!$T$2:$T$251,0))) -> Douglas Watson | E63: =IF($A63="","",INDEX('Raw Data'!$F$2:$F$251,MATCH($A63,'Raw Data'!$T$2:$T$251,0))) -> Smartphone | F63: =IF($A63="","",INDEX('Raw Data'!$G$2:$G$251,MATCH($A63,'Raw Data'!$T$2:$T$251,0))) -> Electronics | G63: =IF($A63="","",INDEX('Raw Data'!$K$2:$K$251,MATCH($A63,'Raw Data'!$T$2:$T$251,0))) -> North | H63: =IF($A63="","",INDEX('Raw Data'!$H$2:$H$251,MATCH($A63,'Raw Data'!$T$2:$T$251,0))) -> 3 | I63: =IF($A63="","",INDEX('Raw Data'!$N$2:$N$251,MATCH($A63,'Raw Data'!$T$2:$T$251,0))) -> 2099.97
A64: =IF(55<=$C$7,55,"") | B64: =IF($A64="","",INDEX('Raw Data'!$A$2:$A$251,MATCH($A64,'Raw Data'!$T$2:$T$251,0))) | C64: =IF($A64="","",INDEX('Raw Data'!$B$2:$B$251,MATCH($A64,'Raw Data'!$T$2:$T$251,0))) | D64: =IF($A64="","",INDEX('Raw Data'!$D$2:$D$251,MATCH($A64,'Raw Data'!$T$2:$T$251,0))) | E64: =IF($A64="","",INDEX('Raw Data'!$F$2:$F$251,MATCH($A64,'Raw Data'!$T$2:$T$251,0))) | F64: =IF($A64="","",INDEX('Raw Data'!$G$2:$G$251,MATCH($A64,'Raw Data'!$T$2:$T$251,0))) | G64: =IF($A64="","",INDEX('Raw Data'!$K$2:$K$251,MATCH($A64,'Raw Data'!$T$2:$T$251,0))) | H64: =IF($A64="","",INDEX('Raw Data'!$H$2:$H$251,MATCH($A64,'Raw Data'!$T$2:$T$251,0))) | I64: =IF($A64="","",INDEX('Raw Data'!$N$2:$N$251,MATCH($A64,'Raw Data'!$T$2:$T$251,0)))
A65: =IF(56<=$C$7,56,"") | B65: =IF($A65="","",INDEX('Raw Data'!$A$2:$A$251,MATCH($A65,'Raw Data'!$T$2:$T$251,0))) | C65: =IF($A65="","",INDEX('Raw Data'!$B$2:$B$251,MATCH($A65,'Raw Data'!$T$2:$T$251,0))) | D65: =IF($A65="","",INDEX('Raw Data'!$D$2:$D$251,MATCH($A65,'Raw Data'!$T$2:$T$251,0))) | E65: =IF($A65="","",INDEX('Raw Data'!$F$2:$F$251,MATCH($A65,'Raw Data'!$T$2:$T$251,0))) | F65: =IF($A65="","",INDEX('Raw Data'!$G$2:$G$251,MATCH($A65,'Raw Data'!$T$2:$T$251,0))) | G65: =IF($A65="","",INDEX('Raw Data'!$K$2:$K$251,MATCH($A65,'Raw Data'!$T$2:$T$251,0))) | H65: =IF($A65="","",INDEX('Raw Data'!$H$2:$H$251,MATCH($A65,'Raw Data'!$T$2:$T$251,0))) | I65: =IF($A65="","",INDEX('Raw Data'!$N$2:$N$251,MATCH($A65,'Raw Data'!$T$2:$T$251,0)))
A66: =IF(57<=$C$7,57,"") | B66: =IF($A66="","",INDEX('Raw Data'!$A$2:$A$251,MATCH($A66,'Raw Data'!$T$2:$T$251,0))) | C66: =IF($A66="","",INDEX('Raw Data'!$B$2:$B$251,MATCH($A66,'Raw Data'!$T$2:$T$251,0))) | D66: =IF($A66="","",INDEX('Raw Data'!$D$2:$D$251,MATCH($A66,'Raw Data'!$T$2:$T$251,0))) | E66: =IF($A66="","",INDEX('Raw Data'!$F$2:$F$251,MATCH($A66,'Raw Data'!$T$2:$T$251,0))) | F66: =IF($A66="","",INDEX('Raw Data'!$G$2:$G$251,MATCH($A66,'Raw Data'!$T$2:$T$251,0))) | G66: =IF($A66="","",INDEX('Raw Data'!$K$2:$K$251,MATCH($A66,'Raw Data'!$T$2:$T$251,0))) | H66: =IF($A66="","",INDEX('Raw Data'!$H$2:$H$251,MATCH($A66,'Raw Data'!$T$2:$T$251,0))) | I66: =IF($A66="","",INDEX('Raw Data'!$N$2:$N$251,MATCH($A66,'Raw Data'!$T$2:$T$251,0)))
A67: =IF(58<=$C$7,58,"") | B67: =IF($A67="","",INDEX('Raw Data'!$A$2:$A$251,MATCH($A67,'Raw Data'!$T$2:$T$251,0))) | C67: =IF($A67="","",INDEX('Raw Data'!$B$2:$B$251,MATCH($A67,'Raw Data'!$T$2:$T$251,0))) | D67: =IF($A67="","",INDEX('Raw Data'!$D$2:$D$251,MATCH($A67,'Raw Data'!$T$2:$T$251,0))) | E67: =IF($A67="","",INDEX('Raw Data'!$F$2:$F$251,MATCH($A67,'Raw Data'!$T$2:$T$251,0))) | F67: =IF($A67="","",INDEX('Raw Data'!$G$2:$G$251,MATCH($A67,'Raw Data'!$T$2:$T$251,0))) | G67: =IF($A67="","",INDEX('Raw Data'!$K$2:$K$251,MATCH($A67,'Raw Data'!$T$2:$T$251,0))) | H67: =IF($A67="","",INDEX('Raw Data'!$H$2:$H$251,MATCH($A67,'Raw Data'!$T$2:$T$251,0))) | I67: =IF($A67="","",INDEX('Raw Data'!$N$2:$N$251,MATCH($A67,'Raw Data'!$T$2:$T$251,0)))
A68: =IF(59<=$C$7,59,"") | B68: =IF($A68="","",INDEX('Raw Data'!$A$2:$A$251,MATCH($A68,'Raw Data'!$T$2:$T$251,0))) | C68: =IF($A68="","",INDEX('Raw Data'!$B$2:$B$251,MATCH($A68,'Raw Data'!$T$2:$T$251,0))) | D68: =IF($A68="","",INDEX('Raw Data'!$D$2:$D$251,MATCH($A68,'Raw Data'!$T$2:$T$251,0))) | E68: =IF($A68="","",INDEX('Raw Data'!$F$2:$F$251,MATCH($A68,'Raw Data'!$T$2:$T$251,0))) | F68: =IF($A68="","",INDEX('Raw Data'!$G$2:$G$251,MATCH($A68,'Raw Data'!$T$2:$T$251,0))) | G68: =IF($A68="","",INDEX('Raw Data'!$K$2:$K$251,MATCH($A68,'Raw Data'!$T$2:$T$251,0))) | H68: =IF($A68="","",INDEX('Raw Data'!$H$2:$H$251,MATCH($A68,'Raw Data'!$T$2:$T$251,0))) | I68: =IF($A68="","",INDEX('Raw Data'!$N$2:$N$251,MATCH($A68,'Raw Data'!$T$2:$T$251,0)))
A69: =IF(60<=$C$7,60,"") | B69: =IF($A69="","",INDEX('Raw Data'!$A$2:$A$251,MATCH($A69,'Raw Data'!$T$2:$T$251,0))) | C69: =IF($A69="","",INDEX('Raw Data'!$B$2:$B$251,MATCH($A69,'Raw Data'!$T$2:$T$251,0))) | D69: =IF($A69="","",INDEX('Raw Data'!$D$2:$D$251,MATCH($A69,'Raw Data'!$T$2:$T$251,0))) | E69: =IF($A69="","",INDEX('Raw Data'!$F$2:$F$251,MATCH($A69,'Raw Data'!$T$2:$T$251,0))) | F69: =IF($A69="","",INDEX('Raw Data'!$G$2:$G$251,MATCH($A69,'Raw Data'!$T$2:$T$251,0))) | G69: =IF($A69="","",INDEX('Raw Data'!$K$2:$K$251,MATCH($A69,'Raw Data'!$T$2:$T$251,0))) | H69: =IF($A69="","",INDEX('Raw Data'!$H$2:$H$251,MATCH($A69,'Raw Data'!$T$2:$T$251,0))) | I69: =IF($A69="","",INDEX('Raw Data'!$N$2:$N$251,MATCH($A69,'Raw Data'!$T$2:$T$251,0)))
A70: =IF(61<=$C$7,61,"") | B70: =IF($A70="","",INDEX('Raw Data'!$A$2:$A$251,MATCH($A70,'Raw Data'!$T$2:$T$251,0))) | C70: =IF($A70="","",INDEX('Raw Data'!$B$2:$B$251,MATCH($A70,'Raw Data'!$T$2:$T$251,0))) | D70: =IF($A70="","",INDEX('Raw Data'!$D$2:$D$251,MATCH($A70,'Raw Data'!$T$2:$T$251,0))) | E70: =IF($A70="","",INDEX('Raw Data'!$F$2:$F$251,MATCH($A70,'Raw Data'!$T$2:$T$251,0))) | F70: =IF($A70="","",INDEX('Raw Data'!$G$2:$G$251,MATCH($A70,'Raw Data'!$T$2:$T$251,0))) | G70: =IF($A70="","",INDEX('Raw Data'!$K$2:$K$251,MATCH($A70,'Raw Data'!$T$2:$T$251,0))) | H70: =IF($A70="","",INDEX('Raw Data'!$H$2:$H$251,MATCH($A70,'Raw Data'!$T$2:$T$251,0))) | I70: =IF($A70="","",INDEX('Raw Data'!$N$2:$N$251,MATCH($A70,'Raw Data'!$T$2:$T$251,0)))
A71: =IF(62<=$C$7,62,"") | B71: =IF($A71="","",INDEX('Raw Data'!$A$2:$A$251,MATCH($A71,'Raw Data'!$T$2:$T$251,0))) | C71: =IF($A71="","",INDEX('Raw Data'!$B$2:$B$251,MATCH($A71,'Raw Data'!$T$2:$T$251,0))) | D71: =IF($A71="","",INDEX('Raw Data'!$D$2:$D$251,MATCH($A71,'Raw Data'!$T$2:$T$251,0))) | E71: =IF($A71="","",INDEX('Raw Data'!$F$2:$F$251,MATCH($A71,'Raw Data'!$T$2:$T$251,0))) | F71: =IF($A71="","",INDEX('Raw Data'!$G$2:$G$251,MATCH($A71,'Raw Data'!$T$2:$T$251,0))) | G71: =IF($A71="","",INDEX('Raw Data'!$K$2:$K$251,MATCH($A71,'Raw Data'!$T$2:$T$251,0))) | H71: =IF($A71="","",INDEX('Raw Data'!$H$2:$H$251,MATCH($A71,'Raw Data'!$T$2:$T$251,0))) | I71: =IF($A71="","",INDEX('Raw Data'!$N$2:$N$251,MATCH($A71,'Raw Data'!$T$2:$T$251,0)))
A72: =IF(63<=$C$7,63,"") | B72: =IF($A72="","",INDEX('Raw Data'!$A$2:$A$251,MATCH($A72,'Raw Data'!$T$2:$T$251,0))) | C72: =IF($A72="","",INDEX('Raw Data'!$B$2:$B$251,MATCH($A72,'Raw Data'!$T$2:$T$251,0))) | D72: =IF($A72="","",INDEX('Raw Data'!$D$2:$D$251,MATCH($A72,'Raw Data'!$T$2:$T$251,0))) | E72: =IF($A72="","",INDEX('Raw Data'!$F$2:$F$251,MATCH($A72,'Raw Data'!$T$2:$T$251,0))) | F72: =IF($A72="","",INDEX('Raw Data'!$G$2:$G$251,MATCH($A72,'Raw Data'!$T$2:$T$251,0))) | G72: =IF($A72="","",INDEX('Raw Data'!$K$2:$K$251,MATCH($A72,'Raw Data'!$T$2:$T$251,0))) | H72: =IF($A72="","",INDEX('Raw Data'!$H$2:$H$251,MATCH($A72,'Raw Data'!$T$2:$T$251,0))) | I72: =IF($A72="","",INDEX('Raw Data'!$N$2:$N$251,MATCH($A72,'Raw Data'!$T$2:$T$251,0)))
A73: =IF(64<=$C$7,64,"") | B73: =IF($A73="","",INDEX('Raw Data'!$A$2:$A$251,MATCH($A73,'Raw Data'!$T$2:$T$251,0))) | C73: =IF($A73="","",INDEX('Raw Data'!$B$2:$B$251,MATCH($A73,'Raw Data'!$T$2:$T$251,0))) | D73: =IF($A73="","",INDEX('Raw Data'!$D$2:$D$251,MATCH($A73,'Raw Data'!$T$2:$T$251,0))) | E73: =IF($A73="","",INDEX('Raw Data'!$F$2:$F$251,MATCH($A73,'Raw Data'!$T$2:$T$251,0))) | F73: =IF($A73="","",INDEX('Raw Data'!$G$2:$G$251,MATCH($A73,'Raw Data'!$T$2:$T$251,0))) | G73: =IF($A73="","",INDEX('Raw Data'!$K$2:$K$251,MATCH($A73,'Raw Data'!$T$2:$T$251,0))) | H73: =IF($A73="","",INDEX('Raw Data'!$H$2:$H$251,MATCH($A73,'Raw Data'!$T$2:$T$251,0))) | I73: =IF($A73="","",INDEX('Raw Data'!$N$2:$N$251,MATCH($A73,'Raw Data'!$T$2:$T$251,0)))
A74: =IF(65<=$C$7,65,"") | B74: =IF($A74="","",INDEX('Raw Data'!$A$2:$A$251,MATCH($A74,'Raw Data'!$T$2:$T$251,0))) | C74: =IF($A74="","",INDEX('Raw Data'!$B$2:$B$251,MATCH($A74,'Raw Data'!$T$2:$T$251,0))) | D74: =IF($A74="","",INDEX('Raw Data'!$D$2:$D$251,MATCH($A74,'Raw Data'!$T$2:$T$251,0))) | E74: =IF($A74="","",INDEX('Raw Data'!$F$2:$F$251,MATCH($A74,'Raw Data'!$T$2:$T$251,0))) | F74: =IF($A74="","",INDEX('Raw Data'!$G$2:$G$251,MATCH($A74,'Raw Data'!$T$2:$T$251,0))) | G74: =IF($A74="","",INDEX('Raw Data'!$K$2:$K$251,MATCH($A74,'Raw Data'!$T$2:$T$251,0))) | H74: =IF($A74="","",INDEX('Raw Data'!$H$2:$H$251,MATCH($A74,'Raw Data'!$T$2:$T$251,0))) | I74: =IF($A74="","",INDEX('Raw Data'!$N$2:$N$251,MATCH($A74,'Raw Data'!$T$2:$T$251,0)))
A75: =IF(66<=$C$7,66,"") | B75: =IF($A75="","",INDEX('Raw Data'!$A$2:$A$251,MATCH($A75,'Raw Data'!$T$2:$T$251,0))) | C75: =IF($A75="","",INDEX('Raw Data'!$B$2:$B$251,MATCH($A75,'Raw Data'!$T$2:$T$251,0))) | D75: =IF($A75="","",INDEX('Raw Data'!$D$2:$D$251,MATCH($A75,'Raw Data'!$T$2:$T$251,0))) | E75: =IF($A75="","",INDEX('Raw Data'!$F$2:$F$251,MATCH($A75,'Raw Data'!$T$2:$T$251,0))) | F75: =IF($A75="","",INDEX('Raw Data'!$G$2:$G$251,MATCH($A75,'Raw Data'!$T$2:$T$251,0))) | G75: =IF($A75="","",INDEX('Raw Data'!$K$2:$K$251,MATCH($A75,'Raw Data'!$T$2:$T$251,0))) | H75: =IF($A75="","",INDEX('Raw Data'!$H$2:$H$251,MATCH($A75,'Raw Data'!$T$2:$T$251,0))) | I75: =IF($A75="","",INDEX('Raw Data'!$N$2:$N$251,MATCH($A75,'Raw Data'!$T$2:$T$251,0)))
A76: =IF(67<=$C$7,67,"") | B76: =IF($A76="","",INDEX('Raw Data'!$A$2:$A$251,MATCH($A76,'Raw Data'!$T$2:$T$251,0))) | C76: =IF($A76="","",INDEX('Raw Data'!$B$2:$B$251,MATCH($A76,'Raw Data'!$T$2:$T$251,0))) | D76: =IF($A76="","",INDEX('Raw Data'!$D$2:$D$251,MATCH($A76,'Raw Data'!$T$2:$T$251,0))) | E76: =IF($A76="","",INDEX('Raw Data'!$F$2:$F$251,MATCH($A76,'Raw Data'!$T$2:$T$251,0))) | F76: =IF($A76="","",INDEX('Raw Data'!$G$2:$G$251,MATCH($A76,'Raw Data'!$T$2:$T$251,0))) | G76: =IF($A76="","",INDEX('Raw Data'!$K$2:$K$251,MATCH($A76,'Raw Data'!$T$2:$T$251,0))) | H76: =IF($A76="","",INDEX('Raw Data'!$H$2:$H$251,MATCH($A76,'Raw Data'!$T$2:$T$251,0))) | I76: =IF($A76="","",INDEX('Raw Data'!$N$2:$N$251,MATCH($A76,'Raw Data'!$T$2:$T$251,0)))
A77: =IF(68<=$C$7,68,"") | B77: =IF($A77="","",INDEX('Raw Data'!$A$2:$A$251,MATCH($A77,'Raw Data'!$T$2:$T$251,0))) | C77: =IF($A77="","",INDEX('Raw Data'!$B$2:$B$251,MATCH($A77,'Raw Data'!$T$2:$T$251,0))) | D77: =IF($A77="","",INDEX('Raw Data'!$D$2:$D$251,MATCH($A77,'Raw Data'!$T$2:$T$251,0))) | E77: =IF($A77="","",INDEX('Raw Data'!$F$2:$F$251,MATCH($A77,'Raw Data'!$T$2:$T$251,0))) | F77: =IF($A77="","",INDEX('Raw Data'!$G$2:$G$251,MATCH($A77,'Raw Data'!$T$2:$T$251,0))) | G77: =IF($A77="","",INDEX('Raw Data'!$K$2:$K$251,MATCH($A77,'Raw Data'!$T$2:$T$251,0))) | H77: =IF($A77="","",INDEX('Raw Data'!$H$2:$H$251,MATCH($A77,'Raw Data'!$T$2:$T$251,0))) | I77: =IF($A77="","",INDEX('Raw Data'!$N$2:$N$251,MATCH($A77,'Raw Data'!$T$2:$T$251,0)))
A78: =IF(69<=$C$7,69,"") | B78: =IF($A78="","",INDEX('Raw Data'!$A$2:$A$251,MATCH($A78,'Raw Data'!$T$2:$T$251,0))) | C78: =IF($A78="","",INDEX('Raw Data'!$B$2:$B$251,MATCH($A78,'Raw Data'!$T$2:$T$251,0))) | D78: =IF($A78="","",INDEX('Raw Data'!$D$2:$D$251,MATCH($A78,'Raw Data'!$T$2:$T$251,0))) | E78: =IF($A78="","",INDEX('Raw Data'!$F$2:$F$251,MATCH($A78,'Raw Data'!$T$2:$T$251,0))) | F78: =IF($A78="","",INDEX('Raw Data'!$G$2:$G$251,MATCH($A78,'Raw Data'!$T$2:$T$251,0))) | G78: =IF($A78="","",INDEX('Raw Data'!$K$2:$K$251,MATCH($A78,'Raw Data'!$T$2:$T$251,0))) | H78: =IF($A78="","",INDEX('Raw Data'!$H$2:$H$251,MATCH($A78,'Raw Data'!$T$2:$T$251,0))) | I78: =IF($A78="","",INDEX('Raw Data'!$N$2:$N$251,MATCH($A78,'Raw Data'!$T$2:$T$251,0)))
A79: =IF(70<=$C$7,70,"") | B79: =IF($A79="","",INDEX('Raw Data'!$A$2:$A$251,MATCH($A79,'Raw Data'!$T$2:$T$251,0))) | C79: =IF($A79="","",INDEX('Raw Data'!$B$2:$B$251,MATCH($A79,'Raw Data'!$T$2:$T$251,0))) | D79: =IF($A79="","",INDEX('Raw Data'!$D$2:$D$251,MATCH($A79,'Raw Data'!$T$2:$T$251,0))) | E79: =IF($A79="","",INDEX('Raw Data'!$F$2:$F$251,MATCH($A79,'Raw Data'!$T$2:$T$251,0))) | F79: =IF($A79="","",INDEX('Raw Data'!$G$2:$G$251,MATCH($A79,'Raw Data'!$T$2:$T$251,0))) | G79: =IF($A79="","",INDEX('Raw Data'!$K$2:$K$251,MATCH($A79,'Raw Data'!$T$2:$T$251,0))) | H79: =IF($A79="","",INDEX('Raw Data'!$H$2:$H$251,MATCH($A79,'Raw Data'!$T$2:$T$251,0))) | I79: =IF($A79="","",INDEX('Raw Data'!$N$2:$N$251,MATCH($A79,'Raw Data'!$T$2:$T$251,0)))
A80: =IF(71<=$C$7,71,"") | B80: =IF($A80="","",INDEX('Raw Data'!$A$2:$A$251,MATCH($A80,'Raw Data'!$T$2:$T$251,0))) | C80: =IF($A80="","",INDEX('Raw Data'!$B$2:$B$251,MATCH($A80,'Raw Data'!$T$2:$T$251,0))) | D80: =IF($A80="","",INDEX('Raw Data'!$D$2:$D$251,MATCH($A80,'Raw Data'!$T$2:$T$251,0))) | E80: =IF($A80="","",INDEX('Raw Data'!$F$2:$F$251,MATCH($A80,'Raw Data'!$T$2:$T$251,0))) | F80: =IF($A80="","",INDEX('Raw Data'!$G$2:$G$251,MATCH($A80,'Raw Data'!$T$2:$T$251,0))) | G80: =IF($A80="","",INDEX('Raw Data'!$K$2:$K$251,MATCH($A80,'Raw Data'!$T$2:$T$251,0))) | H80: =IF($A80="","",INDEX('Raw Data'!$H$2:$H$251,MATCH($A80,'Raw Data'!$T$2:$T$251,0))) | I80: =IF($A80="","",INDEX('Raw Data'!$N$2:$N$251,MATCH($A80,'Raw Data'!$T$2:$T$251,0)))
A81: =IF(72<=$C$7,72,"") | B81: =IF($A81="","",INDEX('Raw Data'!$A$2:$A$251,MATCH($A81,'Raw Data'!$T$2:$T$251,0))) | C81: =IF($A81="","",INDEX('Raw Data'!$B$2:$B$251,MATCH($A81,'Raw Data'!$T$2:$T$251,0))) | D81: =IF($A81="","",INDEX('Raw Data'!$D$2:$D$251,MATCH($A81,'Raw Data'!$T$2:$T$251,0))) | E81: =IF($A81="","",INDEX('Raw Data'!$F$2:$F$251,MATCH($A81,'Raw Data'!$T$2:$T$251,0))) | F81: =IF($A81="","",INDEX('Raw Data'!$G$2:$G$251,MATCH($A81,'Raw Data'!$T$2:$T$251,0))) | G81: =IF($A81="","",INDEX('Raw Data'!$K$2:$K$251,MATCH($A81,'Raw Data'!$T$2:$T$251,0))) | H81: =IF($A81="","",INDEX('Raw Data'!$H$2:$H$251,MATCH($A81,'Raw Data'!$T$2:$T$251,0))) | I81: =IF($A81="","",INDEX('Raw Data'!$N$2:$N$251,MATCH($A81,'Raw Data'!$T$2:$T$251,0)))
A82: =IF(73<=$C$7,73,"") | B82: =IF($A82="","",INDEX('Raw Data'!$A$2:$A$251,MATCH($A82,'Raw Data'!$T$2:$T$251,0))) | C82: =IF($A82="","",INDEX('Raw Data'!$B$2:$B$251,MATCH($A82,'Raw Data'!$T$2:$T$251,0))) | D82: =IF($A82="","",INDEX('Raw Data'!$D$2:$D$251,MATCH($A82,'Raw Data'!$T$2:$T$251,0))) | E82: =IF($A82="","",INDEX('Raw Data'!$F$2:$F$251,MATCH($A82,'Raw Data'!$T$2:$T$251,0))) | F82: =IF($A82="","",INDEX('Raw Data'!$G$2:$G$251,MATCH($A82,'Raw Data'!$T$2:$T$251,0))) | G82: =IF($A82="","",INDEX('Raw Data'!$K$2:$K$251,MATCH($A82,'Raw Data'!$T$2:$T$251,0))) | H82: =IF($A82="","",INDEX('Raw Data'!$H$2:$H$251,MATCH($A82,'Raw Data'!$T$2:$T$251,0))) | I82: =IF($A82="","",INDEX('Raw Data'!$N$2:$N$251,MATCH($A82,'Raw Data'!$T$2:$T$251,0)))
A83: =IF(74<=$C$7,74,"") | B83: =IF($A83="","",INDEX('Raw Data'!$A$2:$A$251,MATCH($A83,'Raw Data'!$T$2:$T$251,0))) | C83: =IF($A83="","",INDEX('Raw Data'!$B$2:$B$251,MATCH($A83,'Raw Data'!$T$2:$T$251,0))) | D83: =IF($A83="","",INDEX('Raw Data'!$D$2:$D$251,MATCH($A83,'Raw Data'!$T$2:$T$251,0))) | E83: =IF($A83="","",INDEX('Raw Data'!$F$2:$F$251,MATCH($A83,'Raw Data'!$T$2:$T$251,0))) | F83: =IF($A83="","",INDEX('Raw Data'!$G$2:$G$251,MATCH($A83,'Raw Data'!$T$2:$T$251,0))) | G83: =IF($A83="","",INDEX('Raw Data'!$K$2:$K$251,MATCH($A83,'Raw Data'!$T$2:$T$251,0))) | H83: =IF($A83="","",INDEX('Raw Data'!$H$2:$H$251,MATCH($A83,'Raw Data'!$T$2:$T$251,0))) | I83: =IF($A83="","",INDEX('Raw Data'!$N$2:$N$251,MATCH($A83,'Raw Data'!$T$2:$T$251,0)))
A84: =IF(75<=$C$7,75,"") | B84: =IF($A84="","",INDEX('Raw Data'!$A$2:$A$251,MATCH($A84,'Raw Data'!$T$2:$T$251,0))) | C84: =IF($A84="","",INDEX('Raw Data'!$B$2:$B$251,MATCH($A84,'Raw Data'!$T$2:$T$251,0))) | D84: =IF($A84="","",INDEX('Raw Data'!$D$2:$D$251,MATCH($A84,'Raw Data'!$T$2:$T$251,0))) | E84: =IF($A84="","",INDEX('Raw Data'!$F$2:$F$251,MATCH($A84,'Raw Data'!$T$2:$T$251,0))) | F84: =IF($A84="","",INDEX('Raw Data'!$G$2:$G$251,MATCH($A84,'Raw Data'!$T$2:$T$251,0))) | G84: =IF($A84="","",INDEX('Raw Data'!$K$2:$K$251,MATCH($A84,'Raw Data'!$T$2:$T$251,0))) | H84: =IF($A84="","",INDEX('Raw Data'!$H$2:$H$251,MATCH($A84,'Raw Data'!$T$2:$T$251,0))) | I84: =IF($A84="","",INDEX('Raw Data'!$N$2:$N$251,MATCH($A84,'Raw Data'!$T$2:$T$251,0)))
A85: =IF(76<=$C$7,76,"") | B85: =IF($A85="","",INDEX('Raw Data'!$A$2:$A$251,MATCH($A85,'Raw Data'!$T$2:$T$251,0))) | C85: =IF($A85="","",INDEX('Raw Data'!$B$2:$B$251,MATCH($A85,'Raw Data'!$T$2:$T$251,0))) | D85: =IF($A85="","",INDEX('Raw Data'!$D$2:$D$251,MATCH($A85,'Raw Data'!$T$2:$T$251,0))) | E85: =IF($A85="","",INDEX('Raw Data'!$F$2:$F$251,MATCH($A85,'Raw Data'!$T$2:$T$251,0))) | F85: =IF($A85="","",INDEX('Raw Data'!$G$2:$G$251,MATCH($A85,'Raw Data'!$T$2:$T$251,0))) | G85: =IF($A85="","",INDEX('Raw Data'!$K$2:$K$251,MATCH($A85,'Raw Data'!$T$2:$T$251,0))) | H85: =IF($A85="","",INDEX('Raw Data'!$H$2:$H$251,MATCH($A85,'Raw Data'!$T$2:$T$251,0))) | I85: =IF($A85="","",INDEX('Raw Data'!$N$2:$N$251,MATCH($A85,'Raw Data'!$T$2:$T$251,0)))
A86: =IF(77<=$C$7,77,"") | B86: =IF($A86="","",INDEX('Raw Data'!$A$2:$A$251,MATCH($A86,'Raw Data'!$T$2:$T$251,0))) | C86: =IF($A86="","",INDEX('Raw Data'!$B$2:$B$251,MATCH($A86,'Raw Data'!$T$2:$T$251,0))) | D86: =IF($A86="","",INDEX('Raw Data'!$D$2:$D$251,MATCH($A86,'Raw Data'!$T$2:$T$251,0))) | E86: =IF($A86="","",INDEX('Raw Data'!$F$2:$F$251,MATCH($A86,'Raw Data'!$T$2:$T$251,0))) | F86: =IF($A86="","",INDEX('Raw Data'!$G$2:$G$251,MATCH($A86,'Raw Data'!$T$2:$T$251,0))) | G86: =IF($A86="","",INDEX('Raw Data'!$K$2:$K$251,MATCH($A86,'Raw Data'!$T$2:$T$251,0))) | H86: =IF($A86="","",INDEX('Raw Data'!$H$2:$H$251,MATCH($A86,'Raw Data'!$T$2:$T$251,0))) | I86: =IF($A86="","",INDEX('Raw Data'!$N$2:$N$251,MATCH($A86,'Raw Data'!$T$2:$T$251,0)))
A87: =IF(78<=$C$7,78,"") | B87: =IF($A87="","",INDEX('Raw Data'!$A$2:$A$251,MATCH($A87,'Raw Data'!$T$2:$T$251,0))) | C87: =IF($A87="","",INDEX('Raw Data'!$B$2:$B$251,MATCH($A87,'Raw Data'!$T$2:$T$251,0))) | D87: =IF($A87="","",INDEX('Raw Data'!$D$2:$D$251,MATCH($A87,'Raw Data'!$T$2:$T$251,0))) | E87: =IF($A87="","",INDEX('Raw Data'!$F$2:$F$251,MATCH($A87,'Raw Data'!$T$2:$T$251,0))) | F87: =IF($A87="","",INDEX('Raw Data'!$G$2:$G$251,MATCH($A87,'Raw Data'!$T$2:$T$251,0))) | G87: =IF($A87="","",INDEX('Raw Data'!$K$2:$K$251,MATCH($A87,'Raw Data'!$T$2:$T$251,0))) | H87: =IF($A87="","",INDEX('Raw Data'!$H$2:$H$251,MATCH($A87,'Raw Data'!$T$2:$T$251,0))) | I87: =IF($A87="","",INDEX('Raw Data'!$N$2:$N$251,MATCH($A87,'Raw Data'!$T$2:$T$251,0)))
A88: =IF(79<=$C$7,79,"") | B88: =IF($A88="","",INDEX('Raw Data'!$A$2:$A$251,MATCH($A88,'Raw Data'!$T$2:$T$251,0))) | C88: =IF($A88="","",INDEX('Raw Data'!$B$2:$B$251,MATCH($A88,'Raw Data'!$T$2:$T$251,0))) | D88: =IF($A88="","",INDEX('Raw Data'!$D$2:$D$251,MATCH($A88,'Raw Data'!$T$2:$T$251,0))) | E88: =IF($A88="","",INDEX('Raw Data'!$F$2:$F$251,MATCH($A88,'Raw Data'!$T$2:$T$251,0))) | F88: =IF($A88="","",INDEX('Raw Data'!$G$2:$G$251,MATCH($A88,'Raw Data'!$T$2:$T$251,0))) | G88: =IF($A88="","",INDEX('Raw Data'!$K$2:$K$251,MATCH($A88,'Raw Data'!$T$2:$T$251,0))) | H88: =IF($A88="","",INDEX('Raw Data'!$H$2:$H$251,MATCH($A88,'Raw Data'!$T$2:$T$251,0))) | I88: =IF($A88="","",INDEX('Raw Data'!$N$2:$N$251,MATCH($A88,'Raw Data'!$T$2:$T$251,0)))
A89: =IF(80<=$C$7,80,"") | B89: =IF($A89="","",INDEX('Raw Data'!$A$2:$A$251,MATCH($A89,'Raw Data'!$T$2:$T$251,0))) | C89: =IF($A89="","",INDEX('Raw Data'!$B$2:$B$251,MATCH($A89,'Raw Data'!$T$2:$T$251,0))) | D89: =IF($A89="","",INDEX('Raw Data'!$D$2:$D$251,MATCH($A89,'Raw Data'!$T$2:$T$251,0))) | E89: =IF($A89="","",INDEX('Raw Data'!$F$2:$F$251,MATCH($A89,'Raw Data'!$T$2:$T$251,0))) | F89: =IF($A89="","",INDEX('Raw Data'!$G$2:$G$251,MATCH($A89,'Raw Data'!$T$2:$T$251,0))) | G89: =IF($A89="","",INDEX('Raw Data'!$K$2:$K$251,MATCH($A89,'Raw Data'!$T$2:$T$251,0))) | H89: =IF($A89="","",INDEX('Raw Data'!$H$2:$H$251,MATCH($A89,'Raw Data'!$T$2:$T$251,0))) | I89: =IF($A89="","",INDEX('Raw Data'!$N$2:$N$251,MATCH($A89,'Raw Data'!$T$2:$T$251,0)))
A90: =IF(81<=$C$7,81,"") | B90: =IF($A90="","",INDEX('Raw Data'!$A$2:$A$251,MATCH($A90,'Raw Data'!$T$2:$T$251,0))) | C90: =IF($A90="","",INDEX('Raw Data'!$B$2:$B$251,MATCH($A90,'Raw Data'!$T$2:$T$251,0))) | D90: =IF($A90="","",INDEX('Raw Data'!$D$2:$D$251,MATCH($A90,'Raw Data'!$T$2:$T$251,0))) | E90: =IF($A90="","",INDEX('Raw Data'!$F$2:$F$251,MATCH($A90,'Raw Data'!$T$2:$T$251,0))) | F90: =IF($A90="","",INDEX('Raw Data'!$G$2:$G$251,MATCH($A90,'Raw Data'!$T$2:$T$251,0))) | G90: =IF($A90="","",INDEX('Raw Data'!$K$2:$K$251,MATCH($A90,'Raw Data'!$T$2:$T$251,0))) | H90: =IF($A90="","",INDEX('Raw Data'!$H$2:$H$251,MATCH($A90,'Raw Data'!$T$2:$T$251,0))) | I90: =IF($A90="","",INDEX('Raw Data'!$N$2:$N$251,MATCH($A90,'Raw Data'!$T$2:$T$251,0)))
A91: =IF(82<=$C$7,82,"") | B91: =IF($A91="","",INDEX('Raw Data'!$A$2:$A$251,MATCH($A91,'Raw Data'!$T$2:$T$251,0))) | C91: =IF($A91="","",INDEX('Raw Data'!$B$2:$B$251,MATCH($A91,'Raw Data'!$T$2:$T$251,0))) | D91: =IF($A91="","",INDEX('Raw Data'!$D$2:$D$251,MATCH($A91,'Raw Data'!$T$2:$T$251,0))) | E91: =IF($A91="","",INDEX('Raw Data'!$F$2:$F$251,MATCH($A91,'Raw Data'!$T$2:$T$251,0))) | F91: =IF($A91="","",INDEX('Raw Data'!$G$2:$G$251,MATCH($A91,'Raw Data'!$T$2:$T$251,0))) | G91: =IF($A91="","",INDEX('Raw Data'!$K$2:$K$251,MATCH($A91,'Raw Data'!$T$2:$T$251,0))) | H91: =IF($A91="","",INDEX('Raw Data'!$H$2:$H$251,MATCH($A91,'Raw Data'!$T$2:$T$251,0))) | I91: =IF($A91="","",INDEX('Raw Data'!$N$2:$N$251,MATCH($A91,'Raw Data'!$T$2:$T$251,0)))
A92: =IF(83<=$C$7,83,"") | B92: =IF($A92="","",INDEX('Raw Data'!$A$2:$A$251,MATCH($A92,'Raw Data'!$T$2:$T$251,0))) | C92: =IF($A92="","",INDEX('Raw Data'!$B$2:$B$251,MATCH($A92,'Raw Data'!$T$2:$T$251,0))) | D92: =IF($A92="","",INDEX('Raw Data'!$D$2:$D$251,MATCH($A92,'Raw Data'!$T$2:$T$251,0))) | E92: =IF($A92="","",INDEX('Raw Data'!$F$2:$F$251,MATCH($A92,'Raw Data'!$T$2:$T$251,0))) | F92: =IF($A92="","",INDEX('Raw Data'!$G$2:$G$251,MATCH($A92,'Raw Data'!$T$2:$T$251,0))) | G92: =IF($A92="","",INDEX('Raw Data'!$K$2:$K$251,MATCH($A92,'Raw Data'!$T$2:$T$251,0))) | H92: =IF($A92="","",INDEX('Raw Data'!$H$2:$H$251,MATCH($A92,'Raw Data'!$T$2:$T$251,0))) | I92: =IF($A92="","",INDEX('Raw Data'!$N$2:$N$251,MATCH($A92,'Raw Data'!$T$2:$T$251,0)))
A93: =IF(84<=$C$7,84,"") | B93: =IF($A93="","",INDEX('Raw Data'!$A$2:$A$251,MATCH($A93,'Raw Data'!$T$2:$T$251,0))) | C93: =IF($A93="","",INDEX('Raw Data'!$B$2:$B$251,MATCH($A93,'Raw Data'!$T$2:$T$251,0))) | D93: =IF($A93="","",INDEX('Raw Data'!$D$2:$D$251,MATCH($A93,'Raw Data'!$T$2:$T$251,0))) | E93: =IF($A93="","",INDEX('Raw Data'!$F$2:$F$251,MATCH($A93,'Raw Data'!$T$2:$T$251,0))) | F93: =IF($A93="","",INDEX('Raw Data'!$G$2:$G$251,MATCH($A93,'Raw Data'!$T$2:$T$251,0))) | G93: =IF($A93="","",INDEX('Raw Data'!$K$2:$K$251,MATCH($A93,'Raw Data'!$T$2:$T$251,0))) | H93: =IF($A93="","",INDEX('Raw Data'!$H$2:$H$251,MATCH($A93,'Raw Data'!$T$2:$T$251,0))) | I93: =IF($A93="","",INDEX('Raw Data'!$N$2:$N$251,MATCH($A93,'Raw Data'!$T$2:$T$251,0)))
A94: =IF(85<=$C$7,85,"") | B94: =IF($A94="","",INDEX('Raw Data'!$A$2:$A$251,MATCH($A94,'Raw Data'!$T$2:$T$251,0))) | C94: =IF($A94="","",INDEX('Raw Data'!$B$2:$B$251,MATCH($A94,'Raw Data'!$T$2:$T$251,0))) | D94: =IF($A94="","",INDEX('Raw Data'!$D$2:$D$251,MATCH($A94,'Raw Data'!$T$2:$T$251,0))) | E94: =IF($A94="","",INDEX('Raw Data'!$F$2:$F$251,MATCH($A94,'Raw Data'!$T$2:$T$251,0))) | F94: =IF($A94="","",INDEX('Raw Data'!$G$2:$G$251,MATCH($A94,'Raw Data'!$T$2:$T$251,0))) | G94: =IF($A94="","",INDEX('Raw Data'!$K$2:$K$251,MATCH($A94,'Raw Data'!$T$2:$T$251,0))) | H94: =IF($A94="","",INDEX('Raw Data'!$H$2:$H$251,MATCH($A94,'Raw Data'!$T$2:$T$251,0))) | I94: =IF($A94="","",INDEX('Raw Data'!$N$2:$N$251,MATCH($A94,'Raw Data'!$T$2:$T$251,0)))
A95: =IF(86<=$C$7,86,"") | B95: =IF($A95="","",INDEX('Raw Data'!$A$2:$A$251,MATCH($A95,'Raw Data'!$T$2:$T$251,0))) | C95: =IF($A95="","",INDEX('Raw Data'!$B$2:$B$251,MATCH($A95,'Raw Data'!$T$2:$T$251,0))) | D95: =IF($A95="","",INDEX('Raw Data'!$D$2:$D$251,MATCH($A95,'Raw Data'!$T$2:$T$251,0))) | E95: =IF($A95="","",INDEX('Raw Data'!$F$2:$F$251,MATCH($A95,'Raw Data'!$T$2:$T$251,0))) | F95: =IF($A95="","",INDEX('Raw Data'!$G$2:$G$251,MATCH($A95,'Raw Data'!$T$2:$T$251,0))) | G95: =IF($A95="","",INDEX('Raw Data'!$K$2:$K$251,MATCH($A95,'Raw Data'!$T$2:$T$251,0))) | H95: =IF($A95="","",INDEX('Raw Data'!$H$2:$H$251,MATCH($A95,'Raw Data'!$T$2:$T$251,0))) | I95: =IF($A95="","",INDEX('Raw Data'!$N$2:$N$251,MATCH($A95,'Raw Data'!$T$2:$T$251,0)))
A96: =IF(87<=$C$7,87,"") | B96: =IF($A96="","",INDEX('Raw Data'!$A$2:$A$251,MATCH($A96,'Raw Data'!$T$2:$T$251,0))) | C96: =IF($A96="","",INDEX('Raw Data'!$B$2:$B$251,MATCH($A96,'Raw Data'!$T$2:$T$251,0))) | D96: =IF($A96="","",INDEX('Raw Data'!$D$2:$D$251,MATCH($A96,'Raw Data'!$T$2:$T$251,0))) | E96: =IF($A96="","",INDEX('Raw Data'!$F$2:$F$251,MATCH($A96,'Raw Data'!$T$2:$T$251,0))) | F96: =IF($A96="","",INDEX('Raw Data'!$G$2:$G$251,MATCH($A96,'Raw Data'!$T$2:$T$251,0))) | G96: =IF($A96="","",INDEX('Raw Data'!$K$2:$K$251,MATCH($A96,'Raw Data'!$T$2:$T$251,0))) | H96: =IF($A96="","",INDEX('Raw Data'!$H$2:$H$251,MATCH($A96,'Raw Data'!$T$2:$T$251,0))) | I96: =IF($A96="","",INDEX('Raw Data'!$N$2:$N$251,MATCH($A96,'Raw Data'!$T$2:$T$251,0)))
A97: =IF(88<=$C$7,88,"") | B97: =IF($A97="","",INDEX('Raw Data'!$A$2:$A$251,MATCH($A97,'Raw Data'!$T$2:$T$251,0))) | C97: =IF($A97="","",INDEX('Raw Data'!$B$2:$B$251,MATCH($A97,'Raw Data'!$T$2:$T$251,0))) | D97: =IF($A97="","",INDEX('Raw Data'!$D$2:$D$251,MATCH($A97,'Raw Data'!$T$2:$T$251,0))) | E97: =IF($A97="","",INDEX('Raw Data'!$F$2:$F$251,MATCH($A97,'Raw Data'!$T$2:$T$251,0))) | F97: =IF($A97="","",INDEX('Raw Data'!$G$2:$G$251,MATCH($A97,'Raw Data'!$T$2:$T$251,0))) | G97: =IF($A97="","",INDEX('Raw Data'!$K$2:$K$251,MATCH($A97,'Raw Data'!$T$2:$T$251,0))) | H97: =IF($A97="","",INDEX('Raw Data'!$H$2:$H$251,MATCH($A97,'Raw Data'!$T$2:$T$251,0))) | I97: =IF($A97="","",INDEX('Raw Data'!$N$2:$N$251,MATCH($A97,'Raw Data'!$T$2:$T$251,0)))
A98: =IF(89<=$C$7,89,"") | B98: =IF($A98="","",INDEX('Raw Data'!$A$2:$A$251,MATCH($A98,'Raw Data'!$T$2:$T$251,0))) | C98: =IF($A98="","",INDEX('Raw Data'!$B$2:$B$251,MATCH($A98,'Raw Data'!$T$2:$T$251,0))) | D98: =IF($A98="","",INDEX('Raw Data'!$D$2:$D$251,MATCH($A98,'Raw Data'!$T$2:$T$251,0))) | E98: =IF($A98="","",INDEX('Raw Data'!$F$2:$F$251,MATCH($A98,'Raw Data'!$T$2:$T$251,0))) | F98: =IF($A98="","",INDEX('Raw Data'!$G$2:$G$251,MATCH($A98,'Raw Data'!$T$2:$T$251,0))) | G98: =IF($A98="","",INDEX('Raw Data'!$K$2:$K$251,MATCH($A98,'Raw Data'!$T$2:$T$251,0))) | H98: =IF($A98="","",INDEX('Raw Data'!$H$2:$H$251,MATCH($A98,'Raw Data'!$T$2:$T$251,0))) | I98: =IF($A98="","",INDEX('Raw Data'!$N$2:$N$251,MATCH($A98,'Raw Data'!$T$2:$T$251,0)))
A99: =IF(90<=$C$7,90,"") | B99: =IF($A99="","",INDEX('Raw Data'!$A$2:$A$251,MATCH($A99,'Raw Data'!$T$2:$T$251,0))) | C99: =IF($A99="","",INDEX('Raw Data'!$B$2:$B$251,MATCH($A99,'Raw Data'!$T$2:$T$251,0))) | D99: =IF($A99="","",INDEX('Raw Data'!$D$2:$D$251,MATCH($A99,'Raw Data'!$T$2:$T$251,0))) | E99: =IF($A99="","",INDEX('Raw Data'!$F$2:$F$251,MATCH($A99,'Raw Data'!$T$2:$T$251,0))) | F99: =IF($A99="","",INDEX('Raw Data'!$G$2:$G$251,MATCH($A99,'Raw Data'!$T$2:$T$251,0))) | G99: =IF($A99="","",INDEX('Raw Data'!$K$2:$K$251,MATCH($A99,'Raw Data'!$T$2:$T$251,0))) | H99: =IF($A99="","",INDEX('Raw Data'!$H$2:$H$251,MATCH($A99,'Raw Data'!$T$2:$T$251,0))) | I99: =IF($A99="","",INDEX('Raw Data'!$N$2:$N$251,MATCH($A99,'Raw Data'!$T$2:$T$251,0)))
A100: =IF(91<=$C$7,91,"") | B100: =IF($A100="","",INDEX('Raw Data'!$A$2:$A$251,MATCH($A100,'Raw Data'!$T$2:$T$251,0))) | C100: =IF($A100="","",INDEX('Raw Data'!$B$2:$B$251,MATCH($A100,'Raw Data'!$T$2:$T$251,0))) | D100: =IF($A100="","",INDEX('Raw Data'!$D$2:$D$251,MATCH($A100,'Raw Data'!$T$2:$T$251,0))) | E100: =IF($A100="","",INDEX('Raw Data'!$F$2:$F$251,MATCH($A100,'Raw Data'!$T$2:$T$251,0))) | F100: =IF($A100="","",INDEX('Raw Data'!$G$2:$G$251,MATCH($A100,'Raw Data'!$T$2:$T$251,0))) | G100: =IF($A100="","",INDEX('Raw Data'!$K$2:$K$251,MATCH($A100,'Raw Data'!$T$2:$T$251,0))) | H100: =IF($A100="","",INDEX('Raw Data'!$H$2:$H$251,MATCH($A100,'Raw Data'!$T$2:$T$251,0))) | I100: =IF($A100="","",INDEX('Raw Data'!$N$2:$N$251,MATCH($A100,'Raw Data'!$T$2:$T$251,0)))
A101: =IF(92<=$C$7,92,"") | B101: =IF($A101="","",INDEX('Raw Data'!$A$2:$A$251,MATCH($A101,'Raw Data'!$T$2:$T$251,0))) | C101: =IF($A101="","",INDEX('Raw Data'!$B$2:$B$251,MATCH($A101,'Raw Data'!$T$2:$T$251,0))) | D101: =IF($A101="","",INDEX('Raw Data'!$D$2:$D$251,MATCH($A101,'Raw Data'!$T$2:$T$251,0))) | E101: =IF($A101="","",INDEX('Raw Data'!$F$2:$F$251,MATCH($A101,'Raw Data'!$T$2:$T$251,0))) | F101: =IF($A101="","",INDEX('Raw Data'!$G$2:$G$251,MATCH($A101,'Raw Data'!$T$2:$T$251,0))) | G101: =IF($A101="","",INDEX('Raw Data'!$K$2:$K$251,MATCH($A101,'Raw Data'!$T$2:$T$251,0))) | H101: =IF($A101="","",INDEX('Raw Data'!$H$2:$H$251,MATCH($A101,'Raw Data'!$T$2:$T$251,0))) | I101: =IF($A101="","",INDEX('Raw Data'!$N$2:$N$251,MATCH($A101,'Raw Data'!$T$2:$T$251,0)))
A102: =IF(93<=$C$7,93,"") | B102: =IF($A102="","",INDEX('Raw Data'!$A$2:$A$251,MATCH($A102,'Raw Data'!$T$2:$T$251,0))) | C102: =IF($A102="","",INDEX('Raw Data'!$B$2:$B$251,MATCH($A102,'Raw Data'!$T$2:$T$251,0))) | D102: =IF($A102="","",INDEX('Raw Data'!$D$2:$D$251,MATCH($A102,'Raw Data'!$T$2:$T$251,0))) | E102: =IF($A102="","",INDEX('Raw Data'!$F$2:$F$251,MATCH($A102,'Raw Data'!$T$2:$T$251,0))) | F102: =IF($A102="","",INDEX('Raw Data'!$G$2:$G$251,MATCH($A102,'Raw Data'!$T$2:$T$251,0))) | G102: =IF($A102="","",INDEX('Raw Data'!$K$2:$K$251,MATCH($A102,'Raw Data'!$T$2:$T$251,0))) | H102: =IF($A102="","",INDEX('Raw Data'!$H$2:$H$251,MATCH($A102,'Raw Data'!$T$2:$T$251,0))) | I102: =IF($A102="","",INDEX('Raw Data'!$N$2:$N$251,MATCH($A102,'Raw Data'!$T$2:$T$251,0)))
A103: =IF(94<=$C$7,94,"") | B103: =IF($A103="","",INDEX('Raw Data'!$A$2:$A$251,MATCH($A103,'Raw Data'!$T$2:$T$251,0))) | C103: =IF($A103="","",INDEX('Raw Data'!$B$2:$B$251,MATCH($A103,'Raw Data'!$T$2:$T$251,0))) | D103: =IF($A103="","",INDEX('Raw Data'!$D$2:$D$251,MATCH($A103,'Raw Data'!$T$2:$T$251,0))) | E103: =IF($A103="","",INDEX('Raw Data'!$F$2:$F$251,MATCH($A103,'Raw Data'!$T$2:$T$251,0))) | F103: =IF($A103="","",INDEX('Raw Data'!$G$2:$G$251,MATCH($A103,'Raw Data'!$T$2:$T$251,0))) | G103: =IF($A103="","",INDEX('Raw Data'!$K$2:$K$251,MATCH($A103,'Raw Data'!$T$2:$T$251,0))) | H103: =IF($A103="","",INDEX('Raw Data'!$H$2:$H$251,MATCH($A103,'Raw Data'!$T$2:$T$251,0))) | I103: =IF($A103="","",INDEX('Raw Data'!$N$2:$N$251,MATCH($A103,'Raw Data'!$T$2:$T$251,0)))
...

Sheet What-If
A1: What-If Analysis - Scenarios & Goal Seek
A3: 1. Baseline (from Raw Data)
A4: Base Revenue | B4: =SUM('Raw Data'!$N$2:$N$251) -> 229192.47
A5: Base Units | B5: =SUM('Raw Data'!$H$2:$H$251) -> 753
A6: Base Orders | B6: =COUNTA('Raw Data'!$A$2:$A$251) -> 250
A7: Avg Realised Price / Unit | B7: =B4/B5 -> 304.37247
A8: Gross Margin % (ASSUMPTION - not in data) | B8: 0.35
A9: Base COGS | B9: =B4*(1-B8) -> 148975.11
A10: Base Gross Profit | B10: =B4-B9 -> 80217.365
A12: 2. Scenario Manager Table (Base / Optimistic / Pessimistic)
A13: Driver | B13: Base | C13: Optimistic | D13: Pessimistic | E13: Live (selected)
A14: Price change % | B14: 0 | C14: 0.05 | D14: 0 | E14: =INDEX(B14:D14,MATCH($B$18,$B$13:$D$13,0)) -> 0.05
A15: Volume change % | B15: 0 | C15: 0.1 | D15: -0.1 | E15: =INDEX(B15:D15,MATCH($B$18,$B$13:$D$13,0)) -> 0.1
A16: Discount % | B16: 0 | C16: 0.03 | D16: 0.08 | E16: =INDEX(B16:D16,MATCH($B$18,$B$13:$D$13,0)) -> 0.03
A18: Selected scenario | B18: Optimistic
A20: Outcome | B20: Base | C20: Optimistic | D20: Pessimistic | E20: Live (selected)
A21: Revenue | B21: =$B$4*(1+B14)*(1+B15)*(1-B16) -> 229192.47 | C21: =$B$4*(1+C14)*(1+C15)*(1-C16) -> 256775.78 | D21: =$B$4*(1+D14)*(1+D15)*(1-D16) -> 189771.37 | E21: =$B$4*(1+E14)*(1+E15)*(1-E16) -> 256775.78
A22: Units Sold | B22: =$B$5*(1+B15) -> 753 | C22: =$B$5*(1+C15) -> 828.3 | D22: =$B$5*(1+D15) -> 677.7 | E22: =$B$5*(1+E15) -> 828.3
A23: Gross Profit | B23: =B21-$B$9*(1+B15) -> 80217.365 | C23: =C21-$B$9*(1+C15) -> 92903.168 | D23: =D21-$B$9*(1+D15) -> 55693.77 | E23: =E21-$B$9*(1+E15) -> 92903.168
A24: Gross Margin % | B24: =IFERROR(B23/B21,0) -> 0.35 | C24: =IFERROR(C23/C21,0) -> 0.36180658 | D24: =IFERROR(D23/D21,0) -> 0.29347826 | E24: =IFERROR(E23/E21,0) -> 0.36180658
A25: Revenue vs Base ($) | B25: =B21-$B$21 -> 0 | C25: =C21-$B$21 -> 27583.314 | D25: =D21-$B$21 -> -39421.105 | E25: =E21-$B$21 -> 27583.314
A26: Revenue vs Base (%) | B26: =B21/$B$21-1 -> 0 | C26: =C21/$B$21-1 -> 0.12035 | D26: =D21/$B$21-1 -> -0.172 | E26: =E21/$B$21-1 -> 0.12035
A27: Gross Profit vs Base ($) | B27: =B23-$B$23 -> 0 | C27: =C23-$B$23 -> 12685.803 | D27: =D23-$B$23 -> -24523.594 | E27: =E23-$B$23 -> 12685.803
A31: 3. Goal Seek - volume growth needed to hit a revenue target
A32: Price change % (assumption) | B32: 0.05
A33: Discount % (assumption) | B33: 0.03
A34: Target revenue growth % (assumption) | B34: 0.2
A35: Target revenue | B35: =B4*(1+B34) -> 275030.96
A36: CHANGING CELL: volume change % (Goal Seek result) | B36: 0.17820324
A37: Result revenue (formula) | B37: =B4*(1+B32)*(1+B36)*(1-B33) -> 275030.96
A38: Gap (result - target) | B38: =B37-B35 -> 0
A39: Analytical check of required volume % | B39: =B35/(B4*(1+B32)*(1-B33))-1 -> 0.17820324
A40: Extra units required | B40: =B5*B36 -> 134.18704
A41: Status | B41: =IF(ABS(B38)<0.5,"Goal achieved","Re-run Goal Seek") -> Goal achieved
A45: 4. Goal Seek 2 - orders needed at current Avg Order Value
A46: Current Avg Order Value | B46: =B4/B6 -> 916.76988
A47: Required orders for target revenue | B47: =ROUNDUP(B35/B46,0) -> 300
A48: Additional orders vs today | B48: =B47-B6 -> 50

Sheet Regression
A1: Linear Regression (Data Analysis ToolPak-style output via LINEST)
A4: A. Transaction level: Total_Amount (Y) ~ Quantity + Unit_Price (X)
A5: Regression Statistics | B5: Value
A6: Multiple R | B6: =SQRT(B7) -> 0.92884475
A7: R Square | B7: =INDEX(LINEST('Raw Data'!$N$2:$N$251,'Raw Data'!$H$2:$I$251,TRUE(),TRUE()),3,1) -> 0.86275258
A8: Adjusted R Square | B8: =1-(1-B7)*(B10-1)/(B10-2-1) -> 0.86164126
A9: Standard Error | B9: =INDEX(LINEST('Raw Data'!$N$2:$N$251,'Raw Data'!$H$2:$I$251,TRUE(),TRUE()),3,2) -> 384.0375
A10: Observations | B10: =COUNT('Raw Data'!$N$2:$N$251) -> 250
A12: ANOVA | B12: df | C12: SS | D12: MS | E12: F | F12: Significance F
A13: Regression | B13: 2 | C13: =INDEX(LINEST('Raw Data'!$N$2:$N$251,'Raw Data'!$H$2:$I$251,TRUE(),TRUE()),5,1) -> 2.2899515e+08 | D13: =C13/B13 -> 1.1449757e+08 | E13: =INDEX(LINEST('Raw Data'!$N$2:$N$251,'Raw Data'!$H$2:$I$251,TRUE(),TRUE()),4,1) -> 776.33474 | F13: =FDIST(E13,B13,B14) -> 3.032279e-107
A14: Residual | B14: =INDEX(LINEST('Raw Data'!$N$2:$N$251,'Raw Data'!$H$2:$I$251,TRUE(),TRUE()),4,2) -> 247 | C14: =INDEX(LINEST('Raw Data'!$N$2:$N$251,'Raw Data'!$H$2:$I$251,TRUE(),TRUE()),5,2) -> 36428746 | D14: =C14/B14 -> 147484.8
A15: Total | B15: =B13+B14 -> 249 | C15: =C13+C14 -> 2.6542389e+08
B17: Coefficients | C17: Standard Error | D17: t Stat | E17: P-value | F17: Lower 95% | G17: Upper 95%
A18: Intercept | B18: =INDEX(LINEST('Raw Data'!$N$2:$N$251,'Raw Data'!$H$2:$I$251,TRUE(),TRUE()),1,3) -> -931.80859 | C18: =INDEX(LINEST('Raw Data'!$N$2:$N$251,'Raw Data'!$H$2:$I$251,TRUE(),TRUE()),2,3) -> 64.176586 | D18: =B18/C18 -> -14.519448 | E18: =TDIST(ABS(D18),$B$14,2) -> 5.9491879e-35 | F18: =B18-TINV(0.05,$B$14)*C18 -> -1058.2117 | G18: =B18+TINV(0.05,$B$14)*C18 -> -805.40543
A19: Quantity | B19: =INDEX(LINEST('Raw Data'!$N$2:$N$251,'Raw Data'!$H$2:$I$251,TRUE(),TRUE()),1,2) -> 314.14588 | C19: =INDEX(LINEST('Raw Data'!$N$2:$N$251,'Raw Data'!$H$2:$I$251,TRUE(),TRUE()),2,2) -> 18.242562 | D19: =B19/C19 -> 17.220491 | E19: =TDIST(ABS(D19),$B$14,2) -> 3.4020508e-44 | F19: =B19-TINV(0.05,$B$14)*C19 -> 278.21506 | G19: =B19+TINV(0.05,$B$14)*C19 -> 350.0767
A20: Unit_Price | B20: =INDEX(LINEST('Raw Data'!$N$2:$N$251,'Raw Data'!$H$2:$I$251,TRUE(),TRUE()),1,1) -> 3.041666 | C20: =INDEX(LINEST('Raw Data'!$N$2:$N$251,'Raw Data'!$H$2:$I$251,TRUE(),TRUE()),2,1) -> 0.088733343 | D20: =B20/C20 -> 34.278727 | E20: =TDIST(ABS(D20),$B$14,2) -> 7.2446245e-96 | F20: =B20-TINV(0.05,$B$14)*C20 -> 2.8668955 | G20: =B20+TINV(0.05,$B$14)*C20 -> 3.2164365
A21: ="Equation: Total_Amount = "&TEXT(B18,"#,##0.00")&" + "&TEXT(B19,"#,##0.00")&" x Quantity + "&TEXT(B20,"#,##0.00")&" x Unit_Price" -> Equation: Total_Amount = -931.81 + 314.15 x Quantity + 3.04 x Unit_Price
A26: B. Monthly revenue trend: Revenue (Y) ~ Month # (X) - 11 full months (May-24 to Mar-25)
A27: Regression Statistics | B27: Value
A28: Multiple R | B28: =SQRT(B29) -> 0.27649117
A29: R Square | B29: =INDEX(LINEST('Sales Analysis'!$C$61:$C$71,'Sales Analysis'!$J$61:$J$71,TRUE(),TRUE()),3,1) -> 0.076447365
A30: Adjusted R Square | B30: =1-(1-B29)*(B32-1)/(B32-1-1) -> -0.026169594
A31: Standard Error | B31: =INDEX(LINEST('Sales Analysis'!$C$61:$C$71,'Sales Analysis'!$J$61:$J$71,TRUE(),TRUE()),3,2) -> 4111.4425
A32: Observations | B32: =COUNT('Sales Analysis'!$C$61:$C$71) -> 11
A34: ANOVA | B34: df | C34: SS | D34: MS | E34: F | F34: Significance F
A35: Regression | B35: 1 | C35: =INDEX(LINEST('Sales Analysis'!$C$61:$C$71,'Sales Analysis'!$J$61:$J$71,TRUE(),TRUE()),5,1) -> 12593076 | D35: =C35/B35 -> 12593076 | E35: =INDEX(LINEST('Sales Analysis'!$C$61:$C$71,'Sales Analysis'!$J$61:$J$71,TRUE(),TRUE()),4,1) -> 0.74497788 | F35: =FDIST(E35,B35,B36) -> 0.41048135
A36: Residual | B36: =INDEX(LINEST('Sales Analysis'!$C$61:$C$71,'Sales Analysis'!$J$61:$J$71,TRUE(),TRUE()),4,2) -> 9 | C36: =INDEX(LINEST('Sales Analysis'!$C$61:$C$71,'Sales Analysis'!$J$61:$J$71,TRUE(),TRUE()),5,2) -> 1.5213563e+08 | D36: =C36/B36 -> 16903959
A37: Total | B37: =B35+B36 -> 10 | C37: =C35+C36 -> 1.6472871e+08
B39: Coefficients | C39: Standard Error | D39: t Stat | E39: P-value | F39: Lower 95% | G39: Upper 95%
A40: Intercept | B40: =INDEX(LINEST('Sales Analysis'!$C$61:$C$71,'Sales Analysis'!$J$61:$J$71,TRUE(),TRUE()),1,2) -> 15930.923 | C40: =INDEX(LINEST('Sales Analysis'!$C$61:$C$71,'Sales Analysis'!$J$61:$J$71,TRUE(),TRUE()),2,2) -> 3011.091 | D40: =B40/C40 -> 5.2907479 | E40: =TDIST(ABS(D40),$B$36,2) -> 0.00049993777 | F40: =B40-TINV(0.05,$B$36)*C40 -> 9119.3623 | G40: =B40+TINV(0.05,$B$36)*C40 -> 22742.484
A41: Month # | B41: =INDEX(LINEST('Sales Analysis'!$C$61:$C$71,'Sales Analysis'!$J$61:$J$71,TRUE(),TRUE()),1,1) -> 338.35264 | C41: =INDEX(LINEST('Sales Analysis'!$C$61:$C$71,'Sales Analysis'!$J$61:$J$71,TRUE(),TRUE()),2,1) -> 392.01066 | D41: =B41/C41 -> 0.86312101 | E41: =TDIST(ABS(D41),$B$36,2) -> 0.41048135 | F41: =B41-TINV(0.05,$B$36)*C41 -> -548.43708 | G41: =B41+TINV(0.05,$B$36)*C41 -> 1225.1424
A43: ="Trend: revenue changes by "&TEXT(B41,"$#,##0")&" per month (p = "&TEXT(E41,"0.000")&") - "&IF(E41<0.05,"statistically significant trend.","NOT statistically significant: no reliable up/down trend.") -> Trend: revenue changes by $338 per month (p = 0.410) - NOT statistically significant: no reliable up/down trend.
A45: C. 3-Month Forecast from the Trend Line (FORECAST)
A46: Month | B46: Month # | C46: Forecast Revenue
A47: =TEXT(EDATE('Sales Analysis'!$A$60,B47-1),"mmm yyyy") -> Apr 2025 | B47: 13 | C47: =FORECAST(B47,'Sales Analysis'!$C$61:$C$71,'Sales Analysis'!$J$61:$J$71) -> 20329.508
A48: =TEXT(EDATE('Sales Analysis'!$A$60,B48-1),"mmm yyyy") -> May 2025 | B48: 14 | C48: =FORECAST(B48,'Sales Analysis'!$C$61:$C$71,'Sales Analysis'!$J$61:$J$71) -> 20667.86
A49: =TEXT(EDATE('Sales Analysis'!$A$60,B49-1),"mmm yyyy") -> Jun 2025 | B49: 15 | C49: =FORECAST(B49,'Sales Analysis'!$C$61:$C$71,'Sales Analysis'!$J$61:$J$71) -> 21006.213

Sheet Chart Data
A1: Chart Data - helper tables feeding the Executive Charts sheet (all formulas, recalculates with Raw Data)
A2: Blue = typed input (bucket limits). Black = formula. Do not delete: charts on "Executive Charts" read from here.
A3: 1. Monthly trend (from Sales Analysis section 7)
A4: Month | B4: Revenue | C4: Orders | D4: Cumulative Revenue | E4: MoM Growth (full months) | F4: Daily Run-Rate
A5: =TEXT('Sales Analysis'!A60,"mmm-yy") -> Apr-24 | B5: ='Sales Analysis'!C60 -> 20919.33 | C5: ='Sales Analysis'!D60 -> 21 | D5: ='Sales Analysis'!G60 -> 20919.33 | F5: ='Sales Analysis'!I60 -> 1045.9665
A6: =TEXT('Sales Analysis'!A61,"mmm-yy") -> May-24 | B6: ='Sales Analysis'!C61 -> 17039.35 | C6: ='Sales Analysis'!D61 -> 19 | D6: ='Sales Analysis'!G61 -> 37958.68 | E6: =IF(AND('Sales Analysis'!K61="Full",'Sales Analysis'!K60="Full"),'Sales Analysis'!F61,"") | F6: ='Sales Analysis'!I61 -> 549.65645
A7: =TEXT('Sales Analysis'!A62,"mmm-yy") -> Jun-24 | B7: ='Sales Analysis'!C62 -> 19299.45 | C7: ='Sales Analysis'!D62 -> 19 | D7: ='Sales Analysis'!G62 -> 57258.13 | E7: =IF(AND('Sales Analysis'!K62="Full",'Sales Analysis'!K61="Full"),'Sales Analysis'!F62,"") -> 0.13264004 | F7: ='Sales Analysis'!I62 -> 643.315
A8: =TEXT('Sales Analysis'!A63,"mmm-yy") -> Jul-24 | B8: ='Sales Analysis'!C63 -> 18479.4 | C8: ='Sales Analysis'!D63 -> 24 | D8: ='Sales Analysis'!G63 -> 75737.53 | E8: =IF(AND('Sales Analysis'!K63="Full",'Sales Analysis'!K62="Full"),'Sales Analysis'!F63,"") -> -0.042490848 | F8: ='Sales Analysis'!I63 -> 596.10968
A9: =TEXT('Sales Analysis'!A64,"mmm-yy") -> Aug-24 | B9: ='Sales Analysis'!C64 -> 15759.43 | C9: ='Sales Analysis'!D64 -> 18 | D9: ='Sales Analysis'!G64 -> 91496.96 | E9: =IF(AND('Sales Analysis'!K64="Full",'Sales Analysis'!K63="Full"),'Sales Analysis'!F64,"") -> -0.1471893 | F9: ='Sales Analysis'!I64 -> 508.36871
A10: =TEXT('Sales Analysis'!A65,"mmm-yy") -> Sep-24 | B10: ='Sales Analysis'!C65 -> 12989.51 | C10: ='Sales Analysis'!D65 -> 19 | D10: ='Sales Analysis'!G65 -> 104486.47 | E10: =IF(AND('Sales Analysis'!K65="Full",'Sales Analysis'!K64="Full"),'Sales Analysis'!F65,"") -> -0.1757627 | F10: ='Sales Analysis'!I65 -> 432.98367
A11: =TEXT('Sales Analysis'!A66,"mmm-yy") -> Oct-24 | B11: ='Sales Analysis'!C66 -> 20609.52 | C11: ='Sales Analysis'!D66 -> 16 | D11: ='Sales Analysis'!G66 -> 125095.99 | E11: =IF(AND('Sales Analysis'!K66="Full",'Sales Analysis'!K65="Full"),'Sales Analysis'!F66,"") -> 0.58662798 | F11: ='Sales Analysis'!I66 -> 664.82323
A12: =TEXT('Sales Analysis'!A67,"mmm-yy") -> Nov-24 | B12: ='Sales Analysis'!C67 -> 12309.44 | C12: ='Sales Analysis'!D67 -> 17 | D12: ='Sales Analysis'!G67 -> 137405.43 | E12: =IF(AND('Sales Analysis'!K67="Full",'Sales Analysis'!K66="Full"),'Sales Analysis'!F67,"") -> -0.40273039 | F12: ='Sales Analysis'!I67 -> 410.31467
A13: =TEXT('Sales Analysis'!A68,"mmm-yy") -> Dec-24 | B13: ='Sales Analysis'!C68 -> 23039.3 | C13: ='Sales Analysis'!D68 -> 25 | D13: ='Sales Analysis'!G68 -> 160444.73 | E13: =IF(AND('Sales Analysis'!K68="Full",'Sales Analysis'!K67="Full"),'Sales Analysis'!F68,"") -> 0.87167735 | F13: ='Sales Analysis'!I68 -> 743.20323
A14: =TEXT('Sales Analysis'!A69,"mmm-yy") -> Jan-25 | B14: ='Sales Analysis'!C69 -> 25799.15 | C14: ='Sales Analysis'!D69 -> 26 | D14: ='Sales Analysis'!G69 -> 186243.88 | E14: =IF(AND('Sales Analysis'!K69="Full",'Sales Analysis'!K68="Full"),'Sales Analysis'!F69,"") -> 0.1197888 | F14: ='Sales Analysis'!I69 -> 832.23065
A15: =TEXT('Sales Analysis'!A70,"mmm-yy") -> Feb-25 | B15: ='Sales Analysis'!C70 -> 16069.38 | C15: ='Sales Analysis'!D70 -> 20 | D15: ='Sales Analysis'!G70 -> 202313.26 | E15: =IF(AND('Sales Analysis'!K70="Full",'Sales Analysis'!K69="Full"),'Sales Analysis'!F70,"") -> -0.37713529 | F15: ='Sales Analysis'!I70 -> 573.90643
A16: =TEXT('Sales Analysis'!A71,"mmm-yy") -> Mar-25 | B16: ='Sales Analysis'!C71 -> 19899.38 | C16: ='Sales Analysis'!D71 -> 19 | D16: ='Sales Analysis'!G71 -> 222212.64 | E16: =IF(AND('Sales Analysis'!K71="Full",'Sales Analysis'!K70="Full"),'Sales Analysis'!F71,"") -> 0.23834149 | F16: ='Sales Analysis'!I71 -> 641.91548
A17: =TEXT('Sales Analysis'!A72,"mmm-yy") -> Apr-25 | B17: ='Sales Analysis'!C72 -> 6979.83 | C17: ='Sales Analysis'!D72 -> 7 | D17: ='Sales Analysis'!G72 -> 229192.47 | E17: =IF(AND('Sales Analysis'!K72="Full",'Sales Analysis'!K71="Full"),'Sales Analysis'!F72,"") | F17: ='Sales Analysis'!I72 -> 634.53
A18: MoM growth is shown only when both the month and the month before it are full months (Apr-24 and Apr-25 are partial).
A20: 2. Products ranked by revenue (sorted with INDEX/MATCH)
A21: Rank | B21: Product | C21: Revenue | D21: Units Sold | E21: Orders | H21: Product (unsorted) | I21: Revenue | J21: Units | K21: Unique Rank
A22: 1 | B22: =INDEX($H$22:$H$31,MATCH($A22,$K$22:$K$31,0)) -> Laptop | C22: =INDEX($I$22:$I$31,MATCH($A22,$K$22:$K$31,0)) -> 67499.25 | D22: =INDEX($J$22:$J$31,MATCH($A22,$K$22:$K$31,0)) -> 75 | E22: =COUNTIF('Raw Data'!$F$2:$F$251,B22) -> 24 | H22: ='Sales Analysis'!A37 -> Laptop | I22: ='Sales Analysis'!B37 -> 67499.25 | J22: ='Sales Analysis'!D37 -> 75 | K22: =RANK(I22,$I$22:$I$31,0)+COUNTIF($I$22:I22,I22)-1 -> 1
A23: 2 | B23: =INDEX($H$22:$H$31,MATCH($A23,$K$22:$K$31,0)) -> Smartphone | C23: =INDEX($I$22:$I$31,MATCH($A23,$K$22:$K$31,0)) -> 67199.04 | D23: =INDEX($J$22:$J$31,MATCH($A23,$K$22:$K$31,0)) -> 96 | E23: =COUNTIF('Raw Data'!$F$2:$F$251,B23) -> 31 | H23: ='Sales Analysis'!A38 -> Smartphone | I23: ='Sales Analysis'!B38 -> 67199.04 | J23: ='Sales Analysis'!D38 -> 96 | K23: =RANK(I23,$I$22:$I$31,0)+COUNTIF($I$22:I23,I23)-1 -> 2
A24: 3 | B24: =INDEX($H$22:$H$31,MATCH($A24,$K$22:$K$31,0)) -> Desk | C24: =INDEX($I$22:$I$31,MATCH($A24,$K$22:$K$31,0)) -> 23399.22 | D24: =INDEX($J$22:$J$31,MATCH($A24,$K$22:$K$31,0)) -> 78 | E24: =COUNTIF('Raw Data'!$F$2:$F$251,B24) -> 26 | H24: ='Sales Analysis'!A39 -> Headphones | I24: ='Sales Analysis'!B39 -> 7049.53 | J24: ='Sales Analysis'!D39 -> 47 | K24: =RANK(I24,$I$22:$I$31,0)+COUNTIF($I$22:I24,I24)-1 -> 8
A25: 4 | B25: =INDEX($H$22:$H$31,MATCH($A25,$K$22:$K$31,0)) -> Monitor | C25: =INDEX($I$22:$I$31,MATCH($A25,$K$22:$K$31,0)) -> 21999.12 | D25: =INDEX($J$22:$J$31,MATCH($A25,$K$22:$K$31,0)) -> 88 | E25: =COUNTIF('Raw Data'!$F$2:$F$251,B25) -> 26 | H25: ='Sales Analysis'!A40 -> Coffee Maker | I25: ='Sales Analysis'!B40 -> 3119.61 | J25: ='Sales Analysis'!D40 -> 39 | K25: =RANK(I25,$I$22:$I$31,0)+COUNTIF($I$22:I25,I25)-1 -> 10
A26: 5 | B26: =INDEX($H$22:$H$31,MATCH($A26,$K$22:$K$31,0)) -> Bookshelf | C26: =INDEX($I$22:$I$31,MATCH($A26,$K$22:$K$31,0)) -> 15298.98 | D26: =INDEX($J$22:$J$31,MATCH($A26,$K$22:$K$31,0)) -> 102 | E26: =COUNTIF('Raw Data'!$F$2:$F$251,B26) -> 35 | H26: ='Sales Analysis'!A41 -> Blender | I26: ='Sales Analysis'!B41 -> 5219.13 | J26: ='Sales Analysis'!D41 -> 87 | K26: =RANK(I26,$I$22:$I$31,0)+COUNTIF($I$22:I26,I26)-1 -> 9
A27: 6 | B27: =INDEX($H$22:$H$31,MATCH($A27,$K$22:$K$31,0)) -> Office Chair | C27: =INDEX($I$22:$I$31,MATCH($A27,$K$22:$K$31,0)) -> 10399.48 | D27: =INDEX($J$22:$J$31,MATCH($A27,$K$22:$K$31,0)) -> 52 | E27: =COUNTIF('Raw Data'!$F$2:$F$251,B27) -> 15 | H27: ='Sales Analysis'!A42 -> Office Chair | I27: ='Sales Analysis'!B42 -> 10399.48 | J27: ='Sales Analysis'!D42 -> 52 | K27: =RANK(I27,$I$22:$I$31,0)+COUNTIF($I$22:I27,I27)-1 -> 6
A28: 7 | B28: =INDEX($H$22:$H$31,MATCH($A28,$K$22:$K$31,0)) -> Keyboard | C28: =INDEX($I$22:$I$31,MATCH($A28,$K$22:$K$31,0)) -> 8009.11 | D28: =INDEX($J$22:$J$31,MATCH($A28,$K$22:$K$31,0)) -> 89 | E28: =COUNTIF('Raw Data'!$F$2:$F$251,B28) -> 34 | H28: ='Sales Analysis'!A43 -> Desk | I28: ='Sales Analysis'!B43 -> 23399.22 | J28: ='Sales Analysis'!D43 -> 78 | K28: =RANK(I28,$I$22:$I$31,0)+COUNTIF($I$22:I28,I28)-1 -> 3
A29: 8 | B29: =INDEX($H$22:$H$31,MATCH($A29,$K$22:$K$31,0)) -> Headphones | C29: =INDEX($I$22:$I$31,MATCH($A29,$K$22:$K$31,0)) -> 7049.53 | D29: =INDEX($J$22:$J$31,MATCH($A29,$K$22:$K$31,0)) -> 47 | E29: =COUNTIF('Raw Data'!$F$2:$F$251,B29) -> 16 | H29: ='Sales Analysis'!A44 -> Bookshelf | I29: ='Sales Analysis'!B44 -> 15298.98 | J29: ='Sales Analysis'!D44 -> 102 | K29: =RANK(I29,$I$22:$I$31,0)+COUNTIF($I$22:I29,I29)-1 -> 5
A30: 9 | B30: =INDEX($H$22:$H$31,MATCH($A30,$K$22:$K$31,0)) -> Blender | C30: =INDEX($I$22:$I$31,MATCH($A30,$K$22:$K$31,0)) -> 5219.13 | D30: =INDEX($J$22:$J$31,MATCH($A30,$K$22:$K$31,0)) -> 87 | E30: =COUNTIF('Raw Data'!$F$2:$F$251,B30) -> 29 | H30: ='Sales Analysis'!A45 -> Monitor | I30: ='Sales Analysis'!B45 -> 21999.12 | J30: ='Sales Analysis'!D45 -> 88 | K30: =RANK(I30,$I$22:$I$31,0)+COUNTIF($I$22:I30,I30)-1 -> 4
A31: 10 | B31: =INDEX($H$22:$H$31,MATCH($A31,$K$22:$K$31,0)) -> Coffee Maker | C31: =INDEX($I$22:$I$31,MATCH($A31,$K$22:$K$31,0)) -> 3119.61 | D31: =INDEX($J$22:$J$31,MATCH($A31,$K$22:$K$31,0)) -> 39 | E31: =COUNTIF('Raw Data'!$F$2:$F$251,B31) -> 14 | H31: ='Sales Analysis'!A46 -> Keyboard | I31: ='Sales Analysis'!B46 -> 8009.11 | J31: ='Sales Analysis'!D46 -> 89 | K31: =RANK(I31,$I$22:$I$31,0)+COUNTIF($I$22:I31,I31)-1 -> 7
A33: 3. Revenue by Region x Category
A34: Region | B34: ='Sales Analysis'!$A$15 -> Appliances | C34: ='Sales Analysis'!$A$16 -> Electronics | D34: ='Sales Analysis'!$A$17 -> Furniture
A35: ='Sales Analysis'!$A$6 -> Central | B35: =SUMIFS('Raw Data'!$N$2:$N$251,'Raw Data'!$K$2:$K$251,$A35,'Raw Data'!$G$2:$G$251,B$34) -> 1999.71 | C35: =SUMIFS('Raw Data'!$N$2:$N$251,'Raw Data'!$K$2:$K$251,$A35,'Raw Data'!$G$2:$G$251,C$34) -> 24889.33 | D35: =SUMIFS('Raw Data'!$N$2:$N$251,'Raw Data'!$K$2:$K$251,$A35,'Raw Data'!$G$2:$G$251,D$34) -> 14399.3
A36: ='Sales Analysis'!$A$7 -> East | B36: =SUMIFS('Raw Data'!$N$2:$N$251,'Raw Data'!$K$2:$K$251,$A36,'Raw Data'!$G$2:$G$251,B$34) -> 2239.67 | C36: =SUMIFS('Raw Data'!$N$2:$N$251,'Raw Data'!$K$2:$K$251,$A36,'Raw Data'!$G$2:$G$251,C$34) -> 50649.01 | D36: =SUMIFS('Raw Data'!$N$2:$N$251,'Raw Data'!$K$2:$K$251,$A36,'Raw Data'!$G$2:$G$251,D$34) -> 6399.71
A37: ='Sales Analysis'!$A$8 -> North | B37: =SUMIFS('Raw Data'!$N$2:$N$251,'Raw Data'!$K$2:$K$251,$A37,'Raw Data'!$G$2:$G$251,B$34) -> 1119.84 | C37: =SUMIFS('Raw Data'!$N$2:$N$251,'Raw Data'!$K$2:$K$251,$A37,'Raw Data'!$G$2:$G$251,C$34) -> 39239.04 | D37: =SUMIFS('Raw Data'!$N$2:$N$251,'Raw Data'!$K$2:$K$251,$A37,'Raw Data'!$G$2:$G$251,D$34) -> 10449.43
A38: ='Sales Analysis'!$A$9 -> South | B38: =SUMIFS('Raw Data'!$N$2:$N$251,'Raw Data'!$K$2:$K$251,$A38,'Raw Data'!$G$2:$G$251,B$34) -> 1099.83 | C38: =SUMIFS('Raw Data'!$N$2:$N$251,'Raw Data'!$K$2:$K$251,$A38,'Raw Data'!$G$2:$G$251,C$34) -> 25549.32 | D38: =SUMIFS('Raw Data'!$N$2:$N$251,'Raw Data'!$K$2:$K$251,$A38,'Raw Data'!$G$2:$G$251,D$34) -> 9749.6
A39: ='Sales Analysis'!$A$10 -> West | B39: =SUMIFS('Raw Data'!$N$2:$N$251,'Raw Data'!$K$2:$K$251,$A39,'Raw Data'!$G$2:$G$251,B$34) -> 1879.69 | C39: =SUMIFS('Raw Data'!$N$2:$N$251,'Raw Data'!$K$2:$K$251,$A39,'Raw Data'!$G$2:$G$251,C$34) -> 31429.35 | D39: =SUMIFS('Raw Data'!$N$2:$N$251,'Raw Data'!$K$2:$K$251,$A39,'Raw Data'!$G$2:$G$251,D$34) -> 8099.64
A43: 4. Region revenue and average order value
A44: Region | B44: Revenue | C44: Avg Order Value | D44: Orders
A45: ='Sales Analysis'!A6 -> Central | B45: ='Sales Analysis'!B6 -> 41288.34 | C45: ='Sales Analysis'!E6 -> 764.59889 | D45: ='Sales Analysis'!C6 -> 54
A46: ='Sales Analysis'!A7 -> East | B46: ='Sales Analysis'!B7 -> 59288.39 | C46: ='Sales Analysis'!E7 -> 1235.1748 | D46: ='Sales Analysis'!C7 -> 48
A47: ='Sales Analysis'!A8 -> North | B47: ='Sales Analysis'!B8 -> 50808.31 | C47: ='Sales Analysis'!E8 -> 861.1578 | D47: ='Sales Analysis'!C8 -> 59
A48: ='Sales Analysis'!A9 -> South | B48: ='Sales Analysis'!B9 -> 36398.75 | C48: ='Sales Analysis'!E9 -> 866.6369 | D48: ='Sales Analysis'!C9 -> 42
A49: ='Sales Analysis'!A10 -> West | B49: ='Sales Analysis'!B10 -> 41408.68 | C49: ='Sales Analysis'!E10 -> 881.03574 | D49: ='Sales Analysis'!C10 -> 47
A52: 5. Revenue by Region x Payment Method
A53: Region | B53: ='Sales Analysis'!$A$22 -> Cash | C53: ='Sales Analysis'!$A$23 -> Credit Card | D53: ='Sales Analysis'!$A$24 -> Debit Card | E53: ='Sales Analysis'!$A$25 -> PayPal
A54: ='Sales Analysis'!$A$6 -> Central | B54: =SUMIFS('Raw Data'!$N$2:$N$251,'Raw Data'!$K$2:$K$251,$A54,'Raw Data'!$J$2:$J$251,B$53) -> 13919.47 | C54: =SUMIFS('Raw Data'!$N$2:$N$251,'Raw Data'!$K$2:$K$251,$A54,'Raw Data'!$J$2:$J$251,C$53) -> 10869.59 | D54: =SUMIFS('Raw Data'!$N$2:$N$251,'Raw Data'!$K$2:$K$251,$A54,'Raw Data'!$J$2:$J$251,D$53) -> 8669.63 | E54: =SUMIFS('Raw Data'!$N$2:$N$251,'Raw Data'!$K$2:$K$251,$A54,'Raw Data'!$J$2:$J$251,E$53) -> 7829.65
A55: ='Sales Analysis'!$A$7 -> East | B55: =SUMIFS('Raw Data'!$N$2:$N$251,'Raw Data'!$K$2:$K$251,$A55,'Raw Data'!$J$2:$J$251,B$53) -> 11809.7 | C55: =SUMIFS('Raw Data'!$N$2:$N$251,'Raw Data'!$K$2:$K$251,$A55,'Raw Data'!$J$2:$J$251,C$53) -> 10099.71 | D55: =SUMIFS('Raw Data'!$N$2:$N$251,'Raw Data'!$K$2:$K$251,$A55,'Raw Data'!$J$2:$J$251,D$53) -> 18159.46 | E55: =SUMIFS('Raw Data'!$N$2:$N$251,'Raw Data'!$K$2:$K$251,$A55,'Raw Data'!$J$2:$J$251,E$53) -> 19219.52
A56: ='Sales Analysis'!$A$8 -> North | B56: =SUMIFS('Raw Data'!$N$2:$N$251,'Raw Data'!$K$2:$K$251,$A56,'Raw Data'!$J$2:$J$251,B$53) -> 16839.37 | C56: =SUMIFS('Raw Data'!$N$2:$N$251,'Raw Data'!$K$2:$K$251,$A56,'Raw Data'!$J$2:$J$251,C$53) -> 16649.44 | D56: =SUMIFS('Raw Data'!$N$2:$N$251,'Raw Data'!$K$2:$K$251,$A56,'Raw Data'!$J$2:$J$251,D$53) -> 6819.72 | E56: =SUMIFS('Raw Data'!$N$2:$N$251,'Raw Data'!$K$2:$K$251,$A56,'Raw Data'!$J$2:$J$251,E$53) -> 10499.78
A57: ='Sales Analysis'!$A$9 -> South | B57: =SUMIFS('Raw Data'!$N$2:$N$251,'Raw Data'!$K$2:$K$251,$A57,'Raw Data'!$J$2:$J$251,B$53) -> 5369.7 | C57: =SUMIFS('Raw Data'!$N$2:$N$251,'Raw Data'!$K$2:$K$251,$A57,'Raw Data'!$J$2:$J$251,C$53) -> 11549.62 | D57: =SUMIFS('Raw Data'!$N$2:$N$251,'Raw Data'!$K$2:$K$251,$A57,'Raw Data'!$J$2:$J$251,D$53) -> 10669.68 | E57: =SUMIFS('Raw Data'!$N$2:$N$251,'Raw Data'!$K$2:$K$251,$A57,'Raw Data'!$J$2:$J$251,E$53) -> 8809.75
A58: ='Sales Analysis'!$A$10 -> West | B58: =SUMIFS('Raw Data'!$N$2:$N$251,'Raw Data'!$K$2:$K$251,$A58,'Raw Data'!$J$2:$J$251,B$53) -> 9489.55 | C58: =SUMIFS('Raw Data'!$N$2:$N$251,'Raw Data'!$K$2:$K$251,$A58,'Raw Data'!$J$2:$J$251,C$53) -> 12279.6 | D58: =SUMIFS('Raw Data'!$N$2:$N$251,'Raw Data'!$K$2:$K$251,$A58,'Raw Data'!$J$2:$J$251,D$53) -> 7799.82 | E58: =SUMIFS('Raw Data'!$N$2:$N$251,'Raw Data'!$K$2:$K$251,$A58,'Raw Data'!$J$2:$J$251,E$53) -> 11839.71
A61: 6. Orders and revenue by weekday
A62: Weekday | B62: Orders | C62: Revenue | D62: Day # (Mon=1)
A63: Mon | B63: =SUMPRODUCT(--(WEEKDAY('Raw Data'!$B$2:$B$251,2)=D63)) -> 38 | C63: =SUMPRODUCT((WEEKDAY('Raw Data'!$B$2:$B$251,2)=D63)*'Raw Data'!$N$2:$N$251) -> 23378.97 | D63: 1
A64: Tue | B64: =SUMPRODUCT(--(WEEKDAY('Raw Data'!$B$2:$B$251,2)=D64)) -> 33 | C64: =SUMPRODUCT((WEEKDAY('Raw Data'!$B$2:$B$251,2)=D64)*'Raw Data'!$N$2:$N$251) -> 35458.99 | D64: 2
