Workbook

Sheet Sheet1
A1: Customer_ID | B1: Customer_Name | C1: Region | D1: Product_Category | E1: Sales | F1: Quantity | G1: Discount | H1: Order_Date | I1: Profit
A2: CUST019 | B2: James Davis | C2: West | D2: Books | E2: 1036.09 | F2: 4 | G2: 0.2 | H2: 45392 | I2: 331.55
A3: CUST012 | B3: Robert Anderson | C3: West | D3: Clothing | E3: 1101.28 | F3: 3 | G3: 0.2 | H3: 45393 | I3: 440.51
A4: CUST017 | B4: James Taylor | C4: East | D4: Books | E4: 713.34 | F4: 17 | G4: 0 | H4: 45396 | I4: 285.34
A5: CUST005 | B5: Robert Anderson | C5: South | D5: Electronics | E5: 760.93 | F5: 4 | G5: 0.15 | H5: 45396 | I5: 161.7
A6: CUST030 | B6: James Wilson | C6: North | D6: Books | E6: 847 | F6: 12 | G6: 0.2 | H6: 45397 | I6: 271.04
A7: CUST007 | B7: Michael Anderson | C7: North | D7: Furniture | E7: 965.64 | F7: 8 | G7: 0.1 | H7: 45398 | I7: 304.18
A8: CUST001 | B8: Linda Wilson | C8: West | D8: Electronics | E8: 1317.53 | F8: 12 | G8: 0.05 | H8: 45398 | I8: 312.91
A9: CUST026 | B9: Mary Davis | C9: East | D9: Furniture | E9: 1074.47 | F9: 6 | G9: 0.2 | H9: 45401 | I9: 300.85
A10: CUST009 | B10: Linda Jackson | C10: Central | D10: Books | E10: 501.54 | F10: 11 | G10: 0.05 | H10: 45401 | I10: 190.59
A11: CUST010 | B11: David Thomas | C11: Central | D11: Clothing | E11: 737.31 | F11: 2 | G11: 0.05 | H11: 45401 | I11: 350.22
A12: CUST014 | B12: Emma Davis | C12: West | D12: Office Supplies | E12: 1572.82 | F12: 6 | G12: 0.05 | H12: 45402 | I12: 672.38
A13: CUST014 | B13: David Thomas | C13: Central | D13: Books | E13: 1343.13 | F13: 14 | G13: 0.15 | H13: 45404 | I13: 456.66
... A201: CUST016 | B201: David Thomas | C201: South | D201: Clothing | E201: 928.32 | F201: 2 | G201: 0.05 | H201: 45754 | I201: 440.95

Sheet Q.1 & Q.7
A1: Customer_ID | B1: Total_Purchase | C1: Orders | D1: Rank | E1: Status
A2: CUST001 | B2: =SUMIFS(Sheet1!$E$2:$E$201,Sheet1!$A$2:$A$201,A2) -> 6549.55 | C2: =COUNTIF([1]Sheet1!$A$2:$A$201,A2) -> 7 | D2: =RANK(B2,$B$2:$B$31) -> 15 | E2: =IF(B2>=$H$2,"High Value","Regular") -> High Value
A3: CUST002 | B3: =SUMIFS(Sheet1!$E$2:$E$201,Sheet1!$A$2:$A$201,A3) -> 6481.43 | C3: =COUNTIF([1]Sheet1!$A$2:$A$201,A3) -> 6 | D3: =RANK(B3,$B$2:$B$31) -> 17 | E3: =IF(B3>=$H$2,"High Value","Regular") -> High Value
A4: CUST003 | B4: =SUMIFS(Sheet1!$E$2:$E$201,Sheet1!$A$2:$A$201,A4) -> 8490.18 | C4: =COUNTIF([1]Sheet1!$A$2:$A$201,A4) -> 9 | D4: =RANK(B4,$B$2:$B$31) -> 7 | E4: =IF(B4>=$H$2,"High Value","Regular") -> High Value | H4: Task 7 – High-value settings
A5: CUST004 | B5: =SUMIFS(Sheet1!$E$2:$E$201,Sheet1!$A$2:$A$201,A5) -> 7813.59 | C5: =COUNTIF([1]Sheet1!$A$2:$A$201,A5) -> 7 | D5: =RANK(B5,$B$2:$B$31) -> 10 | E5: =IF(B5>=$H$2,"High Value","Regular") -> High Value | H5: High Value Limit (≥) | I5: 8000
A6: CUST005 | B6: =SUMIFS(Sheet1!$E$2:$E$201,Sheet1!$A$2:$A$201,A6) -> 6666.13 | C6: =COUNTIF([1]Sheet1!$A$2:$A$201,A6) -> 6 | D6: =RANK(B6,$B$2:$B$31) -> 14 | E6: =IF(B6>=$H$2,"High Value","Regular") -> High Value
A7: CUST006 | B7: =SUMIFS(Sheet1!$E$2:$E$201,Sheet1!$A$2:$A$201,A7) -> 2699.75 | C7: =COUNTIF([1]Sheet1!$A$2:$A$201,A7) -> 2 | D7: =RANK(B7,$B$2:$B$31) -> 30 | E7: =IF(B7>=$H$2,"High Value","Regular") -> High Value | H7: INDEX/MATCH lookup
A8: CUST007 | B8: =SUMIFS(Sheet1!$E$2:$E$201,Sheet1!$A$2:$A$201,A8) -> 9941.88 | C8: =COUNTIF([1]Sheet1!$A$2:$A$201,A8) -> 10 | D8: =RANK(B8,$B$2:$B$31) -> 3 | E8: =IF(B8>=$H$2,"High Value","Regular") -> High Value | H8: Customer ID | I8: CUST015
A9: CUST008 | B9: =SUMIFS(Sheet1!$E$2:$E$201,Sheet1!$A$2:$A$201,A9) -> 9760.8 | C9: =COUNTIF([1]Sheet1!$A$2:$A$201,A9) -> 10 | D9: =RANK(B9,$B$2:$B$31) -> 4 | E9: =IF(B9>=$H$2,"High Value","Regular") -> High Value | H9: Total Purchase | I9: =INDEX($B$2:$B$31,MATCH(I8,$A$2:$A$31,0)) -> 11611.06
A10: CUST009 | B10: =SUMIFS(Sheet1!$E$2:$E$201,Sheet1!$A$2:$A$201,A10) -> 6505.2 | C10: =COUNTIF([1]Sheet1!$A$2:$A$201,A10) -> 7 | D10: =RANK(B10,$B$2:$B$31) -> 16 | E10: =IF(B10>=$H$2,"High Value","Regular") -> High Value | H10: Rank | I10: =INDEX($D$2:$D$31,MATCH(I8,$A$2:$A$31,0)) -> 1
A11: CUST010 | B11: =SUMIFS(Sheet1!$E$2:$E$201,Sheet1!$A$2:$A$201,A11) -> 4259.22 | C11: =COUNTIF([1]Sheet1!$A$2:$A$201,A11) -> 5 | D11: =RANK(B11,$B$2:$B$31) -> 24 | E11: =IF(B11>=$H$2,"High Value","Regular") -> High Value | H11: Status | I11: =INDEX($E$2:$E$31,MATCH(I8,$A$2:$A$31,0)) -> High Value
A12: CUST011 | B12: =SUMIFS(Sheet1!$E$2:$E$201,Sheet1!$A$2:$A$201,A12) -> 3762.29 | C12: =COUNTIF([1]Sheet1!$A$2:$A$201,A12) -> 4 | D12: =RANK(B12,$B$2:$B$31) -> 27 | E12: =IF(B12>=$H$2,"High Value","Regular") -> High Value
A13: CUST012 | B13: =SUMIFS(Sheet1!$E$2:$E$201,Sheet1!$A$2:$A$201,A13) -> 8339 | C13: =COUNTIF([1]Sheet1!$A$2:$A$201,A13) -> 9 | D13: =RANK(B13,$B$2:$B$31) -> 8 | E13: =IF(B13>=$H$2,"High Value","Regular") -> High Value | H13: High-value customer list (auto, via LARGE + INDEX + MATCH)
A14: CUST013 | B14: =SUMIFS(Sheet1!$E$2:$E$201,Sheet1!$A$2:$A$201,A14) -> 4162.44 | C14: =COUNTIF([1]Sheet1!$A$2:$A$201,A14) -> 4 | D14: =RANK(B14,$B$2:$B$31) -> 25 | E14: =IF(B14>=$H$2,"High Value","Regular") -> High Value | H14: Rank | I14: Customer_ID | J14: Total_Purchase
A15: CUST014 | B15: =SUMIFS(Sheet1!$E$2:$E$201,Sheet1!$A$2:$A$201,A15) -> 6729.89 | C15: =COUNTIF([1]Sheet1!$A$2:$A$201,A15) -> 6 | D15: =RANK(B15,$B$2:$B$31) -> 12 | E15: =IF(B15>=$H$2,"High Value","Regular") -> High Value | H15: 1 | I15: =IF(J15="","",INDEX($A$2:$A$31,MATCH(J15,$B$2:$B$31,0))) -> CUST015 | J15: =IF(LARGE($B$2:$B$31,H15)>=$H$2,LARGE($B$2:$B$31,H15),"") -> 11611.06
A16: CUST015 | B16: =SUMIFS(Sheet1!$E$2:$E$201,Sheet1!$A$2:$A$201,A16) -> 11611.06 | C16: =COUNTIF([1]Sheet1!$A$2:$A$201,A16) -> 11 | D16: =RANK(B16,$B$2:$B$31) -> 1 | E16: =IF(B16>=$H$2,"High Value","Regular") -> High Value | H16: 2 | I16: =IF(J16="","",INDEX($A$2:$A$31,MATCH(J16,$B$2:$B$31,0))) -> CUST028 | J16: =IF(LARGE($B$2:$B$31,H16)>=$H$2,LARGE($B$2:$B$31,H16),"") -> 10293.87
A17: CUST016 | B17: =SUMIFS(Sheet1!$E$2:$E$201,Sheet1!$A$2:$A$201,A17) -> 3369.17 | C17: =COUNTIF([1]Sheet1!$A$2:$A$201,A17) -> 4 | D17: =RANK(B17,$B$2:$B$31) -> 29 | E17: =IF(B17>=$H$2,"High Value","Regular") -> High Value | H17: 3 | I17: =IF(J17="","",INDEX($A$2:$A$31,MATCH(J17,$B$2:$B$31,0))) -> CUST007 | J17: =IF(LARGE($B$2:$B$31,H17)>=$H$2,LARGE($B$2:$B$31,H17),"") -> 9941.88
A18: CUST017 | B18: =SUMIFS(Sheet1!$E$2:$E$201,Sheet1!$A$2:$A$201,A18) -> 3419.2 | C18: =COUNTIF([1]Sheet1!$A$2:$A$201,A18) -> 4 | D18: =RANK(B18,$B$2:$B$31) -> 28 | E18: =IF(B18>=$H$2,"High Value","Regular") -> High Value | H18: 4 | I18: =IF(J18="","",INDEX($A$2:$A$31,MATCH(J18,$B$2:$B$31,0))) -> CUST008 | J18: =IF(LARGE($B$2:$B$31,H18)>=$H$2,LARGE($B$2:$B$31,H18),"") -> 9760.8
A19: CUST018 | B19: =SUMIFS(Sheet1!$E$2:$E$201,Sheet1!$A$2:$A$201,A19) -> 4951.89 | C19: =COUNTIF([1]Sheet1!$A$2:$A$201,A19) -> 5 | D19: =RANK(B19,$B$2:$B$31) -> 20 | E19: =IF(B19>=$H$2,"High Value","Regular") -> High Value | H19: 5 | I19: =IF(J19="","",INDEX($A$2:$A$31,MATCH(J19,$B$2:$B$31,0))) -> CUST026 | J19: =IF(LARGE($B$2:$B$31,H19)>=$H$2,LARGE($B$2:$B$31,H19),"") -> 9371.81
A20: CUST019 | B20: =SUMIFS(Sheet1!$E$2:$E$201,Sheet1!$A$2:$A$201,A20) -> 4640.11 | C20: =COUNTIF([1]Sheet1!$A$2:$A$201,A20) -> 5 | D20: =RANK(B20,$B$2:$B$31) -> 21 | E20: =IF(B20>=$H$2,"High Value","Regular") -> High Value | H20: 6 | I20: =IF(J20="","",INDEX($A$2:$A$31,MATCH(J20,$B$2:$B$31,0))) -> CUST021 | J20: =IF(LARGE($B$2:$B$31,H20)>=$H$2,LARGE($B$2:$B$31,H20),"") -> 8740.18
A21: CUST020 | B21: =SUMIFS(Sheet1!$E$2:$E$201,Sheet1!$A$2:$A$201,A21) -> 4413.71 | C21: =COUNTIF([1]Sheet1!$A$2:$A$201,A21) -> 4 | D21: =RANK(B21,$B$2:$B$31) -> 23 | E21: =IF(B21>=$H$2,"High Value","Regular") -> High Value | H21: 7 | I21: =IF(J21="","",INDEX($A$2:$A$31,MATCH(J21,$B$2:$B$31,0))) -> CUST003 | J21: =IF(LARGE($B$2:$B$31,H21)>=$H$2,LARGE($B$2:$B$31,H21),"") -> 8490.18
A22: CUST021 | B22: =SUMIFS(Sheet1!$E$2:$E$201,Sheet1!$A$2:$A$201,A22) -> 8740.18 | C22: =COUNTIF([1]Sheet1!$A$2:$A$201,A22) -> 8 | D22: =RANK(B22,$B$2:$B$31) -> 6 | E22: =IF(B22>=$H$2,"High Value","Regular") -> High Value | H22: 8 | I22: =IF(J22="","",INDEX($A$2:$A$31,MATCH(J22,$B$2:$B$31,0))) -> CUST012 | J22: =IF(LARGE($B$2:$B$31,H22)>=$H$2,LARGE($B$2:$B$31,H22),"") -> 8339
A23: CUST022 | B23: =SUMIFS(Sheet1!$E$2:$E$201,Sheet1!$A$2:$A$201,A23) -> 4418.28 | C23: =COUNTIF([1]Sheet1!$A$2:$A$201,A23) -> 5 | D23: =RANK(B23,$B$2:$B$31) -> 22 | E23: =IF(B23>=$H$2,"High Value","Regular") -> High Value | H23: 9 | I23: =IF(J23="","",INDEX($A$2:$A$31,MATCH(J23,$B$2:$B$31,0))) -> CUST030 | J23: =IF(LARGE($B$2:$B$31,H23)>=$H$2,LARGE($B$2:$B$31,H23),"") -> 7928.71
A24: CUST023 | B24: =SUMIFS(Sheet1!$E$2:$E$201,Sheet1!$A$2:$A$201,A24) -> 5913.68 | C24: =COUNTIF([1]Sheet1!$A$2:$A$201,A24) -> 7 | D24: =RANK(B24,$B$2:$B$31) -> 18 | E24: =IF(B24>=$H$2,"High Value","Regular") -> High Value | H24: 10 | I24: =IF(J24="","",INDEX($A$2:$A$31,MATCH(J24,$B$2:$B$31,0))) -> CUST004 | J24: =IF(LARGE($B$2:$B$31,H24)>=$H$2,LARGE($B$2:$B$31,H24),"") -> 7813.59
A25: CUST024 | B25: =SUMIFS(Sheet1!$E$2:$E$201,Sheet1!$A$2:$A$201,A25) -> 7583.13 | C25: =COUNTIF([1]Sheet1!$A$2:$A$201,A25) -> 7 | D25: =RANK(B25,$B$2:$B$31) -> 11 | E25: =IF(B25>=$H$2,"High Value","Regular") -> High Value | H25: 11 | I25: =IF(J25="","",INDEX($A$2:$A$31,MATCH(J25,$B$2:$B$31,0))) -> CUST024 | J25: =IF(LARGE($B$2:$B$31,H25)>=$H$2,LARGE($B$2:$B$31,H25),"") -> 7583.13
A26: CUST025 | B26: =SUMIFS(Sheet1!$E$2:$E$201,Sheet1!$A$2:$A$201,A26) -> 6716.52 | C26: =COUNTIF([1]Sheet1!$A$2:$A$201,A26) -> 6 | D26: =RANK(B26,$B$2:$B$31) -> 13 | E26: =IF(B26>=$H$2,"High Value","Regular") -> High Value | H26: 12 | I26: =IF(J26="","",INDEX($A$2:$A$31,MATCH(J26,$B$2:$B$31,0))) -> CUST014 | J26: =IF(LARGE($B$2:$B$31,H26)>=$H$2,LARGE($B$2:$B$31,H26),"") -> 6729.89
A27: CUST026 | B27: =SUMIFS(Sheet1!$E$2:$E$201,Sheet1!$A$2:$A$201,A27) -> 9371.81 | C27: =COUNTIF([1]Sheet1!$A$2:$A$201,A27) -> 9 | D27: =RANK(B27,$B$2:$B$31) -> 5 | E27: =IF(B27>=$H$2,"High Value","Regular") -> High Value
A28: CUST027 | B28: =SUMIFS(Sheet1!$E$2:$E$201,Sheet1!$A$2:$A$201,A28) -> 3906.04 | C28: =COUNTIF([1]Sheet1!$A$2:$A$201,A28) -> 5 | D28: =RANK(B28,$B$2:$B$31) -> 26 | E28: =IF(B28>=$H$2,"High Value","Regular") -> High Value
A29: CUST028 | B29: =SUMIFS(Sheet1!$E$2:$E$201,Sheet1!$A$2:$A$201,A29) -> 10293.87 | C29: =COUNTIF([1]Sheet1!$A$2:$A$201,A29) -> 12 | D29: =RANK(B29,$B$2:$B$31) -> 2 | E29: =IF(B29>=$H$2,"High Value","Regular") -> High Value
A30: CUST029 | B30: =SUMIFS(Sheet1!$E$2:$E$201,Sheet1!$A$2:$A$201,A30) -> 5779.05 | C30: =COUNTIF([1]Sheet1!$A$2:$A$201,A30) -> 7 | D30: =RANK(B30,$B$2:$B$31) -> 19 | E30: =IF(B30>=$H$2,"High Value","Regular") -> High Value
A31: CUST030 | B31: =SUMIFS(Sheet1!$E$2:$E$201,Sheet1!$A$2:$A$201,A31) -> 7928.71 | C31: =COUNTIF([1]Sheet1!$A$2:$A$201,A31) -> 9 | D31: =RANK(B31,$B$2:$B$31) -> 9 | E31: =IF(B31>=$H$2,"High Value","Regular") -> High Value

Sheet Q.2
A1: New Discount (input) | B1: 0.1
A2: Current Total Profit | B2: =SUM(Sheet1!I2:I201) -> 68287.01
A3: Profit at New Discount | B3: {=SUM(Sheet1!$I$2:$I$201)+SUMPRODUCT(Sheet1!$E$2:$E$201/(1-Sheet1!$G$2:$G$201))*(1-B1)-SUM(Sheet1!$E$2:$E$201)} -> 69293.725
A4: Change in Profit | B4: =B3-B2 -> 1006.7146
A5: Current Average Discount | B5: =AVERAGE(Sheet1!G2:G201) -> 0.09725
A8: Discount | B8: Total Sales | C8: Total Profit | D8: Change vs Current | E8: Profit Margin
A9: 0 | B9: =SUMPRODUCT([1]Sheet1!$E$2:$E$201/(1-[1]Sheet1!$G$2:$G$201))*(1-A9) -> 218027.19 | C9: =SUM([1]Sheet1!$I$2:$I$201)+B9-SUM([1]Sheet1!$E$2:$E$201) -> 91096.444 | D9: =C9-$B$2 -> 22809.434 | E9: =C9/B9 -> 0.41782148
A10: 0.05 | B10: =SUMPRODUCT([1]Sheet1!$E$2:$E$201/(1-[1]Sheet1!$G$2:$G$201))*(1-A10) -> 207125.83 | C10: =SUM([1]Sheet1!$I$2:$I$201)+B10-SUM([1]Sheet1!$E$2:$E$201) -> 80195.084 | D10: =C10-$B$2 -> 11908.074 | E10: =C10/B10 -> 0.3871805
A11: 0.1 | B11: =SUMPRODUCT([1]Sheet1!$E$2:$E$201/(1-[1]Sheet1!$G$2:$G$201))*(1-A11) -> 196224.47 | C11: =SUM([1]Sheet1!$I$2:$I$201)+B11-SUM([1]Sheet1!$E$2:$E$201) -> 69293.725 | D11: =C11-$B$2 -> 1006.7146 | E11: =C11/B11 -> 0.35313497
A12: 0.15 | B12: =SUMPRODUCT([1]Sheet1!$E$2:$E$201/(1-[1]Sheet1!$G$2:$G$201))*(1-A12) -> 185323.11 | C12: =SUM([1]Sheet1!$I$2:$I$201)+B12-SUM([1]Sheet1!$E$2:$E$201) -> 58392.365 | D12: =C12-$B$2 -> -9894.6451 | E12: =C12/B12 -> 0.31508409
A13: 0.2 | B13: =SUMPRODUCT([1]Sheet1!$E$2:$E$201/(1-[1]Sheet1!$G$2:$G$201))*(1-A13) -> 174421.76 | C13: =SUM([1]Sheet1!$I$2:$I$201)+B13-SUM([1]Sheet1!$E$2:$E$201) -> 47491.005 | D13: =C13-$B$2 -> -20796.005 | E13: =C13/B13 -> 0.27227684
A14: 0.25 | B14: =SUMPRODUCT([1]Sheet1!$E$2:$E$201/(1-[1]Sheet1!$G$2:$G$201))*(1-A14) -> 163520.4 | C14: =SUM([1]Sheet1!$I$2:$I$201)+B14-SUM([1]Sheet1!$E$2:$E$201) -> 36589.645 | D14: =C14-$B$2 -> -31697.365 | E14: =C14/B14 -> 0.22376197

Sheet Q.3
A1: SUMMARY OUTPUT
A3: Regression Statistics
A4: Multiple R | B4: 0.77340306
A5: R Square | B5: 0.5981523
A6: Adjusted R Square | B6: 0.59612277
A7: Standard Error | B7: 86.281231
A8: Observations | B8: 200
A10: ANOVA
B11: df | C11: SS | D11: MS | E11: F | F11: Significance F
A12: Regression | B12: 1 | C12: 2194058.2 | D12: 2194058.2 | E12: 294.72398 | F12: 4.6269368e-41
A13: Residual | B13: 198 | C13: 1474001.2 | D13: 7444.4507
A14: Total | B14: 199 | C14: 3668059.4
B16: Coefficients | C16: Standard Error | D16: t Stat | E16: P-value | F16: Lower 95% | G16: Upper 95% | H16: Lower 95.0% | I16: Upper 95.0%
A17: Intercept | B17: -1.0315505 | C17: 20.860617 | D17: -0.049449663 | E17: 0.9606108 | F17: -42.169052 | G17: 40.105951 | H17: -42.169052 | I17: 40.105951
A18: Sales | B18: 0.35085599 | C18: 0.020437189 | D18: 17.167527 | E18: 4.6269368e-41 | F18: 0.3105535 | G18: 0.39115848 | H18: 0.3105535 | I18: 0.39115848

Sheet Q.4
A1: Sales | C1: Quantity | E1: Discount | G1: Profit
A3: Mean | B3: 976.0888 | C3: Mean | D3: 9.995 | E3: Mean | F3: 0.09725 | G3: Mean | H3: 341.43505
A4: Standard Error | B4: 21.16185 | C4: Standard Error | D4: 0.39927683 | E4: Standard Error | F4: 0.0051142414 | G4: Standard Error | H4: 9.6001196
A5: Median | B5: 976.72 | C5: Median | D5: 10 | E5: Median | F5: 0.1 | G5: Median | H5: 332.255
A6: Mode | B6: #N/A | C6: Mode | D6: 8 | E6: Mode | F6: 0.2 | G6: Mode | H6: #N/A
A7: Standard Deviation | B7: 299.27376 | C7: Standard Deviation | D7: 5.646627 | E7: Standard Deviation | F7: 0.072326295 | G7: Standard Deviation | H7: 135.76619
A8: Sample Variance | B8: 89564.783 | C8: Sample Variance | D8: 31.884397 | E8: Sample Variance | F8: 0.005231093 | G8: Sample Variance | H8: 18432.459
A9: Kurtosis | B9: -0.088595232 | C9: Kurtosis | D9: -1.2091054 | E9: Kurtosis | F9: -1.3257012 | G9: Kurtosis | H9: 0.26450644
A10: Skewness | B10: 0.14685797 | C10: Skewness | D10: 0.060845864 | E10: Skewness | F10: 0.096827386 | G10: Skewness | H10: 0.57339636
A11: Range | B11: 1665.15 | C11: Range | D11: 18 | E11: Range | F11: 0.2 | G11: Range | H11: 704.83
A12: Minimum | B12: 258.51 | C12: Minimum | D12: 1 | E12: Minimum | F12: 0 | G12: Minimum | H12: 64.63
A13: Maximum | B13: 1923.66 | C13: Maximum | D13: 19 | E13: Maximum | F13: 0.2 | G13: Maximum | H13: 769.46
A14: Sum | B14: 195217.76 | C14: Sum | D14: 1999 | E14: Sum | F14: 19.45 | G14: Sum | H14: 68287.01
A15: Count | B15: 200 | C15: Count | D15: 200 | E15: Count | F15: 200 | G15: Count | H15: 200

Sheet Q.5
A3: Row Labels | B3: Sum of Sales | C3: Month's Sales
A4: 2024 | B4: 145429.36
A5: Apr | B5: 19029.96 | C5: =(B6-B5)/B5 -> -0.027463011
A6: May | B6: 18507.34 | C6: =(B7-B6)/B6 -> 0.090783981
A7: Jun | B7: 20187.51 | C7: =(B8-B7)/B7 -> -0.42493948
A8: Jul | B8: 11609.04 | C8: =(B9-B8)/B8 -> -0.13070331
A9: Aug | B9: 10091.7 | C9: =(B10-B9)/B9 -> 1.0346919
A10: Sep | B10: 20533.5 | C10: =(B11-B10)/B10 -> -0.30770497
A11: Oct | B11: 14215.24 | C11: =(B12-B11)/B11 -> 0.41643968
A12: Nov | B12: 20135.03 | C12: =(B13-B12)/B12 -> -0.44772667
A13: Dec | B13: 11120.04
A14: 2025 | B14: 49788.4
A15: Jan | B15: 14914.65 | C15: =(B15-B13)/B13 -> 0.34124068
A16: Feb | B16: 14006.36 | C16: =(B16-B15)/B15 -> -0.060899183
A17: Mar | B17: 17655.22 | C17: =(B17-B16)/B16 -> 0.26051451
A18: Apr | B18: 3212.17 | C18: =(B18-B17)/B17 -> -0.81806117
A19: Grand Total | B19: 195217.76

Sheet Q.6
A1: Customer_ID | B1: Customer_Name | C1: Region | D1: Product_Category | E1: Sales | F1: Quantity | G1: Discount | H1: Profit | I1: Order_Date | J1: Profit | L1: Timestamp Column
A2: CUST019 | B2: James Davis | C2: West | D2: Books | E2: 1036.09 | F2: 4 | G2: 0.2 | H2: 331.55 | I2: 45392 | J2: 331.55 | L2: =NOW() -> 46310.478
A3: CUST012 | B3: Robert Anderson | C3: West | D3: Clothing | E3: 1101.28 | F3: 3 | G3: 0.2 | H3: 440.51 | I3: 45393 | J3: 440.51 | L3: =NOW() -> 46310.478
A4: CUST017 | B4: James Taylor | C4: East | D4: Books | E4: 713.34 | F4: 17 | G4: 0 | H4: 285.34 | I4: 45396 | J4: 285.34 | L4: =NOW() -> 46310.478
A5: CUST005 | B5: Robert Anderson | C5: South | D5: Electronics | E5: 760.93 | F5: 4 | G5: 0.15 | H5: 161.7 | I5: 45396 | J5: 161.7 | L5: =NOW() -> 46310.478
A6: CUST030 | B6: James Wilson | C6: North | D6: Books | E6: 847 | F6: 12 | G6: 0.2 | H6: 271.04 | I6: 45397 | J6: 271.04 | L6: =NOW() -> 46310.478
A7: CUST007 | B7: Michael Anderson | C7: North | D7: Furniture | E7: 965.64 | F7: 8 | G7: 0.1 | H7: 304.18 | I7: 45398 | J7: 304.18 | L7: =NOW() -> 46310.478
A8: CUST001 | B8: Linda Wilson | C8: West | D8: Electronics | E8: 1317.53 | F8: 12 | G8: 0.05 | H8: 312.91 | I8: 45398 | J8: 312.91 | L8: =NOW() -> 46310.478
A9: CUST026 | B9: Mary Davis | C9: East | D9: Furniture | E9: 1074.47 | F9: 6 | G9: 0.2 | H9: 300.85 | I9: 45401 | J9: 300.85 | L9: =NOW() -> 46310.478
A10: CUST009 | B10: Linda Jackson | C10: Central | D10: Books | E10: 501.54 | F10: 11 | G10: 0.05 | H10: 190.59 | I10: 45401 | J10: 190.59 | L10: =NOW() -> 46310.478
A11: CUST010 | B11: David Thomas | C11: Central | D11: Clothing | E11: 737.31 | F11: 2 | G11: 0.05 | H11: 350.22 | I11: 45401 | J11: 350.22 | L11: =NOW() -> 46310.478
A12: CUST014 | B12: Emma Davis | C12: West | D12: Office Supplies | E12: 1572.82 | F12: 6 | G12: 0.05 | H12: 672.38 | I12: 45402 | J12: 672.38 | L12: =NOW() -> 46310.478
A13: CUST014 | B13: David Thomas | C13: Central | D13: Books | E13: 1343.13 | F13: 14 | G13: 0.15 | H13: 456.66 | I13: 45404 | J13: 456.66 | L13: =NOW() -> 46310.478
... A201: CUST016 | B201: David Thomas | C201: South | D201: Clothing | E201: 928.32 | F201: 2 | G201: 0.05 | H201: 440.95 | I201: 45754 | J201: 440.95 | L201: =NOW() -> 46310.478

Sheet Q.8 & Q.9
A3: Sum of Sales
A4: Row Labels | B4: Books | C4: Clothing | D4: Electronics | E4: Furniture | F4: Office Supplies | G4: Grand Total
A5: Central | B5: 11297.15 | C5: 12200.26 | D5: 6621.24 | E5: 4876.96 | F5: 8472.72 | G5: 43468.33
A6: East | B6: 10391.48 | C6: 2401.45 | D6: 2869.54 | E6: 7592.34 | F6: 8189.22 | G6: 31444.03
A7: North | B7: 8037.01 | C7: 8422.82 | D7: 8191.71 | E7: 6978.08 | F7: 3345.8 | G7: 34975.42
A8: South | B8: 9588.04 | C8: 7465.31 | D8: 11989.07 | E8: 7982.73 | F8: 1554.52 | G8: 38579.67
A9: West | B9: 6691.17 | C9: 10509.43 | D9: 11372.44 | E9: 9182.78 | F9: 5782.32 | G9: 43538.14
A10: Grand Total | B10: 46004.85 | C10: 40999.27 | D10: 41044 | E10: 36612.89 | F10: 27344.58 | G10: 192005.59

Sheet Q.10
A1: SALES & PROFIT DASHBOARD
A3: Total Sales | C3: Total Profit | E3: Profit Margin | G3: Total Orders | I3: Avg Discount | K3: Top Customer
A4: =SUM([1]Sheet1!E2:E201) -> 195217.76 | C4: =SUM([1]Sheet1!I2:I201) -> 68287.01 | E4: =SUM([1]Sheet1!I2:I201)/SUM([1]Sheet1!E2:E201) -> 0.34979917 | G4: =COUNTA([1]Sheet1!A2:A201) -> 200 | I4: =AVERAGE([1]Sheet1!G2:G201) -> 0.09725 | K4: =INDEX([1]Customers!A2:A31,MATCH(MAX([1]Customers!B2:B31),[1]Customers!B2:B31,0)) -> CUST015
G22: Top 5 Customers (by total purchase)
G23: Rank | H23: Customer | J23: Total Purchase
G24: 1 | H24: =INDEX([1]Customers!$A$2:$A$31,MATCH(J24,[1]Customers!$B$2:$B$31,0)) -> CUST015 | J24: =LARGE([1]Customers!$B$2:$B$31,G24) -> 11611.06
G25: 2 | H25: =INDEX([1]Customers!$A$2:$A$31,MATCH(J25,[1]Customers!$B$2:$B$31,0)) -> CUST028 | J25: =LARGE([1]Customers!$B$2:$B$31,G25) -> 10293.87
G26: 3 | H26: =INDEX([1]Customers!$A$2:$A$31,MATCH(J26,[1]Customers!$B$2:$B$31,0)) -> CUST007 | J26: =LARGE([1]Customers!$B$2:$B$31,G26) -> 9941.88
G27: 4 | H27: =INDEX([1]Customers!$A$2:$A$31,MATCH(J27,[1]Customers!$B$2:$B$31,0)) -> CUST008 | J27: =LARGE([1]Customers!$B$2:$B$31,G27) -> 9760.8
G28: 5 | H28: =INDEX([1]Customers!$A$2:$A$31,MATCH(J28,[1]Customers!$B$2:$B$31,0)) -> CUST026 | J28: =LARGE([1]Customers!$B$2:$B$31,G28) -> 9371.81
A38: KEY INSIGHTS (update automatically)
A39: ="• Top customer is "&K4&" with total purchases of "&TEXT(MAX([1]Customers!B2:B31),"#,##0")&"; "&COUNTIF([1]Customers!E2:E31,"High Value")&" customers are High Value (≥ "&TEXT([1]Customers!H2,"#,##0")&")." -> • Top customer is CUST015 with total purchases of 11,611; 8 customers are High Value (≥ 8,000).
A40: ="• Best region: "&INDEX(A51:A55,MATCH(MAX(B51:B55),B51:B55,0))&" ("&TEXT(MAX(B51:B55),"#,##0")&"); weakest: "&INDEX(A51:A55,MATCH(MIN(B51:B55),B51:B55,0))&" ("&TEXT(MIN(B51:B55),"#,##0")&")." -> • Best region: West (44,084); weakest: East (32,442).
A41: ="• Best category: "&INDEX(D51:D55,MATCH(MAX(E51:E55),E51:E55,0))&" ("&TEXT(MAX(E51:E55)/SUM(E51:E55),"0%")&" of sales); weakest: "&INDEX(D51:D55,MATCH(MIN(E51:E55),E51:E55,0))&"." -> • Best category: Books (24% of sales); weakest: Office Supplies.
A42: ="• Peak month: "&TEXT(INDEX([1]Monthly!A2:A13,MATCH(MAX([1]Monthly!B2:B13),[1]Monthly!B2:B13,0)),"mmm-yyyy")&"; lowest full month: "&TEXT(INDEX([1]Monthly!A2:A13,MATCH(MIN([1]Monthly!B2:B13),[1]Monthly!B2:B13,0)),"mmm-yyyy")&" (Apr-25 excluded, partial)." -> • Peak month: Sep-2024; lowest full month: Aug-2024 (Apr-25 excluded, partial).
A43: ="• Regression: each extra 1 of Sales adds about "&TEXT([1]Regression!B20,"0.000")&" Profit (R² = "&TEXT([1]Regression!B7,"0.00")&"), so higher sales strongly drive profit." -> • Regression: each extra 1 of Sales adds about 0.351 Profit (R² = 0.60), so higher sales strongly drive profit.
A44: ="• What-If: cutting average discount to 0% would give profit of "&TEXT([1]WhatIf!C8,"#,##0")&" vs "&TEXT([1]WhatIf!B2,"#,##0")&" today (volume held constant)." -> • What-If: cutting average discount to 0% would give profit of 91,096 vs 68,287 today (volume held constant).
A49: Chart data (linked to other sheets)
A50: Region | B50: Sales | D50: Category | E50: Sales
A51: =[1]Pivot_Analysis!A4 -> Central | B51: =[1]Pivot_Analysis!G4 -> 43468.33 | D51: =[1]Pivot_Analysis!B3 -> Books | E51: =[1]Pivot_Analysis!B9 -> 47002.46
A52: =[1]Pivot_Analysis!A5 -> East | B52: =[1]Pivot_Analysis!G5 -> 32441.64 | D52: =[1]Pivot_Analysis!C3 -> Clothing | E52: =[1]Pivot_Analysis!C9 -> 41927.59
A53: =[1]Pivot_Analysis!A6 -> North | B53: =[1]Pivot_Analysis!G6 -> 34975.42 | D53: =[1]Pivot_Analysis!D3 -> Electronics | E53: =[1]Pivot_Analysis!D9 -> 41044
A54: =[1]Pivot_Analysis!A7 -> South | B54: =[1]Pivot_Analysis!G7 -> 40248.79 | D54: =[1]Pivot_Analysis!E3 -> Furniture | E54: =[1]Pivot_Analysis!E9 -> 36612.89
A55: =[1]Pivot_Analysis!A8 -> West | B55: =[1]Pivot_Analysis!G8 -> 44083.58 | D55: =[1]Pivot_Analysis!F3 -> Office Supplies | E55: =[1]Pivot_Analysis!F9 -> 28630.82
